Workbook

Sheet dados_solicitacoes
A1: Número da Solicitação | B1: Orgão | C1: Unidade gestora | D1: Tipo da solicitação | E1: Número da ata | F1: Objeto | G1: Núcleo Pertencente | H1: Data da solicitação | I1: Situação do Processo | J1: Situação Atual | K1: Andamento no PE Integrado | L1: Comparação | M1: Responsável | N1: Andamento SEI | O1: Encaminhado / Setor | P1: SEI | Q1: Status da Coluna M
A2: C.002-ARP.0080.00.2025.GOV.FES-PE.PE | B2: =IFERROR(__xludf.DUMMYFUNCTION("REGEXEXTRACT(A2, ""\.(?:GOV|EXT)\.([A-Z0-9\-]+)"") "),"FES-PE") -> FES-PE | C2: HOSPITAL REGIONAL DO AGRESTE DR.WALDEMIRO FERREIRA | D2: Adesão | E2: =IFERROR(__xludf.DUMMYFUNCTION("REGEXEXTRACT(A2, ""-(.*)"")"),"ARP.0080.00.2025.GOV.FES-PE.PE") -> ARP.0080.00.2025.GOV.FES-PE.PE | F2: Formação de Registro de Preços para o fornecimento eventual de MEDICAMENTOS INJETÁVEIS VOL. 1 visando atender as necessidades do Hospital Jaboatão Prazeres. | G2: NFOCPO | H2: 45933 | I2: Cancelada | J2: =VLOOKUP(A2,'TODOS OS PROCESSOS ATUALIZADOS '!A:I,7,0) -> Cancelada | K2: Cancelado | L2: =IFERROR(IF(J2=I2, "Item não atualizado", "Item atualizado"), "Item não localizado") -> Item não atualizado | N2: Cancelado | O2: SEI não localizado
A3: A.031-ARP.0001.01.2025.GOV.HUOC.PE | B3: =IFERROR(__xludf.DUMMYFUNCTION("REGEXEXTRACT(A3, ""\.(?:GOV|EXT)\.([A-Z0-9\-]+)"") "),"HUOC") -> HUOC | C3: HOSPITAL REGIONAL DO AGRESTE DR.WALDEMIRO FERREIRA | D3: Adesão | E3: =IFERROR(__xludf.DUMMYFUNCTION("REGEXEXTRACT(A3, ""-(.*)"")"),"ARP.0001.01.2025.GOV.HUOC.PE") -> ARP.0001.01.2025.GOV.HUOC.PE | F3: Registro de Preços para o fornecimento eventual de MEDICAMENTOS CONTROLADOS, CLÍNICOS RESPIRATÓRIOS E MANIPULADOS (SEI Nº 0040609437.000157/2024-48) | G3: NFOCPO | H3: 45943 | I3: Cancelada | J3: =VLOOKUP(A3,'TODOS OS PROCESSOS ATUALIZADOS '!A:I,7,0) -> Em configuração | K3: Cancelar Com o Suporte | L3: =IFERROR(IF(J3=I3, "Item não atualizado", "Item atualizado"), "Item não localizado") -> Item atualizado | N3: Cancelar Com o Suporte | O3: SEI não localizado
A4: A.029-ARP.0001.01.2025.GOV.HUOC.PE | B4: =IFERROR(__xludf.DUMMYFUNCTION("REGEXEXTRACT(A4, ""\.(?:GOV|EXT)\.([A-Z0-9\-]+)"") "),"HUOC") -> HUOC | C4: HOSPITAL REGIONAL DO AGRESTE DR.WALDEMIRO FERREIRA | D4: Adesão | E4: =IFERROR(__xludf.DUMMYFUNCTION("REGEXEXTRACT(A4, ""-(.*)"")"),"ARP.0001.01.2025.GOV.HUOC.PE") -> ARP.0001.01.2025.GOV.HUOC.PE | F4: Registro de Preços para o fornecimento eventual de MEDICAMENTOS CONTROLADOS, CLÍNICOS RESPIRATÓRIOS E MANIPULADOS (SEI Nº 0040609437.000157/2024-48) | G4: NFOCPO | H4: 45933 | I4: Concluído | J4: =VLOOKUP(A4,'TODOS OS PROCESSOS ATUALIZADOS '!A:I,7,0) -> Autorizada Sucesso | K4: Concluído | L4: =IFERROR(IF(J4=I4, "Item não atualizado", "Item atualizado"), "Item não localizado") -> Item atualizado | N4: Em andamento | O4: Enviado ao JURIDICO | P4: 2300001213.000370/2025-49
A5: A.027-ARP.0089.01.2024.GOV.HUOC.PE | B5: =IFERROR(__xludf.DUMMYFUNCTION("REGEXEXTRACT(A5, ""\.(?:GOV|EXT)\.([A-Z0-9\-]+)"") "),"HUOC") -> HUOC | C5: HOSPITAL REGIONAL DO AGRESTE DR.WALDEMIRO FERREIRA | D5: Adesão | E5: =IFERROR(__xludf.DUMMYFUNCTION("REGEXEXTRACT(A5, ""-(.*)"")"),"ARP.0089.01.2024.GOV.HUOC.PE") -> ARP.0089.01.2024.GOV.HUOC.PE | F5: Registro de Preços para o fornecimento eventual de MEDICAMENTOS ANTIMICROBIANOS (SEI Nº 0040609437.000129/2024-21) | H5: 45912 | I5: Cancelada | J5: =VLOOKUP(A5,'TODOS OS PROCESSOS ATUALIZADOS '!A:I,7,0) -> Cancelada por fim vigencia ATA | K5: Cancelado | L5: =IFERROR(IF(J5=I5, "Item não atualizado", "Item atualizado"), "Item não localizado") -> Item atualizado | N5: Cancelado | O5: SEI não localizado
A6: A.024-ARP.0119.01.2024.GOV.HUOC.PE | B6: =IFERROR(__xludf.DUMMYFUNCTION("REGEXEXTRACT(A6, ""\.(?:GOV|EXT)\.([A-Z0-9\-]+)"") "),"HUOC") -> HUOC | C6: HOSPITAL REGIONAL DO AGRESTE DR.WALDEMIRO FERREIRA | D6: Adesão | E6: =IFERROR(__xludf.DUMMYFUNCTION("REGEXEXTRACT(A6, ""-(.*)"")"),"ARP.0119.01.2024.GOV.HUOC.PE") -> ARP.0119.01.2024.GOV.HUOC.PE | F6: Registro de Preços para a eventual aquisição de Medicamentos Clínicos Gerais 4 (SEI Nº 0040609437.000172/2024-96) | G6: NFOCPO | H6: 45923 | I6: Concluído | J6: =VLOOKUP(A6,'TODOS OS PROCESSOS ATUALIZADOS '!A:I,7,0) -> Autorizada Sucesso | K6: Concluído | L6: =IFERROR(IF(J6=I6, "Item não atualizado", "Item atualizado"), "Item não localizado") -> Item atualizado | N6: Concluído | O6: Enviado ao NOF | P6: 2300001213.000405/2025-40
A7: A.019-ARP.0013.00.2025.GOV.FUNDARPE.PE | B7: =IFERROR(__xludf.DUMMYFUNCTION("REGEXEXTRACT(A7, ""\.(?:GOV|EXT)\.([A-Z0-9\-]+)"") "),"FUNDARPE") -> FUNDARPE | C7: HOSPITAL REGIONAL DO AGRESTE DR.WALDEMIRO FERREIRA | D7: Adesão | E7: =IFERROR(__xludf.DUMMYFUNCTION("REGEXEXTRACT(A7, ""-(.*)"")"),"ARP.0013.00.2025.GOV.FUNDARPE.PE") -> ARP.0013.00.2025.GOV.FUNDARPE.PE | F7: Formação de Registro de Preços para contratação eventual de prestação de serviços de Alimentação Pronta (marmitex e lanche) e Buffet (coffee break, coquetel volante e self-service), sem a locação de espaço para atender as demandas dos projetos, eventos, ciclos tradicionais, feiras, festivais e demais ações e/ou eventos culturais, promovidos e/ou apoiados pelo Governo de Pernambuco | G7: NAMP | H7: 45943 | I7: Concluído | J7: =VLOOKUP(A7,'TODOS OS PROCESSOS ATUALIZADOS '!A:I,7,0) -> Autorizada Sucesso | K7: Concluído | L7: =IFERROR(IF(J7=I7, "Item não atualizado", "Item atualizado"), "Item não localizado") -> Item atualizado | N7: Em andamento | O7: Enviado a GCONTRATOS | P7: 2300002942.000003/2025-73
A8: A.015-ARP.0017.00.2025.EXT.131763.PB | B8: =IFERROR(__xludf.DUMMYFUNCTION("REGEXEXTRACT(A8, ""\.(?:GOV|EXT)\.([A-Z0-9\-]+)"") "),"131763") -> 131763 | C8: HOSPITAL REGIONAL DO AGRESTE DR.WALDEMIRO FERREIRA | D8: Adesão | E8: =IFERROR(__xludf.DUMMYFUNCTION("REGEXEXTRACT(A8, ""-(.*)"")"),"ARP.0017.00.2025.EXT.131763.PB") -> ARP.0017.00.2025.EXT.131763.PB | F8: A presente Ata tem por objetivo o registro de preços PARA REGISTRO DE PREÇO PARA AQUISIÇÃO DE MEDICAMENTOS ANTIBACTERIANOS INJETÁVEIS especificado, no item 1.1 do Termo de Referência, anexo no edital de Pregão 173/2024 que é parte integrante desta Ata, assim como as propostas cujos preços tenham sido registrados, independentemente da transcrição. | G8: NFOCPO | H8: 45929 | I8: Concluído | J8: =VLOOKUP(A8,'TODOS OS PROCESSOS ATUALIZADOS '!A:I,7,0) -> Autorizada Integrado | K8: Concluído | L8: =IFERROR(IF(J8=I8, "Item não atualizado", "Item atualizado"), "Item não localizado") -> Item atualizado | M8: Daniele | N8: Em andamento | O8: Enviado a NFOCPO | P8: 2300001213.000259/2025-52
A9: A.014-ARP.0017.00.2025.EXT.131763.PB | B9: =IFERROR(__xludf.DUMMYFUNCTION("REGEXEXTRACT(A9, ""\.(?:GOV|EXT)\.([A-Z0-9\-]+)"") "),"131763") -> 131763 | C9: HOSPITAL REGIONAL DO AGRESTE DR.WALDEMIRO FERREIRA | D9: Adesão | E9: =IFERROR(__xludf.DUMMYFUNCTION("REGEXEXTRACT(A9, ""-(.*)"")"),"ARP.0017.00.2025.EXT.131763.PB") -> ARP.0017.00.2025.EXT.131763.PB | F9: A presente Ata tem por objetivo o registro de preços PARA REGISTRO DE PREÇO PARA AQUISIÇÃO DE MEDICAMENTOS ANTIBACTERIANOS INJETÁVEIS especificado, no item 1.1 do Termo de Referência, anexo no edital de Pregão 173/2024 que é parte integrante desta Ata, assim como as propostas cujos preços tenham sido registrados, independentemente da transcrição. | H9: 45917 | I9: Concluído | J9: =VLOOKUP(A9,'TODOS OS PROCESSOS ATUALIZADOS '!A:I,7,0) -> Autorizada Integrado | K9: Concluído | L9: =IFERROR(IF(J9=I9, "Item não atualizado", "Item atualizado"), "Item não localizado") -> Item atualizado | M9: Daniele | N9: Em andamento | O9: Enviado a GCONTRATOS | P9: 2300001213.000190/2025-67 | Q9: solicitação em duplicidade com A.014-ARP.0017.00.2025.EXT.131763.PB - sem efeito para conlcusão da compra
A10: A.013-ARP.0084.05.2024.GOV.CISAM.PE | B10: =IFERROR(__xludf.DUMMYFUNCTION("REGEXEXTRACT(A10, ""\.(?:GOV|EXT)\.([A-Z0-9\-]+)"") "),"CISAM") -> CISAM | C10: HOSPITAL REGIONAL DO AGRESTE DR.WALDEMIRO FERREIRA | D10: Adesão | E10: =IFERROR(__xludf.DUMMYFUNCTION("REGEXEXTRACT(A10, ""-(.*)"")"),"ARP.0084.05.2024.GOV.CISAM.PE") -> ARP.0084.05.2024.GOV.CISAM.PE | F10: REGISTRO DE PREÇOS PARA FORNECIMENTO EVENTUAL DE MOBILIARIOS MEDICO-HOSPITALAR PARA O CENTRO DE PARTO NORMAL E CASA DA GESTANTE BEBE E PUERPERA PARA RECÉM NASCIDOS, VISANDO ATENDER AS NECESSIDADES DO CISAM/UPE E DEMAIS ÓRGÃO PARTICIPANTES. | G10: NAMP | H10: 45923 | I10: Concluído | J10: =VLOOKUP(A10,'TODOS OS PROCESSOS ATUALIZADOS '!A:I,7,0) -> Autorizada Sucesso | K10: Concluído | L10: =IFERROR(IF(J10=I10, "Item não atualizado", "Item atualizado"), "Item não localizado") -> Item atualizado | N10: Em andamento | O10: Enviado ao JURIDICO | P10: 2300002544.000075/2025-11
A11: A.012-ARP.0013.02.2025.GOV.HOF.PE | B11: =IFERROR(__xludf.DUMMYFUNCTION("REGEXEXTRACT(A11, ""\.(?:GOV|EXT)\.([A-Z0-9\-]+)"") "),"HOF") -> HOF | C11: HOSPITAL REGIONAL DO AGRESTE DR.WALDEMIRO FERREIRA | D11: Adesão | E11: =IFERROR(__xludf.DUMMYFUNCTION("REGEXEXTRACT(A11, ""-(.*)"")"),"ARP.0013.02.2025.GOV.HOF.PE") -> ARP.0013.02.2025.GOV.HOF.PE | F11: REGISTRO DE PREÇOS PARA O FORNECIMENTO DE DISPOSITIVOS MÉDICOS DO TIPO INSUMOS PARA OXIGENOTERAPIA, VISANDO ATENDER AS NECESSIDADES DO HOSPITAL OTÁVIO DE FREITAS. | G11: NAEN | H11: 45924 | I11: Em configuração | J11: =VLOOKUP(A11,'TODOS OS PROCESSOS ATUALIZADOS '!A:I,7,0) -> Em configuração | K11: Em andamento | L11: =IFERROR(IF(J11=I11, "Item não atualizado", "Item atualizado"), "Item não localizado") -> Item não atualizado | M11: Elisangela | N11: Em andamento | O11: SEI não localizado | P11: Revisar com Papa | Q11: Finalizar com o nucleo
A12: A.012-ARP.0009.02.2025.GOV.FES-PE.PE | B12: =IFERROR(__xludf.DUMMYFUNCTION("REGEXEXTRACT(A12, ""\.(?:GOV|EXT)\.([A-Z0-9\-]+)"") "),"FES-PE") -> FES-PE | C12: HOSPITAL REGIONAL DO AGRESTE DR.WALDEMIRO FERREIRA | D12: Adesão | E12: =IFERROR(__xludf.DUMMYFUNCTION("REGEXEXTRACT(A12, ""-(.*)"")"),"ARP.0009.02.2025.GOV.FES-PE.PE") -> ARP.0009.02.2025.GOV.FES-PE.PE | F12: Registro de Preços para aquisição de Material Médico Hospitalar - Luvas (Unificado) | G12: NFOCPO | H12: 45943 | I12: Concluído | J12: =VLOOKUP(A12,'TODOS OS PROCESSOS ATUALIZADOS '!A:I,7,0) -> Autorizada Sucesso | K12: Concluído | L12: =IFERROR(IF(J12=I12, "Item não atualizado", "Item atualizado"), "Item não localizado") -> Item atualizado | N12: Concluído | O12: Enviado ao NOF | P12: 2300001213.000385/2025-15
A13: A.011-ARP.0080.00.2025.GOV.FES-PE.PE | B13: =IFERROR(__xludf.DUMMYFUNCTION("REGEXEXTRACT(A13, ""\.(?:GOV|EXT)\.([A-Z0-9\-]+)"") "),"FES-PE") -> FES-PE | C13: HOSPITAL REGIONAL DO AGRESTE DR.WALDEMIRO FERREIRA | D13: Adesão | E13: =IFERROR(__xludf.DUMMYFUNCTION("REGEXEXTRACT(A13, ""-(.*)"")"),"ARP.0080.00.2025.GOV.FES-PE.PE") -> ARP.0080.00.2025.GOV.FES-PE.PE | F13: Formação de Registro de Preços para o fornecimento eventual de MEDICAMENTOS INJETÁVEIS VOL. 1 visando atender as necessidades do Hospital Jaboatão Prazeres. | G13: NFOCPO | H13: 45933 | I13: Concluído | J13: =VLOOKUP(A13,'TODOS OS PROCESSOS ATUALIZADOS '!A:I,7,0) -> Autorizada Sucesso | K13: Concluído | L13: =IFERROR(IF(J13=I13, "Item não atualizado", "Item atualizado"), "Item não localizado") -> Item atualizado | N13: Em andamento | O13: Enviado a NFOCPO | P13: 2300001213.000402/2025-14
A14: A.010-ARP.0051.04.2025.GOV.PROCAPE.PE | B14: =IFERROR(__xludf.DUMMYFUNCTION("REGEXEXTRACT(A14, ""\.(?:GOV|EXT)\.([A-Z0-9\-]+)"") "),"PROCAPE") -> PROCAPE | C14: HOSPITAL REGIONAL DO AGRESTE DR.WALDEMIRO FERREIRA | D14: Adesão | E14: =IFERROR(__xludf.DUMMYFUNCTION("REGEXEXTRACT(A14, ""-(.*)"")"),"ARP.0051.04.2025.GOV.PROCAPE.PE") -> ARP.0051.04.2025.GOV.PROCAPE.PE | F14: REGISTRO DE PREÇOS PARA EVENTUAL FORNECIMENTO DE MATERIAL DE CONSUMO HOSPITALAR (MATERIAL PENSO) | G14: NFOCPO | H14: 45925 | I14: Concluído | J14: =VLOOKUP(A14,'TODOS OS PROCESSOS ATUALIZADOS '!A:I,7,0) -> Autorizada Sucesso | K14: Concluído | L14: =IFERROR(IF(J14=I14, "Item não atualizado", "Item atualizado"), "Item não localizado") -> Item atualizado | N14: Em andamento | O14: Enviado ao JURIDICO | P14: 2300001213.000360/2025-11
A15: A.008-ARP.0072.07.2025.GOV.HUOC.PE | B15: =IFERROR(__xludf.DUMMYFUNCTION("REGEXEXTRACT(A15, ""\.(?:GOV|EXT)\.([A-Z0-9\-]+)"") "),"HUOC") -> HUOC | C15: HOSPITAL REGIONAL DO AGRESTE DR.WALDEMIRO FERREIRA | D15: Adesão | E15: =IFERROR(__xludf.DUMMYFUNCTION("REGEXEXTRACT(A15, ""-(.*)"")"),"ARP.0072.07.2025.GOV.HUOC.PE") -> ARP.0072.07.2025.GOV.HUOC.PE | F15: Registro de Preços para o eventual fornecimento de MEDICAMENTOS CLÍNICOS GERAIS 6 - 18 ITENS - SEI: 0040609437.000009/2025-12 | G15: NFOCPO | H15: 45924 | I15: Cancelada | J15: =VLOOKUP(A15,'TODOS OS PROCESSOS ATUALIZADOS '!A:I,7,0) -> Em configuração | K15: Cancelar Com o Suporte | L15: =IFERROR(IF(J15=I15, "Item não atualizado", "Item atualizado"), "Item não localizado") -> Item atualizado | N15: Cancelar Com o Suporte | O15: SEI não localizado | P15: j
A16: A.008-ARP.0008.05.2025.GOV.HGV.PE | B16: =IFERROR(__xludf.DUMMYFUNCTION("REGEXEXTRACT(A16, ""\.(?:GOV|EXT)\.([A-Z0-9\-]+)"") "),"HGV") -> HGV | C16: HOSPITAL REGIONAL DO AGRESTE DR.WALDEMIRO FERREIRA | D16: Adesão | E16: =IFERROR(__xludf.DUMMYFUNCTION("REGEXEXTRACT(A16, ""-(.*)"")"),"ARP.0008.05.2025.GOV.HGV.PE") -> ARP.0008.05.2025.GOV.HGV.PE | F16: Registro de Preços para o fornecimento eventual de MATERIAIS ESPECIAIS PARA ENDOSCOPIA | G16: NSADRE | H16: 45946 | I16: Cancelada | J16: =VLOOKUP(A16,'TODOS OS PROCESSOS ATUALIZADOS '!A:I,7,0) -> Cancelada | K16: Cancelado | L16: =IFERROR(IF(J16=I16, "Item não atualizado", "Item atualizado"), "Item não localizado") -> Item não atualizado | N16: Cancelado | O16: SEI não localizado
A17: A.031-ARP.0001.01.2025.GOV.HUOC.PE | B17: =IFERROR(__xludf.DUMMYFUNCTION("REGEXEXTRACT(A17, ""\.(?:GOV|EXT)\.([A-Z0-9\-]+)"") "),"HUOC") -> HUOC | C17: HOSPITAL REGIONAL DO AGRESTE DR.WALDEMIRO FERREIRA | D17: Adesão | E17: =IFERROR(__xludf.DUMMYFUNCTION("REGEXEXTRACT(A17, ""-(.*)"")"),"ARP.0001.01.2025.GOV.HUOC.PE") -> ARP.0001.01.2025.GOV.HUOC.PE | F17: Registro de Preços para o eventual fornecimento de ÓRTESES, PRÓTESES E MATERIAIS ESPECIAIS - OPME’S (TRAUMATO I), visando atender as necessidades do Hospital da Restauração. | G17: NFOCPO | H17: 45943 | I17: Concluído | J17: =VLOOKUP(A17,'TODOS OS PROCESSOS ATUALIZADOS '!A:I,7,0) -> Em configuração | K17: Concluído | L17: =IFERROR(IF(J17=I17, "Item não atualizado", "Item atualizado"), "Item não localizado") -> Item atualizado | N17: Em andamento | O17: Enviado ao GFIN | P17: 2300001213.000385/2025-15 | Q17: Finalizar com o nucleo
A18: A.007-ARP.0072.07.2025.GOV.HUOC.PE | B18: =IFERROR(__xludf.DUMMYFUNCTION("REGEXEXTRACT(A18, ""\.(?:GOV|EXT)\.([A-Z0-9\-]+)"") "),"HUOC") -> HUOC | C18: HOSPITAL REGIONAL DO AGRESTE DR.WALDEMIRO FERREIRA | D18: Adesão | E18: =IFERROR(__xludf.DUMMYFUNCTION("REGEXEXTRACT(A18, ""-(.*)"")"),"ARP.0072.07.2025.GOV.HUOC.PE") -> ARP.0072.07.2025.GOV.HUOC.PE | F18: Registro de Preços para o eventual fornecimento de MEDICAMENTOS CLÍNICOS GERAIS 6 - 18 ITENS - SEI: 0040609437.000009/2025-12 | H18: 45918 | I18: Concluído | J18: =VLOOKUP(A18,'TODOS OS PROCESSOS ATUALIZADOS '!A:I,7,0) -> Autorizada Sucesso | K18: Concluído | L18: =IFERROR(IF(J18=I18, "Item não atualizado", "Item atualizado"), "Item não localizado") -> Item atualizado | N18: Em andamento | O18: Enviado ao GFIN | P18: 2300001213.000376/2025-16
A19: A.007-ARP.0057.00.2025.GOV.HUOC.PE | B19: =IFERROR(__xludf.DUMMYFUNCTION("REGEXEXTRACT(A19, ""\.(?:GOV|EXT)\.([A-Z0-9\-]+)"") "),"HUOC") -> HUOC | C19: HOSPITAL REGIONAL DO AGRESTE DR.WALDEMIRO FERREIRA | D19: Adesão | E19: =IFERROR(__xludf.DUMMYFUNCTION("REGEXEXTRACT(A19, ""-(.*)"")"),"ARP.0057.00.2025.GOV.HUOC.PE") -> ARP.0057.00.2025.GOV.HUOC.PE | F19: Registro de Preços para o fornecimento eventual de MATERIAIS MÉDICOS HOSPITALARES - SONDA FOLEYS E CATETER INTRAVENOSO (SEI: 0040609912.000190/2024-15) | G19: NFOCPO | H19: 45925 | I19: Cancelada | J19: =VLOOKUP(A19,'TODOS OS PROCESSOS ATUALIZADOS '!A:I,7,0) -> Em configuração | K19: Cancelar Com o Suporte | L19: =IFERROR(IF(J19=I19, "Item não atualizado", "Item atualizado"), "Item não localizado") -> Item atualizado | N19: Cancelar Com o Suporte | O19: SEI não localizado
A20: A.007-ARP.0013.06.2025.GOV.HOF.PE | B20: =IFERROR(__xludf.DUMMYFUNCTION("REGEXEXTRACT(A20, ""\.(?:GOV|EXT)\.([A-Z0-9\-]+)"") "),"HOF") -> HOF | C20: HOSPITAL REGIONAL DO AGRESTE DR.WALDEMIRO FERREIRA | D20: Adesão | E20: =IFERROR(__xludf.DUMMYFUNCTION("REGEXEXTRACT(A20, ""-(.*)"")"),"ARP.0013.06.2025.GOV.HOF.PE") -> ARP.0013.06.2025.GOV.HOF.PE | F20: REGISTRO DE PREÇOS PARA O FORNECIMENTO DE DISPOSITIVOS MÉDICOS DO TIPO INSUMOS PARA OXIGENOTERAPIA, VISANDO ATENDER AS NECESSIDADES DO HOSPITAL OTÁVIO DE FREITAS. | G20: NAEN | H20: 45918 | I20: Cancelada | J20: =VLOOKUP(A20,'TODOS OS PROCESSOS ATUALIZADOS '!A:I,7,0) -> Em configuração | K20: Cancelar Com o Suporte | L20: =IFERROR(IF(J20=I20, "Item não atualizado", "Item atualizado"), "Item não localizado") -> Item atualizado | N20: Cancelar Com o Suporte | O20: SEI não localizado
A21: A.007-ARP.0008.05.2025.GOV.HGV.PE | B21: =IFERROR(__xludf.DUMMYFUNCTION("REGEXEXTRACT(A21, ""\.(?:GOV|EXT)\.([A-Z0-9\-]+)"") "),"HGV") -> HGV | C21: HOSPITAL REGIONAL DO AGRESTE DR.WALDEMIRO FERREIRA | D21: Adesão | E21: =IFERROR(__xludf.DUMMYFUNCTION("REGEXEXTRACT(A21, ""-(.*)"")"),"ARP.0008.05.2025.GOV.HGV.PE") -> ARP.0008.05.2025.GOV.HGV.PE | F21: Registro de Preços para o fornecimento eventual de MATERIAIS ESPECIAIS PARA ENDOSCOPIA | G21: NSADRE | H21: 45932 | I21: Cancelada | J21: =VLOOKUP(A21,'TODOS OS PROCESSOS ATUALIZADOS '!A:I,7,0) -> Cancelada | K21: Cancelado | L21: =IFERROR(IF(J21=I21, "Item não atualizado", "Item atualizado"), "Item não localizado") -> Item não atualizado | N21: Cancelado | O21: SEI não localizado
A22: A.007-ARP.0005.00.2025.GOV.FEAS.PE | B22: =IFERROR(__xludf.DUMMYFUNCTION("REGEXEXTRACT(A22, ""\.(?:GOV|EXT)\.([A-Z0-9\-]+)"") "),"FEAS") -> FEAS | C22: HOSPITAL REGIONAL DO AGRESTE DR.WALDEMIRO FERREIRA | D22: Adesão | E22: =IFERROR(__xludf.DUMMYFUNCTION("REGEXEXTRACT(A22, ""-(.*)"")"),"ARP.0005.00.2025.GOV.FEAS.PE") -> ARP.0005.00.2025.GOV.FEAS.PE | F22: Formação de Registro de Preços para o fornecimento eventual de MATERIAL DE LIMPEZA e MATERIAL HIGIENE PESSOAL visando atender as necessidades dos municípios que possam vir a ser afetados por desastre, e acolhida pela Secretária de Assistência Social, Combate à Fome e Políticas sobre Drogas por meio da Secretaria Executiva de Assistência Social, nos termos da legislação vigente e conforme as condições, especificações, quantidades e exigências contidas neste Termo de Referência | G22: NAMP | H22: 45923 | I22: Concluído | J22: =VLOOKUP(A22,'TODOS OS PROCESSOS ATUALIZADOS '!A:I,7,0) -> Autorizada Sucesso | K22: Concluído | L22: =IFERROR(IF(J22=I22, "Item não atualizado", "Item atualizado"), "Item não localizado") -> Item atualizado | N22: Em andamento | O22: Enviado ao JURIDICO | P22: 2300001213.000381/2025-29
A23: A.007-ARP.0001.00.2025.GOV.HR.PE | B23: =IFERROR(__xludf.DUMMYFUNCTION("REGEXEXTRACT(A23, ""\.(?:GOV|EXT)\.([A-Z0-9\-]+)"") "),"HR") -> HR | C23: HOSPITAL REGIONAL DO AGRESTE DR.WALDEMIRO FERREIRA | D23: Adesão | E23: =IFERROR(__xludf.DUMMYFUNCTION("REGEXEXTRACT(A23, ""-(.*)"")"),"ARP.0001.00.2025.GOV.HR.PE") -> ARP.0001.00.2025.GOV.HR.PE | F23: Registro de Preços para o eventual fornecimento de ÓRTESES, PRÓTESES E MATERIAIS ESPECIAIS - OPME’S (TRAUMATO I), visando atender as necessidades do Hospital da Restauração. | G23: NFOCPO | H23: 45943 | I23: Concluído | J23: =VLOOKUP(A23,'TODOS OS PROCESSOS ATUALIZADOS '!A:I,7,0) -> Autorizada Sucesso | K23: Concluído | L23: =IFERROR(IF(J23=I23, "Item não atualizado", "Item atualizado"), "Item não localizado") -> Item atualizado | N23: Em andamento | O23: Enviado a GCONTRATOS | P23: 2300002944.000002/2025-17
A24: A.006-ARP.0008.05.2025.GOV.HGV.PE | B24: =IFERROR(__xludf.DUMMYFUNCTION("REGEXEXTRACT(A24, ""\.(?:GOV|EXT)\.([A-Z0-9\-]+)"") "),"HGV") -> HGV | C24: HOSPITAL REGIONAL DO AGRESTE DR.WALDEMIRO FERREIRA | D24: Adesão | E24: =IFERROR(__xludf.DUMMYFUNCTION("REGEXEXTRACT(A24, ""-(.*)"")"),"ARP.0008.05.2025.GOV.HGV.PE") -> ARP.0008.05.2025.GOV.HGV.PE | F24: Registro de Preços para o fornecimento eventual de MATERIAIS ESPECIAIS PARA ENDOSCOPIA | G24: NSADRE | H24: 45925 | I24: Cancelada | J24: =VLOOKUP(A24,'TODOS OS PROCESSOS ATUALIZADOS '!A:I,7,0) -> Cancelada | K24: Cancelado | L24: =IFERROR(IF(J24=I24, "Item não atualizado", "Item atualizado"), "Item não localizado") -> Item não atualizado | N24: Cancelado | O24: SEI não localizado
A25: A.006-ARP.0005.00.2025.GOV.FEAS.PE | B25: =IFERROR(__xludf.DUMMYFUNCTION("REGEXEXTRACT(A25, ""\.(?:GOV|EXT)\.([A-Z0-9\-]+)"") "),"FEAS") -> FEAS | C25: HOSPITAL REGIONAL DO AGRESTE DR.WALDEMIRO FERREIRA | D25: Adesão | E25: =IFERROR(__xludf.DUMMYFUNCTION("REGEXEXTRACT(A25, ""-(.*)"")"),"ARP.0005.00.2025.GOV.FEAS.PE") -> ARP.0005.00.2025.GOV.FEAS.PE | F25: Formação de Registro de Preços para o fornecimento eventual de MATERIAL DE LIMPEZA e MATERIAL HIGIENE PESSOAL visando atender as necessidades dos municípios que possam vir a ser afetados por desastre, e acolhida pela Secretária de Assistência Social, Combate à Fome e Políticas sobre Drogas por meio da Secretaria Executiva de Assistência Social, nos termos da legislação vigente e conforme as condições, especificações, quantidades e exigências contidas neste Termo de Referência | G25: NAMP | H25: 45917 | I25: Cancelada | J25: =VLOOKUP(A25,'TODOS OS PROCESSOS ATUALIZADOS '!A:I,7,0) -> Em configuração | K25: Cancelar Com o Suporte | L25: =IFERROR(IF(J25=I25, "Item não atualizado", "Item atualizado"), "Item não localizado") -> Item atualizado | N25: Cancelar Com o Suporte | O25: SEI não localizado
A26: A.005-ARP.0011.00.2025.GOV.HAM.PE | B26: =IFERROR(__xludf.DUMMYFUNCTION("REGEXEXTRACT(A26, ""\.(?:GOV|EXT)\.([A-Z0-9\-]+)"") "),"HAM") -> HAM | C26: HOSPITAL REGIONAL DO AGRESTE DR.WALDEMIRO FERREIRA | D26: Adesão | E26: =IFERROR(__xludf.DUMMYFUNCTION("REGEXEXTRACT(A26, ""-(.*)"")"),"ARP.0011.00.2025.GOV.HAM.PE") -> ARP.0011.00.2025.GOV.HAM.PE | F26: REGISTRO DE PREÇOS PARA EVENTUAL FORNECIMENTO DE MATERIAL DE CONSUMO HOSPITALAR ( AQUISIÇÃO DE MATERIAL KIT DE CURATIVO P/ TERAPIA POR PRESSÃO NEGATIVA ) | G26: NFOCPO | H26: 45917 | I26: Concluído | J26: =VLOOKUP(A26,'TODOS OS PROCESSOS ATUALIZADOS '!A:I,7,0) -> Autorizada Sucesso | K26: Concluído | L26: =IFERROR(IF(J26=I26, "Item não atualizado", "Item atualizado"), "Item não localizado") -> Item atualizado | M26: Hannah | N26: Em andamento | O26: Enviado a GCONTRATOS | P26: 2300002541.000001/2025-05
A27: A.004-ARP.0010.05.2025.GOV.HAM.PE | B27: =IFERROR(__xludf.DUMMYFUNCTION("REGEXEXTRACT(A27, ""\.(?:GOV|EXT)\.([A-Z0-9\-]+)"") "),"HAM") -> HAM | C27: HOSPITAL REGIONAL DO AGRESTE DR.WALDEMIRO FERREIRA | D27: Adesão | E27: =IFERROR(__xludf.DUMMYFUNCTION("REGEXEXTRACT(A27, ""-(.*)"")"),"ARP.0010.05.2025.GOV.HAM.PE") -> ARP.0010.05.2025.GOV.HAM.PE | F27: Registro de Preços para o fornecimento eventual de material médico hospitalar destinado ao serviço de anestesia, visando atender as necessidades do Hospital Agamenon Magalhães | G27: NFOCPO | H27: 45916 | I27: Concluído | J27: =VLOOKUP(A27,'TODOS OS PROCESSOS ATUALIZADOS '!A:I,7,0) -> Autorizada Sucesso | K27: Concluído | L27: =IFERROR(IF(J27=I27, "Item não atualizado", "Item atualizado"), "Item não localizado") -> Item atualizado | M27: Hannah | N27: Em andamento | O27: Enviado a GCONTRATOS | P27: 2300001213.000369/2025-14
A28: A.003-ARP.0501.00.2025.EXT.HGJMM.RN | B28: =IFERROR(__xludf.DUMMYFUNCTION("REGEXEXTRACT(A28, ""\.(?:GOV|EXT)\.([A-Z0-9\-]+)"") "),"HGJMM") -> HGJMM | C28: HOSPITAL REGIONAL DO AGRESTE DR.WALDEMIRO FERREIRA | D28: Adesão | E28: =IFERROR(__xludf.DUMMYFUNCTION("REGEXEXTRACT(A28, ""-(.*)"")"),"ARP.0501.00.2025.EXT.HGJMM.RN") -> ARP.0501.00.2025.EXT.HGJMM.RN | F28: Aquisição de Medicamentos - ANTIMICROBIANOS , conforme condições e exigências estabelecidas neste instrumento. | G28: NFOCPO | H28: 45924 | I28: Cancelada | J28: =VLOOKUP(A28,'TODOS OS PROCESSOS ATUALIZADOS '!A:I,7,0) -> Cancelada por fim vigencia ATA | K28: Cancelado | L28: =IFERROR(IF(J28=I28, "Item não atualizado", "Item atualizado"), "Item não localizado") -> Item atualizado | N28: Cancelado | O28: SEI não localizado
A29: A.003-ARP.0118.05.2024.GOV.HUOC.PE | B29: =IFERROR(__xludf.DUMMYFUNCTION("REGEXEXTRACT(A29, ""\.(?:GOV|EXT)\.([A-Z0-9\-]+)"") "),"HUOC") -> HUOC | C29: HOSPITAL REGIONAL DO AGRESTE DR.WALDEMIRO FERREIRA | D29: Adesão | E29: =IFERROR(__xludf.DUMMYFUNCTION("REGEXEXTRACT(A29, ""-(.*)"")"),"ARP.0118.05.2024.GOV.HUOC.PE") -> ARP.0118.05.2024.GOV.HUOC.PE | F29: Registro de Preços para eventual fornecimento de MATERIAIS MÉDICOS HOSPITALARES PARA O SERVIÇO DE ENDOSCOPIA (SEI Nº0040609912.000069/2024-93) | H29: 45925 | I29: Concluído | J29: =VLOOKUP(A29,'TODOS OS PROCESSOS ATUALIZADOS '!A:I,7,0) -> Autorizada Sucesso | K29: Concluído | L29: =IFERROR(IF(J29=I29, "Item não atualizado", "Item atualizado"), "Item não localizado") -> Item atualizado | N29: Concluído | O29: Enviado ao NOF | P29: 2300001213.000404/2025-03
A30: A.003-ARP.0118.01.2024.GOV.HUOC.PE | B30: =IFERROR(__xludf.DUMMYFUNCTION("REGEXEXTRACT(A30, ""\.(?:GOV|EXT)\.([A-Z0-9\-]+)"") "),"HUOC") -> HUOC | C30: HOSPITAL REGIONAL DO AGRESTE DR.WALDEMIRO FERREIRA | D30: Adesão | E30: =IFERROR(__xludf.DUMMYFUNCTION("REGEXEXTRACT(A30, ""-(.*)"")"),"ARP.0118.01.2024.GOV.HUOC.PE") -> ARP.0118.01.2024.GOV.HUOC.PE | F30: Registro de Preços para eventual fornecimento de MATERIAIS MÉDICOS HOSPITALARES PARA O SERVIÇO DE ENDOSCOPIA (SEI Nº0040609912.000069/2024-93) | H30: 45925 | I30: Concluído | J30: =VLOOKUP(A30,'TODOS OS PROCESSOS ATUALIZADOS '!A:I,7,0) -> Autorizada Sucesso | K30: Concluído | L30: =IFERROR(IF(J30=I30, "Item não atualizado", "Item atualizado"), "Item não localizado") -> Item atualizado | N30: Concluído | O30: Enviado ao NOF | P30: 2300001213.000342/2025-21
A31: A.003-ARP.0073.05.2025.GOV.HUOC.PE | B31: =IFERROR(__xludf.DUMMYFUNCTION("REGEXEXTRACT(A31, ""\.(?:GOV|EXT)\.([A-Z0-9\-]+)"") "),"HUOC") -> HUOC | C31: HOSPITAL REGIONAL DO AGRESTE DR.WALDEMIRO FERREIRA | D31: Adesão | E31: =IFERROR(__xludf.DUMMYFUNCTION("REGEXEXTRACT(A31, ""-(.*)"")"),"ARP.0073.05.2025.GOV.HUOC.PE") -> ARP.0073.05.2025.GOV.HUOC.PE | F31: Registro de Preços para o eventual fornecimento de MEDICAMENTOS ANTINEOPLÁSICOS E ADJUVANTES (13 ITENS) (SEI: 0040609437.000263/2024-21) | H31: 45916 | I31: Concluído | J31: =VLOOKUP(A31,'TODOS OS PROCESSOS ATUALIZADOS '!A:I,7,0) -> Autorizada Sucesso | K31: Concluído | L31: =IFERROR(IF(J31=I31, "Item não atualizado", "Item atualizado"), "Item não localizado") -> Item atualizado | N31: Concluído | O31: Enviado ao NOF | P31: 2300001213.000362/2025-01
A32: A.003-ARP.0073.00.2025.GOV.FES-PE.PE | B32: =IFERROR(__xludf.DUMMYFUNCTION("REGEXEXTRACT(A32, ""\.(?:GOV|EXT)\.([A-Z0-9\-]+)"") "),"FES-PE") -> FES-PE | C32: HOSPITAL REGIONAL DO AGRESTE DR.WALDEMIRO FERREIRA | D32: Adesão | E32: =IFERROR(__xludf.DUMMYFUNCTION("REGEXEXTRACT(A32, ""-(.*)"")"),"ARP.0073.00.2025.GOV.FES-PE.PE") -> ARP.0073.00.2025.GOV.FES-PE.PE | F32: Registro de Preços para o fornecimento eventual de Dispositivos Médicos do tipo Materiais Médicos (Indicadores, cera, e cimento cirúrgico), conforme especificações e quantitativos previstos no Termo de Referência, visando atender as necessidades dos hospitais e estabelecimentos vinculados à Secretaria Estadual de Saúde de Pernambuco | G32: NFOCPO | H32: 45946 | I32: Concluído | J32: =VLOOKUP(A32,'TODOS OS PROCESSOS ATUALIZADOS '!A:I,7,0) -> Autorizada Sucesso | K32: Concluído | L32: =IFERROR(IF(J32=I32, "Item não atualizado", "Item atualizado"), "Item não localizado") -> Item atualizado | N32: Concluído | O32: Enviado ao NOF | P32: 2300001213.000239/2025-81
A33: A.003-ARP.0044.04.2025.GOV.FES-PE.PE | B33: =IFERROR(__xludf.DUMMYFUNCTION("REGEXEXTRACT(A33, ""\.(?:GOV|EXT)\.([A-Z0-9\-]+)"") "),"FES-PE") -> FES-PE | C33: HOSPITAL REGIONAL DO AGRESTE DR.WALDEMIRO FERREIRA | D33: Adesão | E33: =IFERROR(__xludf.DUMMYFUNCTION("REGEXEXTRACT(A33, ""-(.*)"")"),"ARP.0044.04.2025.GOV.FES-PE.PE") -> ARP.0044.04.2025.GOV.FES-PE.PE | F33: Formação de Registro de Preços para o fornecimento eventual de dispositivos médicos do Tipo DRENOS visando atender as necessidades dos hospitais e estabelecimentos vinculados à Secretaria Estadual de Saúde de Pernambuco, conforme as condições, especificações, quantidades e exigências contidas no Termo de Referência | H33: 45924 | I33: Cancelada | J33: =VLOOKUP(A33,'TODOS OS PROCESSOS ATUALIZADOS '!A:I,7,0) -> Cancelada | K33: Cancelado | L33: =IFERROR(IF(J33=I33, "Item não atualizado", "Item atualizado"), "Item não localizado") -> Item não atualizado | N33: Cancelado | O33: SEI não localizado
A34: A.003-ARP.0009.01.2025.EXT.HMAR.PE | B34: =IFERROR(__xludf.DUMMYFUNCTION("REGEXEXTRACT(A34, ""\.(?:GOV|EXT)\.([A-Z0-9\-]+)"") "),"HMAR") -> HMAR | C34: HOSPITAL REGIONAL DO AGRESTE DR.WALDEMIRO FERREIRA | D34: Adesão | E34: =IFERROR(__xludf.DUMMYFUNCTION("REGEXEXTRACT(A34, ""-(.*)"")"),"ARP.0009.01.2025.EXT.HMAR.PE") -> ARP.0009.01.2025.EXT.HMAR.PE | F34: Registro de preços para eventual aquisição de produtos para saúde - MMH4 , visando atenderas necessidades do Hospital do Hospital Militar de Área de Recife (HMAR) | H34: 45923 | I34: Cancelada | J34: =VLOOKUP(A34,'TODOS OS PROCESSOS ATUALIZADOS '!A:I,7,0) -> Cancelada | K34: Cancelado | L34: =IFERROR(IF(J34=I34, "Item não atualizado", "Item atualizado"), "Item não localizado") -> Item não atualizado | N34: Cancelado | O34: SEI não localizado
A35: A.003-ARP.0008.02.2025.GOV.HGV.PE | B35: =IFERROR(__xludf.DUMMYFUNCTION("REGEXEXTRACT(A35, ""\.(?:GOV|EXT)\.([A-Z0-9\-]+)"") "),"HGV") -> HGV | C35: HOSPITAL REGIONAL DO AGRESTE DR.WALDEMIRO FERREIRA | D35: Adesão | E35: =IFERROR(__xludf.DUMMYFUNCTION("REGEXEXTRACT(A35, ""-(.*)"")"),"ARP.0008.02.2025.GOV.HGV.PE") -> ARP.0008.02.2025.GOV.HGV.PE | F35: Registro de Preços para o fornecimento eventual de MATERIAIS ESPECIAIS PARA ENDOSCOPIA | H35: 45917 | I35: Concluído | J35: =VLOOKUP(A35,'TODOS OS PROCESSOS ATUALIZADOS '!A:I,7,0) -> Autorizada Sucesso | K35: Concluído | L35: =IFERROR(IF(J35=I35, "Item não atualizado", "Item atualizado"), "Item não localizado") -> Item atualizado | N35: Em andamento | O35: Enviado ao GFIN | P35: 2300001213.000313/2025-60
A36: A.003-ARP.0006.03.2025.GOV.PROCAPE.PE | B36: =IFERROR(__xludf.DUMMYFUNCTION("REGEXEXTRACT(A36, ""\.(?:GOV|EXT)\.([A-Z0-9\-]+)"") "),"PROCAPE") -> PROCAPE | C36: HOSPITAL REGIONAL DO AGRESTE DR.WALDEMIRO FERREIRA | D36: Adesão | E36: =IFERROR(__xludf.DUMMYFUNCTION("REGEXEXTRACT(A36, ""-(.*)"")"),"ARP.0006.03.2025.GOV.PROCAPE.PE") -> ARP.0006.03.2025.GOV.PROCAPE.PE | F36: REGISTRO DE PREÇOS PARA EVENTUAL FORNECIMENTO DE MATERIAL DE CONSUMO HOSPITALAR (MEDICAMENTOS) | H36: 45929 | I36: Concluído | J36: =VLOOKUP(A36,'TODOS OS PROCESSOS ATUALIZADOS '!A:I,7,0) -> Autorizada Sucesso | K36: Concluído | L36: =IFERROR(IF(J36=I36, "Item não atualizado", "Item atualizado"), "Item não localizado") -> Item atualizado | N36: Concluído | O36: Enviado ao NOF | P36: 2300001213.000119/2025-84
A37: A.002-ARP.1190.00.2025.EXT.158552.PB | B37: =IFERROR(__xludf.DUMMYFUNCTION("REGEXEXTRACT(A37, ""\.(?:GOV|EXT)\.([A-Z0-9\-]+)"") "),"158552") -> 158552 | C37: HOSPITAL REGIONAL DO AGRESTE DR.WALDEMIRO FERREIRA | D37: Adesão | E37: =IFERROR(__xludf.DUMMYFUNCTION("REGEXEXTRACT(A37, ""-(.*)"")"),"ARP.1190.00.2025.EXT.158552.PB") -> ARP.1190.00.2025.EXT.158552.PB | F37: MIDAZOLAM 1 mg/mL (5 mg) solução injetável (ampola 5 mL). | H37: 45917 | I37: Concluído | J37: =VLOOKUP(A37,'TODOS OS PROCESSOS ATUALIZADOS '!A:I,7,0) -> Autorizada Integrado | K37: Concluído | L37: =IFERROR(IF(J37=I37, "Item não atualizado", "Item atualizado"), "Item não localizado") -> Item atualizado | N37: Concluído | O37: Enviado ao NOF | P37: 2300001213.000237/2025-92
A38: A.002-ARP.0118.05.2024.GOV.HUOC.PE | B38: =IFERROR(__xludf.DUMMYFUNCTION("REGEXEXTRACT(A38, ""\.(?:GOV|EXT)\.([A-Z0-9\-]+)"") "),"HUOC") -> HUOC | C38: HOSPITAL REGIONAL DO AGRESTE DR.WALDEMIRO FERREIRA | D38: Adesão | E38: =IFERROR(__xludf.DUMMYFUNCTION("REGEXEXTRACT(A38, ""-(.*)"")"),"ARP.0118.05.2024.GOV.HUOC.PE") -> ARP.0118.05.2024.GOV.HUOC.PE | F38: Registro de Preços para eventual fornecimento de MATERIAIS MÉDICOS HOSPITALARES PARA O SERVIÇO DE ENDOSCOPIA (SEI Nº0040609912.000069/2024-93) | H38: 45923 | I38: Concluído | J38: =VLOOKUP(A38,'TODOS OS PROCESSOS ATUALIZADOS '!A:I,7,0) -> Autorizada Sucesso | K38: Concluído | L38: =IFERROR(IF(J38=I38, "Item não atualizado", "Item atualizado"), "Item não localizado") -> Item atualizado | N38: Concluído | O38: Enviado ao NOF | P38: 2300001213.000341/2025-87
A39: A.002-ARP.0102.01.2025.GOV.HUOC.PE | B39: =IFERROR(__xludf.DUMMYFUNCTION("REGEXEXTRACT(A39, ""\.(?:GOV|EXT)\.([A-Z0-9\-]+)"") "),"HUOC") -> HUOC | C39: HOSPITAL REGIONAL DO AGRESTE DR.WALDEMIRO FERREIRA | D39: Adesão | E39: =IFERROR(__xludf.DUMMYFUNCTION("REGEXEXTRACT(A39, ""-(.*)"")"),"ARP.0102.01.2025.GOV.HUOC.PE") -> ARP.0102.01.2025.GOV.HUOC.PE | F39: Registro de Preços para o eventual fornecimento de GRAMPEADORES E CARGAR LINEARES E CIRCULARES (SEI Nº 0040609912.000126/2024-34) | G39: NAMP | H39: 45943 | I39: Concluído | J39: =VLOOKUP(A39,'TODOS OS PROCESSOS ATUALIZADOS '!A:I,7,0) -> Autorizada Sucesso | K39: Concluído | L39: =IFERROR(IF(J39=I39, "Item não atualizado", "Item atualizado"), "Item não localizado") -> Item atualizado | N39: Em andamento | O39: Enviado ao GFIN | P39: 2300001213.000398/2025-86
A40: A.002-ARP.0068.04.2025.GOV.FES-PE.PE | B40: =IFERROR(__xludf.DUMMYFUNCTION("REGEXEXTRACT(A40, ""\.(?:GOV|EXT)\.([A-Z0-9\-]+)"") "),"FES-PE") -> FES-PE | C40: HOSPITAL REGIONAL DO AGRESTE DR.WALDEMIRO FERREIRA | D40: Adesão | E40: =IFERROR(__xludf.DUMMYFUNCTION("REGEXEXTRACT(A40, ""-(.*)"")"),"ARP.0068.04.2025.GOV.FES-PE.PE") -> ARP.0068.04.2025.GOV.FES-PE.PE | F40: FORMAÇÃO DE REGISTRO DE PREÇOS PARA O FORNECIMENTO DE DISPOSITIVOS MÉDICOS, DO TIPO INSUMOS PARA OSTOMIA, VISANDO ATENDER AS NECESSIDADES DOS HOSPITAIS E ESTABELECIMENTOS VINCULADOS À SECRETARIA ESTADUAL DE SAÚDE DE PERNAMBUCO | G40: NFOCPO | H40: 45918 | I40: Cancelada | J40: =VLOOKUP(A40,'TODOS OS PROCESSOS ATUALIZADOS '!A:I,7,0) -> Em configuração | K40: Cancelar Com o Suporte | L40: =IFERROR(IF(J40=I40, "Item não atualizado", "Item atualizado"), "Item não localizado") -> Item atualizado | N40: Cancelar Com o Suporte | O40: SEI não localizado
A41: A.002-ARP.0045.02.2025.GOV.PROCAPE.PE | B41: =IFERROR(__xludf.DUMMYFUNCTION("REGEXEXTRACT(A41, ""\.(?:GOV|EXT)\.([A-Z0-9\-]+)"") "),"PROCAPE") -> PROCAPE | C41: HOSPITAL REGIONAL DO AGRESTE DR.WALDEMIRO FERREIRA | D41: Adesão | E41: =IFERROR(__xludf.DUMMYFUNCTION("REGEXEXTRACT(A41, ""-(.*)"")"),"ARP.0045.02.2025.GOV.PROCAPE.PE") -> ARP.0045.02.2025.GOV.PROCAPE.PE | F41: REGISTRO DE PREÇOS PARA EVENTUAL FORNECIMENTO DE MATERIAL DE CONSUMO HOSPITALAR (MATERIAL PENSO) | H41: 45918 | I41: Concluído | J41: =VLOOKUP(A41,'TODOS OS PROCESSOS ATUALIZADOS '!A:I,7,0) -> Autorizada Sucesso | K41: Concluído | L41: =IFERROR(IF(J41=I41, "Item não atualizado", "Item atualizado"), "Item não localizado") -> Item atualizado | N41: Concluído | O41: Enviado ao NOF | P41: 2300001209.000037/2025-07
A42: A.002-ARP.0044.04.2025.GOV.FES-PE.PE | B42: =IFERROR(__xludf.DUMMYFUNCTION("REGEXEXTRACT(A42, ""\.(?:GOV|EXT)\.([A-Z0-9\-]+)"") "),"FES-PE") -> FES-PE | C42: HOSPITAL REGIONAL DO AGRESTE DR.WALDEMIRO FERREIRA | D42: Adesão | E42: =IFERROR(__xludf.DUMMYFUNCTION("REGEXEXTRACT(A42, ""-(.*)"")"),"ARP.0044.04.2025.GOV.FES-PE.PE") -> ARP.0044.04.2025.GOV.FES-PE.PE | F42: Formação de Registro de Preços para o fornecimento eventual de dispositivos médicos do Tipo DRENOS visando atender as necessidades dos hospitais e estabelecimentos vinculados à Secretaria Estadual de Saúde de Pernambuco, conforme as condições, especificações, quantidades e exigências contidas no Termo de Referência | G42: NFOCPO | H42: 45923 | I42: Encaminhada para anuência do gestor | J42: =VLOOKUP(A42,'TODOS OS PROCESSOS ATUALIZADOS '!A:I,7,0) -> Encaminhada para anuência do gestor | K42: Em andamento | L42: =IFERROR(IF(J42=I42, "Item não atualizado", "Item atualizado"), "Item não localizado") -> Item não atualizado | M42: Jean | N42: Em andamento | O42: Enviado a NFOCPO | P42: 2300001213.000401/2025-61 | Q42: Finalizar com o nucleo
A43: A.002-ARP.0021.00.2025.GOV.HOF.PE | B43: =IFERROR(__xludf.DUMMYFUNCTION("REGEXEXTRACT(A43, ""\.(?:GOV|EXT)\.([A-Z0-9\-]+)"") "),"HOF") -> HOF | C43: HOSPITAL REGIONAL DO AGRESTE DR.WALDEMIRO FERREIRA | D43: Adesão | E43: =IFERROR(__xludf.DUMMYFUNCTION("REGEXEXTRACT(A43, ""-(.*)"")"),"ARP.0021.00.2025.GOV.HOF.PE") -> ARP.0021.00.2025.GOV.HOF.PE | F43: Formação de Registro de Preços para o fornecimento de OPME(s)do tipo Medicina Esportiva, sob sistema de consignação, visando atender as necessidades do Hospital Otávio de Freitas - HOF e Hospital Regional do Agreste - HRA, conforme as condições, especificações, quantidades e exigências contidas nos Estudos Técnicos Preliminares e neste Termo de Referência | G43: NFOCPO | H43: 45943 | I43: Concluído | J43: =VLOOKUP(A43,'TODOS OS PROCESSOS ATUALIZADOS '!A:I,7,0) -> Autorizada Sucesso | K43: Concluído | L43: =IFERROR(IF(J43=I43, "Item não atualizado", "Item atualizado"), "Item não localizado") -> Item atualizado | N43: Em andamento | O43: Enviado ao JURIDICO | P43: 2300002944.000001/2025-64
A44: A.002-ARP.0009.03.2025.GOV.HGV.PE | B44: =IFERROR(__xludf.DUMMYFUNCTION("REGEXEXTRACT(A44, ""\.(?:GOV|EXT)\.([A-Z0-9\-]+)"") "),"HGV") -> HGV | C44: HOSPITAL REGIONAL DO AGRESTE DR.WALDEMIRO FERREIRA | D44: Adesão | E44: =IFERROR(__xludf.DUMMYFUNCTION("REGEXEXTRACT(A44, ""-(.*)"")"),"ARP.0009.03.2025.GOV.HGV.PE") -> ARP.0009.03.2025.GOV.HGV.PE | F44: Formação de Registro de Preços para o fornecimento de OPME(s) do tipo GRAMPEADOR CIRURGICO, visando atender as necessidades dos HOSPITAL GETULIO VARGAS, conforme as condições, especificações, quantidades e exigências contidas no anexo I do Edital. | G44: NFOCPO | H44: 45925 | I44: Concluído | J44: =VLOOKUP(A44,'TODOS OS PROCESSOS ATUALIZADOS '!A:I,7,0) -> Autorizada Sucesso | K44: Concluído | L44: =IFERROR(IF(J44=I44, "Item não atualizado", "Item atualizado"), "Item não localizado") -> Item atualizado | N44: Em andamento | O44: Enviado a NFOCPO | P44: 2300001213.000396/2025-97
A45: A.002-ARP.0009.02.2025.GOV.HGV.PE | B45: =IFERROR(__xludf.DUMMYFUNCTION("REGEXEXTRACT(A45, ""\.(?:GOV|EXT)\.([A-Z0-9\-]+)"") "),"HGV") -> HGV | C45: HOSPITAL REGIONAL DO AGRESTE DR.WALDEMIRO FERREIRA | D45: Adesão | E45: =IFERROR(__xludf.DUMMYFUNCTION("REGEXEXTRACT(A45, ""-(.*)"")"),"ARP.0009.02.2025.GOV.HGV.PE") -> ARP.0009.02.2025.GOV.HGV.PE | F45: Formação de Registro de Preços para o fornecimento de OPME(s) do tipo GRAMPEADOR CIRURGICO, visando atender as necessidades dos HOSPITAL GETULIO VARGAS, conforme as condições, especificações, quantidades e exigências contidas no anexo I do Edital. | H45: 45917 | I45: Concluído | J45: =VLOOKUP(A45,'TODOS OS PROCESSOS ATUALIZADOS '!A:I,7,0) -> Autorizada Sucesso | K45: Concluído | L45: =IFERROR(IF(J45=I45, "Item não atualizado", "Item atualizado"), "Item não localizado") -> Item atualizado | N45: Concluído | O45: Enviado ao NOF | P45: 2300001213.000394/2025-06
A46: A.002-ARP.0009.01.2025.EXT.HMAR.PE | B46: =IFERROR(__xludf.DUMMYFUNCTION("REGEXEXTRACT(A46, ""\.(?:GOV|EXT)\.([A-Z0-9\-]+)"") "),"HMAR") -> HMAR | C46: HOSPITAL REGIONAL DO AGRESTE DR.WALDEMIRO FERREIRA | D46: Adesão | E46: =IFERROR(__xludf.DUMMYFUNCTION("REGEXEXTRACT(A46, ""-(.*)"")"),"ARP.0009.01.2025.EXT.HMAR.PE") -> ARP.0009.01.2025.EXT.HMAR.PE | F46: Registro de preços para eventual aquisição de produtos para saúde - MMH4 , visando atenderas necessidades do Hospital do Hospital Militar de Área de Recife (HMAR) | G46: NFOCPO | H46: 45918 | I46: Em revisão | J46: =VLOOKUP(A46,'TODOS OS PROCESSOS ATUALIZADOS '!A:I,7,0) -> Cancelada | K46: Em andamento | L46: =IFERROR(IF(J46=I46, "Item não atualizado", "Item atualizado"), "Item não localizado") -> Item atualizado | M46: Polyana | N46: Em andamento | O46: Enviado a NFOCPO | P46: 2300001213.000378/2025-13 | Q46: Finalizar com o nucleo
A47: A.001-ARP.0089.06.2025.GOV.HUOC.PE | B47: =IFERROR(__xludf.DUMMYFUNCTION("REGEXEXTRACT(A47, ""\.(?:GOV|EXT)\.([A-Z0-9\-]+)"") "),"HUOC") -> HUOC | C47: HOSPITAL REGIONAL DO AGRESTE DR.WALDEMIRO FERREIRA | D47: Adesão | E47: =IFERROR(__xludf.DUMMYFUNCTION("REGEXEXTRACT(A47, ""-(.*)"")"),"ARP.0089.06.2025.GOV.HUOC.PE") -> ARP.0089.06.2025.GOV.HUOC.PE | F47: Registro de Preços para a eventual fornecimento de MATERIAIS MÉDICOS HOSPITALARES - CATETERES DIVERSOS (SEI: 0040609912.000101/2024-31) | H47: 45933 | I47: Concluído | J47: =VLOOKUP(A47,'TODOS OS PROCESSOS ATUALIZADOS '!A:I,7,0) -> Autorizada Sucesso | K47: Concluído | L47: =IFERROR(IF(J47=I47, "Item não atualizado", "Item atualizado"), "Item não localizado") -> Item atualizado | N47: Em andamento | O47: Enviado ao GFIN | P47: 2300001213.000373/2025-82
A48: A.001-ARP.0068.04.2025.GOV.FES-PE.PE | B48: =IFERROR(__xludf.DUMMYFUNCTION("REGEXEXTRACT(A48, ""\.(?:GOV|EXT)\.([A-Z0-9\-]+)"") "),"FES-PE") -> FES-PE | C48: HOSPITAL REGIONAL DO AGRESTE DR.WALDEMIRO FERREIRA | D48: Adesão | E48: =IFERROR(__xludf.DUMMYFUNCTION("REGEXEXTRACT(A48, ""-(.*)"")"),"ARP.0068.04.2025.GOV.FES-PE.PE") -> ARP.0068.04.2025.GOV.FES-PE.PE | F48: FORMAÇÃO DE REGISTRO DE PREÇOS PARA O FORNECIMENTO DE DISPOSITIVOS MÉDICOS, DO TIPO INSUMOS PARA OSTOMIA, VISANDO ATENDER AS NECESSIDADES DOS HOSPITAIS E ESTABELECIMENTOS VINCULADOS À SECRETARIA ESTADUAL DE SAÚDE DE PERNAMBUCO | G48: NFOCPO | H48: 45918 | I48: Concluído | J48: =VLOOKUP(A48,'TODOS OS PROCESSOS ATUALIZADOS '!A:I,7,0) -> Autorizada Sucesso | K48: Concluído | L48: =IFERROR(IF(J48=I48, "Item não atualizado", "Item atualizado"), "Item não localizado") -> Item atualizado | N48: Em andamento | O48: Enviado ao GFIN | P48: 2300001213.000384/2025-62
A49: A.001-ARP.0021.00.2025.GOV.HOF.PE | B49: =IFERROR(__xludf.DUMMYFUNCTION("REGEXEXTRACT(A49, ""\.(?:GOV|EXT)\.([A-Z0-9\-]+)"") "),"HOF") -> HOF | C49: HOSPITAL REGIONAL DO AGRESTE DR.WALDEMIRO FERREIRA | D49: Adesão | E49: =IFERROR(__xludf.DUMMYFUNCTION("REGEXEXTRACT(A49, ""-(.*)"")"),"ARP.0021.00.2025.GOV.HOF.PE") -> ARP.0021.00.2025.GOV.HOF.PE | F49: Formação de Registro de Preços para o fornecimento de OPME(s)do tipo Medicina Esportiva, sob sistema de consignação, visando atender as necessidades do Hospital Otávio de Freitas - HOF e Hospital Regional do Agreste - HRA, conforme as condições, especificações, quantidades e exigências contidas nos Estudos Técnicos Preliminares e neste Termo de Referência | H49: 45943 | I49: Cancelada | J49: =VLOOKUP(A49,'TODOS OS PROCESSOS ATUALIZADOS '!A:I,7,0) -> Cancelada | K49: Cancelado | L49: =IFERROR(IF(J49=I49, "Item não atualizado", "Item atualizado"), "Item não localizado") -> Item não atualizado | N49: Cancelado | O49: SEI não localizado
A50: A.001-ARP.0020.00.2024.GOV.HOF.PE | B50: =IFERROR(__xludf.DUMMYFUNCTION("REGEXEXTRACT(A50, ""\.(?:GOV|EXT)\.([A-Z0-9\-]+)"") "),"HOF") -> HOF | C50: HOSPITAL REGIONAL DO AGRESTE DR.WALDEMIRO FERREIRA | D50: Adesão | E50: =IFERROR(__xludf.DUMMYFUNCTION("REGEXEXTRACT(A50, ""-(.*)"")"),"ARP.0020.00.2024.GOV.HOF.PE") -> ARP.0020.00.2024.GOV.HOF.PE | F50: Formação de registro de preços para o fornecimento eventual dos insumos de Órtese, Próteses e Materiais Especiais para cirurgias de coluna - Deformidades Infantil, em sistema de consignação, para atender demandas judiciais e necessidades específicas de crianças pernambucanas com deformidade na coluna vertebral, através do Hospital Otávio de Freitas | G50: NFOCPO | H50: 45940 | I50: Concluído | J50: =VLOOKUP(A50,'TODOS OS PROCESSOS ATUALIZADOS '!A:I,7,0) -> Autorizada Sucesso | K50: Concluído | L50: =IFERROR(IF(J50=I50, "Item não atualizado", "Item atualizado"), "Item não localizado") -> Item atualizado | N50: Em andamento | O50: Enviado ao JURIDICO | P50: 2300001213.000420/2025-98
A51: A.001-ARP.0011.03.2025.GOV.HGV.PE | B51: =IFERROR(__xludf.DUMMYFUNCTION("REGEXEXTRACT(A51, ""\.(?:GOV|EXT)\.([A-Z0-9\-]+)"") "),"HGV") -> HGV | C51: HOSPITAL REGIONAL DO AGRESTE DR.WALDEMIRO FERREIRA | D51: Adesão | E51: =IFERROR(__xludf.DUMMYFUNCTION("REGEXEXTRACT(A51, ""-(.*)"")"),"ARP.0011.03.2025.GOV.HGV.PE") -> ARP.0011.03.2025.GOV.HGV.PE | F51: Formação de Registro de Preços para o fornecimento eventual de SMS - EMBALAGENS DESCARTÁVEIS PARA ESTERILIZAÇÃO visando atender a demanda do Hospital Getúlio Vargas conforme condições, especificações, quantidades e exigências contidas neste Termo de Referência. | G51: NAEN | H51: 45918 | I51: Concluído | J51: =VLOOKUP(A51,'TODOS OS PROCESSOS ATUALIZADOS '!A:I,7,0) -> Autorizada Sucesso | K51: Concluído | L51: =IFERROR(IF(J51=I51, "Item não atualizado", "Item atualizado"), "Item não localizado") -> Item atualizado | M51: Hannah | N51: Em andamento | O51: Enviado ao GFIN | P51: 2300001213.000387/2025-04
A52: C.007-ARP.0073.00.2025.GOV.FES-PE.PE | B52: =IFERROR(__xludf.DUMMYFUNCTION("REGEXEXTRACT(A52, ""\.(?:GOV|EXT)\.([A-Z0-9\-]+)"") "),"FES-PE") -> FES-PE | C52: HOSPITAL REGIONAL DO AGRESTE DR.WALDEMIRO FERREIRA | D52: Adesão | E52: =IFERROR(__xludf.DUMMYFUNCTION("REGEXEXTRACT(A52, ""-(.*)"")"),"ARP.0073.00.2025.GOV.FES-PE.PE") -> ARP.0073.00.2025.GOV.FES-PE.PE | F52: Registro de Preços para o fornecimento eventual de Dispositivos Médicos do tipo Materiais Médicos (Indicadores, cera, e cimento cirúrgico), conforme especificações e quantitativos previstos no Termo de Referência, visando atender as necessidades dos hospitais e estabelecimentos vinculados à Secretaria Estadual de Saúde de Pernambuco | G52: NFOCPO | H52: 45883 | I52: Cancelada | J52: =VLOOKUP(A52,'TODOS OS PROCESSOS ATUALIZADOS '!A:I,7,0) -> Cancelada | K52: Cancelado | L52: =IFERROR(IF(J52=I52, "Item não atualizado", "Item atualizado"), "Item não localizado") -> Item não atualizado | N52: Cancelado
A53: A.026-ARP.0089.01.2024.GOV.HUOC.PE | B53: =IFERROR(__xludf.DUMMYFUNCTION("REGEXEXTRACT(A53, ""\.(?:GOV|EXT)\.([A-Z0-9\-]+)"") "),"HUOC") -> HUOC | C53: HOSPITAL REGIONAL DO AGRESTE DR.WALDEMIRO FERREIRA | D53: Adesão | E53: =IFERROR(__xludf.DUMMYFUNCTION("REGEXEXTRACT(A53, ""-(.*)"")"),"ARP.0089.01.2024.GOV.HUOC.PE") -> ARP.0089.01.2024.GOV.HUOC.PE | F53: Registro de Preços para o fornecimento eventual de MEDICAMENTOS ANTIMICROBIANOS (SEI Nº 0040609437.000129/2024-21) | H53: 45911 | I53: Cancelada | J53: =VLOOKUP(A53,'TODOS OS PROCESSOS ATUALIZADOS '!A:I,7,0) -> Cancelada por fim vigencia ATA | K53: Cancelado | L53: =IFERROR(IF(J53=I53, "Item não atualizado", "Item atualizado"), "Item não localizado") -> Item atualizado | N53: Cancelado | O53: SEI não localizado
A54: A.025-ARP.0089.01.2024.GOV.HUOC.PE | B54: =IFERROR(__xludf.DUMMYFUNCTION("REGEXEXTRACT(A54, ""\.(?:GOV|EXT)\.([A-Z0-9\-]+)"") "),"HUOC") -> HUOC | C54: HOSPITAL REGIONAL DO AGRESTE DR.WALDEMIRO FERREIRA | D54: Adesão | E54: =IFERROR(__xludf.DUMMYFUNCTION("REGEXEXTRACT(A54, ""-(.*)"")"),"ARP.0089.01.2024.GOV.HUOC.PE") -> ARP.0089.01.2024.GOV.HUOC.PE | F54: Registro de Preços para o fornecimento eventual de MEDICAMENTOS ANTIMICROBIANOS (SEI Nº 0040609437.000129/2024-21) | H54: 45910 | I54: Cancelada | J54: =VLOOKUP(A54,'TODOS OS PROCESSOS ATUALIZADOS '!A:I,7,0) -> Cancelada por fim vigencia ATA | K54: Cancelado | L54: =IFERROR(IF(J54=I54, "Item não atualizado", "Item atualizado"), "Item não localizado") -> Item atualizado | N54: Cancelado | O54: SEI não localizado
A55: A.022-ARP.0002.00.2025.GOV.FES-PE.PE | B55: =IFERROR(__xludf.DUMMYFUNCTION("REGEXEXTRACT(A55, ""\.(?:GOV|EXT)\.([A-Z0-9\-]+)"") "),"FES-PE") -> FES-PE | C55: HOSPITAL REGIONAL DO AGRESTE DR.WALDEMIRO FERREIRA | D55: Adesão | E55: =IFERROR(__xludf.DUMMYFUNCTION("REGEXEXTRACT(A55, ""-(.*)"")"),"ARP.0002.00.2025.GOV.FES-PE.PE") -> ARP.0002.00.2025.GOV.FES-PE.PE | F55: REGISTRO DE PREÇOS (ARP) PARA FORNECIMENTO DE MEDICAMENTOS DIVERSOS ORAIS/TÓPICOS - VOLUME 2 PARA ATENDER AO HOSPITAL JABOATÃO PRAZERES | H55: 45883 | I55: Concluído | J55: =VLOOKUP(A55,'TODOS OS PROCESSOS ATUALIZADOS '!A:I,7,0) -> Autorizada Sucesso | K55: Concluído | L55: =IFERROR(IF(J55=I55, "Item não atualizado", "Item atualizado"), "Item não localizado") -> Item atualizado | N55: Concluído | O55: Enviado ao NOF | P55: 2300001213.000329/2025-72
A56: A.018-ARP.0038.03.2025.GOV.HUOC.PE | B56: =IFERROR(__xludf.DUMMYFUNCTION("REGEXEXTRACT(A56, ""\.(?:GOV|EXT)\.([A-Z0-9\-]+)"") "),"HUOC") -> HUOC | C56: HOSPITAL REGIONAL DO AGRESTE DR.WALDEMIRO FERREIRA | D56: Adesão | E56: =IFERROR(__xludf.DUMMYFUNCTION("REGEXEXTRACT(A56, ""-(.*)"")"),"ARP.0038.03.2025.GOV.HUOC.PE") -> ARP.0038.03.2025.GOV.HUOC.PE | F56: Registro de Preços para a eventual fornecimento de Medicamentos Clínicos Gerais (3) SEI 0040609437.000169/2024-72 | H56: 45884 | I56: Concluído | J56: =VLOOKUP(A56,'TODOS OS PROCESSOS ATUALIZADOS '!A:I,7,0) -> Autorizada Sucesso | K56: Concluído | L56: =IFERROR(IF(J56=I56, "Item não atualizado", "Item atualizado"), "Item não localizado") -> Item atualizado | N56: Concluído | O56: Enviado ao NOF | P56: 2300001213.000282/2025-47
A57: A.015-ARP.0017.00.2025.GOV.HUOC.PE | B57: =IFERROR(__xludf.DUMMYFUNCTION("REGEXEXTRACT(A57, ""\.(?:GOV|EXT)\.([A-Z0-9\-]+)"") "),"HUOC") -> HUOC | C57: HOSPITAL REGIONAL DO AGRESTE DR.WALDEMIRO FERREIRA | D57: Adesão | E57: =IFERROR(__xludf.DUMMYFUNCTION("REGEXEXTRACT(A57, ""-(.*)"")"),"ARP.0017.00.2025.GOV.HUOC.PE") -> ARP.0017.00.2025.GOV.HUOC.PE | F57: Registro de Preços para a eventual fornecimento de REAGENTES PARA O LABORATÓRIO CLINICO COM CESSÃO DE EQUIPAMENTOS EM REGIME DE COMODATO PARA REALIZAÇÃO DE DOSAGEM EM BIOQUÍMICA, HORMÔNIOS E MARCADORES TUMORAIS (SEI Nº 0040609536.000028/2024-31) | G57: NSADRE | H57: 45904 | I57: Encaminhada para o gestor central de ata | J57: =VLOOKUP(A57,'TODOS OS PROCESSOS ATUALIZADOS '!A:I,7,0) -> Aguardando aprovação do gestor de ata | K57: Em andamento | L57: =IFERROR(IF(J57=I57, "Item não atualizado", "Item atualizado"), "Item não localizado") -> Item atualizado | M57: Elsia | N57: Em andamento | O57: Enviado a GCONTRATOS | P57: 2300001209.000065/2025-16 | Q57: Finalizar com o nucleo
A58: A.013-ARP.0122.00.2025.GOV.HUOC.PE | B58: =IFERROR(__xludf.DUMMYFUNCTION("REGEXEXTRACT(A58, ""\.(?:GOV|EXT)\.([A-Z0-9\-]+)"") "),"HUOC") -> HUOC | C58: HOSPITAL REGIONAL DO AGRESTE DR.WALDEMIRO FERREIRA | D58: Adesão | E58: =IFERROR(__xludf.DUMMYFUNCTION("REGEXEXTRACT(A58, ""-(.*)"")"),"ARP.0122.00.2025.GOV.HUOC.PE") -> ARP.0122.00.2025.GOV.HUOC.PE | F58: Registro de Preços para o eventual fornecimento de MEDICAMENTOS CONTROLADOS ORAIS (PORTARIA 344/98) (SEI Nº 0040609437.000080/2025-97) | H58: 45910 | I58: Concluído | J58: =VLOOKUP(A58,'TODOS OS PROCESSOS ATUALIZADOS '!A:I,7,0) -> Autorizada Sucesso | K58: Concluído | L58: =IFERROR(IF(J58=I58, "Item não atualizado", "Item atualizado"), "Item não localizado") -> Item atualizado | N58: Concluído | O58: Enviado ao NOF | P58: 2300001213.000352/2025-67
A59: A.013-ARP.0021.01.2024.GOV.HOF.PE | B59: =IFERROR(__xludf.DUMMYFUNCTION("REGEXEXTRACT(A59, ""\.(?:GOV|EXT)\.([A-Z0-9\-]+)"") "),"HOF") -> HOF | C59: HOSPITAL REGIONAL DO AGRESTE DR.WALDEMIRO FERREIRA | D59: Adesão | E59: =IFERROR(__xludf.DUMMYFUNCTION("REGEXEXTRACT(A59, ""-(.*)"")"),"ARP.0021.01.2024.GOV.HOF.PE") -> ARP.0021.01.2024.GOV.HOF.PE | F59: Formação de Registro de Preços para o fornecimento eventual de Material Médico Hospitalar INSUMOS PARA HIGIENE E PROTEÇÃO, visando atender a necessidade do do Hospital Otávio de Freitas (HOF), Hospital Regional do Agreste (HRA), Hospital Getúlio Vargas (HGV), Hospital Agamenon Magalhães (HAM), | H59: 45897 | I59: Concluído | J59: =VLOOKUP(A59,'TODOS OS PROCESSOS ATUALIZADOS '!A:I,7,0) -> Autorizada Sucesso | K59: Concluído | L59: =IFERROR(IF(J59=I59, "Item não atualizado", "Item atualizado"), "Item não localizado") -> Item atualizado | N59: Em andamento | O59: Enviado ao JURIDICO | P59: 2300001213.000336/2025-74
A60: A.013-ARP.0013.00.2024.GOV.HAM.PE | B60: =IFERROR(__xludf.DUMMYFUNCTION("REGEXEXTRACT(A60, ""\.(?:GOV|EXT)\.([A-Z0-9\-]+)"") "),"HAM") -> HAM | C60: HOSPITAL REGIONAL DO AGRESTE DR.WALDEMIRO FERREIRA | D60: Adesão | E60: =IFERROR(__xludf.DUMMYFUNCTION("REGEXEXTRACT(A60, ""-(.*)"")"),"ARP.0013.00.2024.GOV.HAM.PE") -> ARP.0013.00.2024.GOV.HAM.PE | F60: REGISTRO DE PREÇOS PARA EVENTUAL AQUISIÇÃO DE EQUIPAMENTO PARA UNITARIZAÇÃO DE MEDICAMENTOS | H60: 45884 | I60: Concluído | J60: =VLOOKUP(A60,'TODOS OS PROCESSOS ATUALIZADOS '!A:I,7,0) -> Autorizada Sucesso | K60: Concluído | L60: =IFERROR(IF(J60=I60, "Item não atualizado", "Item atualizado"), "Item não localizado") -> Item atualizado | N60: Concluído | O60: Enviado ao NOF | P60: 2300001213.000176/2025-63
A61: A.012-ARP.0004.00.2025.GOV.HR.PE | B61: =IFERROR(__xludf.DUMMYFUNCTION("REGEXEXTRACT(A61, ""\.(?:GOV|EXT)\.([A-Z0-9\-]+)"") "),"HR") -> HR | C61: HOSPITAL REGIONAL DO AGRESTE DR.WALDEMIRO FERREIRA | D61: Adesão | E61: =IFERROR(__xludf.DUMMYFUNCTION("REGEXEXTRACT(A61, ""-(.*)"")"),"ARP.0004.00.2025.GOV.HR.PE") -> ARP.0004.00.2025.GOV.HR.PE | F61: Formação de Ata de Registro de Preços para o fornecimento eventual de produtos médicos (MATERIAL MÉDICO HOSPITALAR), com cessão de equipamentos em regime de comodato, visando atender as necessidades do Hospital da Restauração Gov. Paulo Guerra. | H61: 45904 | I61: Concluído | J61: =VLOOKUP(A61,'TODOS OS PROCESSOS ATUALIZADOS '!A:I,7,0) -> Autorizada Sucesso | K61: Concluído | L61: =IFERROR(IF(J61=I61, "Item não atualizado", "Item atualizado"), "Item não localizado") -> Item atualizado | N61: Concluído | O61: Enviado ao NOF | P61: 2300001213.000359/2025-89
A62: A.011-ARP.0017.00.2025.EXT.131763.PB | B62: =IFERROR(__xludf.DUMMYFUNCTION("REGEXEXTRACT(A62, ""\.(?:GOV|EXT)\.([A-Z0-9\-]+)"") "),"131763") -> 131763 | C62: HOSPITAL REGIONAL DO AGRESTE DR.WALDEMIRO FERREIRA | D62: Adesão | E62: =IFERROR(__xludf.DUMMYFUNCTION("REGEXEXTRACT(A62, ""-(.*)"")"),"ARP.0017.00.2025.EXT.131763.PB") -> ARP.0017.00.2025.EXT.131763.PB | F62: A presente Ata tem por objetivo o registro de preços PARA REGISTRO DE PREÇO PARA AQUISIÇÃO DE MEDICAMENTOS ANTIBACTERIANOS INJETÁVEIS especificado, no item 1.1 do Termo de Referência, anexo no edital de Pregão 173/2024 que é parte integrante desta Ata, assim como as propostas cujos preços tenham sido registrados, independentemente da transcrição. | H62: 45910 | I62: Concluído | J62: =VLOOKUP(A62,'TODOS OS PROCESSOS ATUALIZADOS '!A:I,7,0) -> Autorizada Integrado | K62: Concluído | L62: =IFERROR(IF(J62=I62, "Item não atualizado", "Item atualizado"), "Item não localizado") -> Item atualizado | N62: Cancelado | O62: Enviado a NFOCPO | P62: 2300001213.000190/2025-67
A63: A.011-ARP.0013.02.2025.GOV.HOF.PE | B63: =IFERROR(__xludf.DUMMYFUNCTION("REGEXEXTRACT(A63, ""\.(?:GOV|EXT)\.([A-Z0-9\-]+)"") "),"HOF") -> HOF | C63: HOSPITAL REGIONAL DO AGRESTE DR.WALDEMIRO FERREIRA | D63: Adesão | E63: =IFERROR(__xludf.DUMMYFUNCTION("REGEXEXTRACT(A63, ""-(.*)"")"),"ARP.0013.02.2025.GOV.HOF.PE") -> ARP.0013.02.2025.GOV.HOF.PE | F63: REGISTRO DE PREÇOS PARA O FORNECIMENTO DE DISPOSITIVOS MÉDICOS DO TIPO INSUMOS PARA OXIGENOTERAPIA, VISANDO ATENDER AS NECESSIDADES DO HOSPITAL OTÁVIO DE FREITAS. | G63: NAEN | H63: 45909 | I63: Cancelada | J63: =VLOOKUP(A63,'TODOS OS PROCESSOS ATUALIZADOS '!A:I,7,0) -> Em configuração | K63: Cancelar Com o Suporte | L63: =IFERROR(IF(J63=I63, "Item não atualizado", "Item atualizado"), "Item não localizado") -> Item atualizado | N63: Cancelar Com o Suporte | O63: SEI não localizado
A64: A.011-ARP.0012.07.2025.GOV.HAM.PE | B64: =IFERROR(__xludf.DUMMYFUNCTION("REGEXEXTRACT(A64, ""\.(?:GOV|EXT)\.([A-Z0-9\-]+)"") "),"HAM") -> HAM | C64: HOSPITAL REGIONAL DO AGRESTE DR.WALDEMIRO FERREIRA | D64: Adesão | E64: =IFERROR(__xludf.DUMMYFUNCTION("REGEXEXTRACT(A64, ""-(.*)"")"),"ARP.0012.07.2025.GOV.HAM.PE") -> ARP.0012.07.2025.GOV.HAM.PE | F64: Registro de Preços para o fornecimento eventual de material de consumo (aquisição de materiais de almoxarifado) visando atender as necessidades do Hospital Agamenon Magalhães, Hospital Otávio de Freitas, Hospital Regional do Agreste e da Secretaria de Saúde | G64: NAMP | H64: 45898 | I64: Concluído | J64: =VLOOKUP(A64,'TODOS OS PROCESSOS ATUALIZADOS '!A:I,7,0) -> Autorizada Sucesso | K64: Concluído | L64: =IFERROR(IF(J64=I64, "Item não atualizado", "Item atualizado"), "Item não localizado") -> Item atualizado | M64: Elsia | N64: Em andamento | O64: Enviado ao JURIDICO | P64: 2300002544.000068/2025-10
A65: A.010-ARP.0106.00.2025.GOV.HUOC.PE | B65: =IFERROR(__xludf.DUMMYFUNCTION("REGEXEXTRACT(A65, ""\.(?:GOV|EXT)\.([A-Z0-9\-]+)"") "),"HUOC") -> HUOC | C65: HOSPITAL REGIONAL DO AGRESTE DR.WALDEMIRO FERREIRA | D65: Adesão | E65: =IFERROR(__xludf.DUMMYFUNCTION("REGEXEXTRACT(A65, ""-(.*)"")"),"ARP.0106.00.2025.GOV.HUOC.PE") -> ARP.0106.00.2025.GOV.HUOC.PE | F65: Registro de Preços para o eventual fornecimento de MEDICAMENTOS CONTROLADOS INJETÁVEIS - Portaria 344/98 (SEI Nº 0040609437.000073/2025-95) | H65: 45894 | I65: Concluído | J65: =VLOOKUP(A65,'TODOS OS PROCESSOS ATUALIZADOS '!A:I,7,0) -> Autorizada Sucesso | K65: Concluído | L65: =IFERROR(IF(J65=I65, "Item não atualizado", "Item atualizado"), "Item não localizado") -> Item atualizado | N65: Em andamento | O65: Enviado a GCONTRATOS | P65: 2300001213.000308/2025-57
A66: A.010-ARP.0059.02.2025.GOV.PROCAPE.PE | B66: =IFERROR(__xludf.DUMMYFUNCTION("REGEXEXTRACT(A66, ""\.(?:GOV|EXT)\.([A-Z0-9\-]+)"") "),"PROCAPE") -> PROCAPE | C66: HOSPITAL REGIONAL DO AGRESTE DR.WALDEMIRO FERREIRA | D66: Adesão | E66: =IFERROR(__xludf.DUMMYFUNCTION("REGEXEXTRACT(A66, ""-(.*)"")"),"ARP.0059.02.2025.GOV.PROCAPE.PE") -> ARP.0059.02.2025.GOV.PROCAPE.PE | F66: REGISTRO DE PREÇOS PARA EVENTUAL FORNECIMENTO DE MATERIAL DE CONSUMO HOSPITALAR (MATERIAL PENSO) | H66: 45896 | I66: Concluído | J66: =VLOOKUP(A66,'TODOS OS PROCESSOS ATUALIZADOS '!A:I,7,0) -> Autorizada Sucesso | K66: Concluído | L66: =IFERROR(IF(J66=I66, "Item não atualizado", "Item atualizado"), "Item não localizado") -> Item atualizado | N66: Concluído | O66: Enviado ao NOF | P66: 2300001213.000275/2025-45
A67: A.010-ARP.0012.07.2025.GOV.HAM.PE | B67: =IFERROR(__xludf.DUMMYFUNCTION("REGEXEXTRACT(A67, ""\.(?:GOV|EXT)\.([A-Z0-9\-]+)"") "),"HAM") -> HAM | C67: HOSPITAL REGIONAL DO AGRESTE DR.WALDEMIRO FERREIRA | D67: Adesão | E67: =IFERROR(__xludf.DUMMYFUNCTION("REGEXEXTRACT(A67, ""-(.*)"")"),"ARP.0012.07.2025.GOV.HAM.PE") -> ARP.0012.07.2025.GOV.HAM.PE | F67: Registro de Preços para o fornecimento eventual de material de consumo (aquisição de materiais de almoxarifado) visando atender as necessidades do Hospital Agamenon Magalhães, Hospital Otávio de Freitas, Hospital Regional do Agreste e da Secretaria de Saúde | G67: NAMP | H67: 45888 | I67: Cancelada | J67: =VLOOKUP(A67,'TODOS OS PROCESSOS ATUALIZADOS '!A:I,7,0) -> Cancelada | K67: Cancelado | L67: =IFERROR(IF(J67=I67, "Item não atualizado", "Item atualizado"), "Item não localizado") -> Item não atualizado | N67: Cancelado | O67: SEI não localizado
A68: A.009-ARP.0028.03.2025.GOV.PROCAPE.PE | B68: =IFERROR(__xludf.DUMMYFUNCTION("REGEXEXTRACT(A68, ""\.(?:GOV|EXT)\.([A-Z0-9\-]+)"") "),"PROCAPE") -> PROCAPE | C68: HOSPITAL REGIONAL DO AGRESTE DR.WALDEMIRO FERREIRA | D68: Adesão | E68: =IFERROR(__xludf.DUMMYFUNCTION("REGEXEXTRACT(A68, ""-(.*)"")"),"ARP.0028.03.2025.GOV.PROCAPE.PE") -> ARP.0028.03.2025.GOV.PROCAPE.PE | F68: REGISTRO DE PREÇOS PARA EVENTUAL FORNECIMENTO DE MATERIAL DE CONSUMO HOSPITALAR (MEDICAMENTOS) | H68: 45884 | I68: Concluído | J68: =VLOOKUP(A68,'TODOS OS PROCESSOS ATUALIZADOS '!A:I,7,0) -> Autorizada Sucesso | K68: Concluído | L68: =IFERROR(IF(J68=I68, "Item não atualizado", "Item atualizado"), "Item não localizado") -> Item atualizado | N68: Concluído | O68: Enviado ao NOF | P68: 2300001213.000309/2025-00
A69: A.008-ARP.0100.00.2024.GOV.HUOC.PE | B69: =IFERROR(__xludf.DUMMYFUNCTION("REGEXEXTRACT(A69, ""\.(?:GOV|EXT)\.([A-Z0-9\-]+)"") "),"HUOC") -> HUOC | C69: HOSPITAL REGIONAL DO AGRESTE DR.WALDEMIRO FERREIRA | D69: Adesão | E69: =IFERROR(__xludf.DUMMYFUNCTION("REGEXEXTRACT(A69, ""-(.*)"")"),"ARP.0100.00.2024.GOV.HUOC.PE") -> ARP.0100.00.2024.GOV.HUOC.PE | F69: Registro de Preços para a eventual fornecimento de REAGENTES PARA O LABORATÓRIO CLINICO COM CESSÃO DE EQUIPAMENTOS EM REGIME DE COMODATO PARA REALIZAÇÃO DE TESTES EM HEMOSTASIA (SEI Nº 0040609536.000027/2024-97) | H69: 45904 | I69: Concluído | J69: =VLOOKUP(A69,'TODOS OS PROCESSOS ATUALIZADOS '!A:I,7,0) -> Autorizada Sucesso | K69: Concluído | L69: =IFERROR(IF(J69=I69, "Item não atualizado", "Item atualizado"), "Item não localizado") -> Item atualizado | N69: Concluído | O69: Enviado ao NOF | P69: 2300001209.000057/2025-70
A70: A.008-ARP.0001.00.2025.GOV.SASSEPE.PE | B70: =IFERROR(__xludf.DUMMYFUNCTION("REGEXEXTRACT(A70, ""\.(?:GOV|EXT)\.([A-Z0-9\-]+)"") "),"SASSEPE") -> SASSEPE | C70: HOSPITAL REGIONAL DO AGRESTE DR.WALDEMIRO FERREIRA | D70: Adesão | E70: =IFERROR(__xludf.DUMMYFUNCTION("REGEXEXTRACT(A70, ""-(.*)"")"),"ARP.0001.00.2025.GOV.SASSEPE.PE") -> ARP.0001.00.2025.GOV.SASSEPE.PE | F70: Formação de Registro de Preços para o fornecimento de OPME(s) do tipo Material Cirúrgico do Vídeo Cirurgia – Lapsus com cessão em comodato de equipamentos , visando atender as necessidades do Hospital dos Servidores do Estado de Pernambuco – HSE, nos termos da legislação vigente, conforme as condições, especificações, quantidades e exigências contidas na Nota Técnica Nº 62/2024 (Doc. SEI nº 51234477) e no Termo de Referência | G70: NFOCPO | H70: 45904 | I70: Concluído | J70: =VLOOKUP(A70,'TODOS OS PROCESSOS ATUALIZADOS '!A:I,7,0) -> Autorizada Sucesso | K70: Concluído | L70: =IFERROR(IF(J70=I70, "Item não atualizado", "Item atualizado"), "Item não localizado") -> Item atualizado | N70: Em andamento | O70: Enviado ao GFIN | P70: 2300002544.000074/2025-69
A71: A.007-ARP.0106.02.2025.GOV.HUOC.PE | B71: =IFERROR(__xludf.DUMMYFUNCTION("REGEXEXTRACT(A71, ""\.(?:GOV|EXT)\.([A-Z0-9\-]+)"") "),"HUOC") -> HUOC | C71: HOSPITAL REGIONAL DO AGRESTE DR.WALDEMIRO FERREIRA | D71: Adesão | E71: =IFERROR(__xludf.DUMMYFUNCTION("REGEXEXTRACT(A71, ""-(.*)"")"),"ARP.0106.02.2025.GOV.HUOC.PE") -> ARP.0106.02.2025.GOV.HUOC.PE | F71: Registro de Preços para o eventual fornecimento de MEDICAMENTOS CONTROLADOS INJETÁVEIS - Portaria 344/98 (SEI Nº 0040609437.000073/2025-95) | H71: 45882 | I71: Concluído | J71: =VLOOKUP(A71,'TODOS OS PROCESSOS ATUALIZADOS '!A:I,7,0) -> Autorizada Sucesso | K71: Concluído | L71: =IFERROR(IF(J71=I71, "Item não atualizado", "Item atualizado"), "Item não localizado") -> Item atualizado | N71: Concluído | O71: Enviado ao NOF | P71: 2300001213.000289/2025-69
A72: A.007-ARP.0080.00.2025.GOV.FES-PE.PE | B72: =IFERROR(__xludf.DUMMYFUNCTION("REGEXEXTRACT(A72, ""\.(?:GOV|EXT)\.([A-Z0-9\-]+)"") "),"FES-PE") -> FES-PE | C72: HOSPITAL REGIONAL DO AGRESTE DR.WALDEMIRO FERREIRA | D72: Adesão | E72: =IFERROR(__xludf.DUMMYFUNCTION("REGEXEXTRACT(A72, ""-(.*)"")"),"ARP.0080.00.2025.GOV.FES-PE.PE") -> ARP.0080.00.2025.GOV.FES-PE.PE | F72: Formação de Registro de Preços para o fornecimento eventual de MEDICAMENTOS INJETÁVEIS VOL. 1 visando atender as necessidades do Hospital Jaboatão Prazeres. | H72: 45911 | I72: Concluído | J72: =VLOOKUP(A72,'TODOS OS PROCESSOS ATUALIZADOS '!A:I,7,0) -> Autorizada Sucesso | K72: Concluído | L72: =IFERROR(IF(J72=I72, "Item não atualizado", "Item atualizado"), "Item não localizado") -> Item atualizado | N72: Concluído | O72: Enviado ao NOF | P72: 2300001213.000383/2025-18
A73: A.007-ARP.0079.03.2025.GOV.HUOC.PE | B73: =IFERROR(__xludf.DUMMYFUNCTION("REGEXEXTRACT(A73, ""\.(?:GOV|EXT)\.([A-Z0-9\-]+)"") "),"HUOC") -> HUOC | C73: HOSPITAL REGIONAL DO AGRESTE DR.WALDEMIRO FERREIRA | D73: Adesão | E73: =IFERROR(__xludf.DUMMYFUNCTION("REGEXEXTRACT(A73, ""-(.*)"")"),"ARP.0079.03.2025.GOV.HUOC.PE") -> ARP.0079.03.2025.GOV.HUOC.PE | F73: Registro de Preços para o eventual fornecimento de MEDICAMENTOS MEDICAMENTOS CONTROLADOS (SEI: 0040609437.000303/2024-35) | H73: 45910 | I73: Concluído | J73: =VLOOKUP(A73,'TODOS OS PROCESSOS ATUALIZADOS '!A:I,7,0) -> Autorizada Sucesso | K73: Concluído | L73: =IFERROR(IF(J73=I73, "Item não atualizado", "Item atualizado"), "Item não localizado") -> Item atualizado | N73: Concluído | O73: Enviado ao NOF | P73: 2300001213.000345/2025-65
A74: A.007-ARP.0079.00.2025.GOV.HUOC.PE | B74: =IFERROR(__xludf.DUMMYFUNCTION("REGEXEXTRACT(A74, ""\.(?:GOV|EXT)\.([A-Z0-9\-]+)"") "),"HUOC") -> HUOC | C74: HOSPITAL REGIONAL DO AGRESTE DR.WALDEMIRO FERREIRA | D74: Adesão | E74: =IFERROR(__xludf.DUMMYFUNCTION("REGEXEXTRACT(A74, ""-(.*)"")"),"ARP.0079.00.2025.GOV.HUOC.PE") -> ARP.0079.00.2025.GOV.HUOC.PE | F74: Registro de Preços para o eventual fornecimento de MEDICAMENTOS MEDICAMENTOS CONTROLADOS (SEI: 0040609437.000303/2024-35) | H74: 45910 | I74: Concluído | J74: =VLOOKUP(A74,'TODOS OS PROCESSOS ATUALIZADOS '!A:I,7,0) -> Autorizada Sucesso | K74: Concluído | L74: =IFERROR(IF(J74=I74, "Item não atualizado", "Item atualizado"), "Item não localizado") -> Item atualizado | N74: Concluído | O74: Enviado ao NOF | P74: 2300001213.000354/2025-56
A75: A.006-ARP.0010.02.2025.GOV.HAM.PE | B75: =IFERROR(__xludf.DUMMYFUNCTION("REGEXEXTRACT(A75, ""\.(?:GOV|EXT)\.([A-Z0-9\-]+)"") "),"HAM") -> HAM | C75: HOSPITAL REGIONAL DO AGRESTE DR.WALDEMIRO FERREIRA | D75: Adesão | E75: =IFERROR(__xludf.DUMMYFUNCTION("REGEXEXTRACT(A75, ""-(.*)"")"),"ARP.0010.02.2025.GOV.HAM.PE") -> ARP.0010.02.2025.GOV.HAM.PE | F75: Registro de Preços para o fornecimento eventual de material médico hospitalar destinado ao serviço de anestesia, visando atender as necessidades do Hospital Agamenon Magalhães | H75: 45877 | I75: Concluído | J75: =VLOOKUP(A75,'TODOS OS PROCESSOS ATUALIZADOS '!A:I,7,0) -> Autorizada Sucesso | K75: Concluído | L75: =IFERROR(IF(J75=I75, "Item não atualizado", "Item atualizado"), "Item não localizado") -> Item atualizado | N75: Concluído | O75: Enviado ao NOF | P75: 2300001213.000244/2025-94
A76: A.005-ARP.0082.06.2025.GOV.HUOC.PE | B76: =IFERROR(__xludf.DUMMYFUNCTION("REGEXEXTRACT(A76, ""\.(?:GOV|EXT)\.([A-Z0-9\-]+)"") "),"HUOC") -> HUOC | C76: HOSPITAL REGIONAL DO AGRESTE DR.WALDEMIRO FERREIRA | D76: Adesão | E76: =IFERROR(__xludf.DUMMYFUNCTION("REGEXEXTRACT(A76, ""-(.*)"")"),"ARP.0082.06.2025.GOV.HUOC.PE") -> ARP.0082.06.2025.GOV.HUOC.PE | F76: Registro de Preços para o eventual fornecimento de MEDICAMENTOS CLÍNICOS GERAIS (SEI 0040609437.000017/2025-51) | H76: 45884 | I76: Concluído | J76: =VLOOKUP(A76,'TODOS OS PROCESSOS ATUALIZADOS '!A:I,7,0) -> Autorizada Sucesso | K76: Concluído | L76: =IFERROR(IF(J76=I76, "Item não atualizado", "Item atualizado"), "Item não localizado") -> Item atualizado | N76: Em andamento | O76: Enviado a NFOCPO | P76: 2300001213.000293/2025-27
A77: A.005-ARP.0064.01.2025.GOV.HUOC.PE | B77: =IFERROR(__xludf.DUMMYFUNCTION("REGEXEXTRACT(A77, ""\.(?:GOV|EXT)\.([A-Z0-9\-]+)"") "),"HUOC") -> HUOC | C77: HOSPITAL REGIONAL DO AGRESTE DR.WALDEMIRO FERREIRA | D77: Adesão | E77: =IFERROR(__xludf.DUMMYFUNCTION("REGEXEXTRACT(A77, ""-(.*)"")"),"ARP.0064.01.2025.GOV.HUOC.PE") -> ARP.0064.01.2025.GOV.HUOC.PE | F77: Registro de Preços para o eventual fornecimento de MEDICAMENTOS CLÍNICOS GERAIS 4 (12 ITENS) SEI: 0040609437.000004/2025-81 | G77: NFOCPO | H77: 45887 | I77: Cancelada | J77: =VLOOKUP(A77,'TODOS OS PROCESSOS ATUALIZADOS '!A:I,7,0) -> Em configuração | K77: Cancelar Com o Suporte | L77: =IFERROR(IF(J77=I77, "Item não atualizado", "Item atualizado"), "Item não localizado") -> Item atualizado | N77: Cancelar Com o Suporte | O77: SEI não localizado
A78: A.005-ARP.0059.00.2025.GOV.FES-PE.PE | B78: =IFERROR(__xludf.DUMMYFUNCTION("REGEXEXTRACT(A78, ""\.(?:GOV|EXT)\.([A-Z0-9\-]+)"") "),"FES-PE") -> FES-PE | C78: HOSPITAL REGIONAL DO AGRESTE DR.WALDEMIRO FERREIRA | D78: Adesão | E78: =IFERROR(__xludf.DUMMYFUNCTION("REGEXEXTRACT(A78, ""-(.*)"")"),"ARP.0059.00.2025.GOV.FES-PE.PE") -> ARP.0059.00.2025.GOV.FES-PE.PE | F78: FORMAÇÃO DE REGISTRO DE PREÇOS PARA O FORNECIMENTO DE DISPOSITIVOS MÉDICOS, DO TIPO BOLSAS PARA OSTOMIA, VISANDO ATENDER AS NECESSIDADES DOS HOSPITAIS E ESTABELECIMENTOS VINCULADOS À SECRETARIA ESTADUAL DE SAÚDE DE PERNAMBUCO. | H78: 45911 | I78: Cancelada | J78: =VLOOKUP(A78,'TODOS OS PROCESSOS ATUALIZADOS '!A:I,7,0) -> Cancelada | K78: Cancelado | L78: =IFERROR(IF(J78=I78, "Item não atualizado", "Item atualizado"), "Item não localizado") -> Item não atualizado | N78: Cancelado | O78: SEI não localizado
A79: A.005-ARP.0038.02.2025.GOV.HUOC.PE | B79: =IFERROR(__xludf.DUMMYFUNCTION("REGEXEXTRACT(A79, ""\.(?:GOV|EXT)\.([A-Z0-9\-]+)"") "),"HUOC") -> HUOC | C79: HOSPITAL REGIONAL DO AGRESTE DR.WALDEMIRO FERREIRA | D79: Adesão | E79: =IFERROR(__xludf.DUMMYFUNCTION("REGEXEXTRACT(A79, ""-(.*)"")"),"ARP.0038.02.2025.GOV.HUOC.PE") -> ARP.0038.02.2025.GOV.HUOC.PE | F79: Registro de Preços para a eventual fornecimento de Medicamentos Clínicos Gerais (3) SEI 0040609437.000169/2024-72 | H79: 45904 | I79: Concluído | J79: =VLOOKUP(A79,'TODOS OS PROCESSOS ATUALIZADOS '!A:I,7,0) -> Autorizada Sucesso | K79: Concluído | L79: =IFERROR(IF(J79=I79, "Item não atualizado", "Item atualizado"), "Item não localizado") -> Item atualizado | N79: Em andamento | O79: Enviado ao GFIN | P79: 2300001213.000261/2025-21
A80: A.005-ARP.0012.02.2025.GOV.HUOC.PE | B80: =IFERROR(__xludf.DUMMYFUNCTION("REGEXEXTRACT(A80, ""\.(?:GOV|EXT)\.([A-Z0-9\-]+)"") "),"HUOC") -> HUOC | C80: HOSPITAL REGIONAL DO AGRESTE DR.WALDEMIRO FERREIRA | D80: Adesão | E80: =IFERROR(__xludf.DUMMYFUNCTION("REGEXEXTRACT(A80, ""-(.*)"")"),"ARP.0012.02.2025.GOV.HUOC.PE") -> ARP.0012.02.2025.GOV.HUOC.PE | F80: Registro de Preço para o eventual fornecimento de REAGENTES E OUTROS INSUMOS DESTINADOS A AGÊNCIA TRANSFUSIONAL COM CESSÃO DE EQUIPAMENTOS A TÍTULO DE COMODATO, visando atender a necessidade das Unidades do Complexo Hospitalar da UPE - UCH/UPE (SEI Nº 0040609916.000029/2024-10) | H80: 45911 | I80: Concluído | J80: =VLOOKUP(A80,'TODOS OS PROCESSOS ATUALIZADOS '!A:I,7,0) -> Autorizada Sucesso | K80: Concluído | L80: =IFERROR(IF(J80=I80, "Item não atualizado", "Item atualizado"), "Item não localizado") -> Item atualizado | N80: Concluído | O80: Enviado ao NOF | P80: 2300002544.000050/2025-18
A81: A.004-ARP.0090.04.2025.GOV.HUOC.PE | B81: =IFERROR(__xludf.DUMMYFUNCTION("REGEXEXTRACT(A81, ""\.(?:GOV|EXT)\.([A-Z0-9\-]+)"") "),"HUOC") -> HUOC | C81: HOSPITAL REGIONAL DO AGRESTE DR.WALDEMIRO FERREIRA | D81: Adesão | E81: =IFERROR(__xludf.DUMMYFUNCTION("REGEXEXTRACT(A81, ""-(.*)"")"),"ARP.0090.04.2025.GOV.HUOC.PE") -> ARP.0090.04.2025.GOV.HUOC.PE | F81: Registro de Preços para a eventual fornecimento de Aquisição de materiais de expediente (SEI:0040609438.000048/2024-11) | H81: 45884 | I81: Concluído | J81: =VLOOKUP(A81,'TODOS OS PROCESSOS ATUALIZADOS '!A:I,7,0) -> Autorizada Sucesso | K81: Concluído | L81: =IFERROR(IF(J81=I81, "Item não atualizado", "Item atualizado"), "Item não localizado") -> Item atualizado | N81: Concluído | O81: Enviado ao NOF | P81: 2300001213.000315/2025-59
A82: A.004-ARP.0059.00.2025.GOV.FES-PE.PE | B82: =IFERROR(__xludf.DUMMYFUNCTION("REGEXEXTRACT(A82, ""\.(?:GOV|EXT)\.([A-Z0-9\-]+)"") "),"FES-PE") -> FES-PE | C82: HOSPITAL REGIONAL DO AGRESTE DR.WALDEMIRO FERREIRA | D82: Adesão | E82: =IFERROR(__xludf.DUMMYFUNCTION("REGEXEXTRACT(A82, ""-(.*)"")"),"ARP.0059.00.2025.GOV.FES-PE.PE") -> ARP.0059.00.2025.GOV.FES-PE.PE | F82: FORMAÇÃO DE REGISTRO DE PREÇOS PARA O FORNECIMENTO DE DISPOSITIVOS MÉDICOS, DO TIPO BOLSAS PARA OSTOMIA, VISANDO ATENDER AS NECESSIDADES DOS HOSPITAIS E ESTABELECIMENTOS VINCULADOS À SECRETARIA ESTADUAL DE SAÚDE DE PERNAMBUCO. | H82: 45911 | I82: Cancelada | J82: =VLOOKUP(A82,'TODOS OS PROCESSOS ATUALIZADOS '!A:I,7,0) -> Cancelada | K82: Cancelado | L82: =IFERROR(IF(J82=I82, "Item não atualizado", "Item atualizado"), "Item não localizado") -> Item não atualizado | N82: Cancelado | O82: SEI não localizado
A83: A.004-ARP.0045.00.2024.GOV.HR.PE | B83: =IFERROR(__xludf.DUMMYFUNCTION("REGEXEXTRACT(A83, ""\.(?:GOV|EXT)\.([A-Z0-9\-]+)"") "),"HR") -> HR | C83: HOSPITAL REGIONAL DO AGRESTE DR.WALDEMIRO FERREIRA | D83: Adesão | E83: =IFERROR(__xludf.DUMMYFUNCTION("REGEXEXTRACT(A83, ""-(.*)"")"),"ARP.0045.00.2024.GOV.HR.PE") -> ARP.0045.00.2024.GOV.HR.PE | F83: Formação de Registro de Preços para o eventual fornecimento de ÓRTESES, PRÓTESES E MATERIAIS ESPECIAIS – OPME’S (GRUPO COLUNA IV), visando atender as necessidades do Hospital da Restauração, nos termos da legislação vigente e do Documento de Formalização da Demanda presente nos autos e conforme as condições, especificações, quantidades e exigências contidas no Termo de Referência. | H83: 45896 | I83: Concluído | J83: =VLOOKUP(A83,'TODOS OS PROCESSOS ATUALIZADOS '!A:I,7,0) -> Autorizada Sucesso | K83: Concluído | L83: =IFERROR(IF(J83=I83, "Item não atualizado", "Item atualizado"), "Item não localizado") -> Item atualizado | N83: Em andamento | O83: Enviado a NFOCPO | P83: 2300002544.000069/2025-56
A84: A.004-ARP.0044.06.2025.GOV.FES-PE.PE | B84: =IFERROR(__xludf.DUMMYFUNCTION("REGEXEXTRACT(A84, ""\.(?:GOV|EXT)\.([A-Z0-9\-]+)"") "),"FES-PE") -> FES-PE | C84: HOSPITAL REGIONAL DO AGRESTE DR.WALDEMIRO FERREIRA | D84: Adesão | E84: =IFERROR(__xludf.DUMMYFUNCTION("REGEXEXTRACT(A84, ""-(.*)"")"),"ARP.0044.06.2025.GOV.FES-PE.PE") -> ARP.0044.06.2025.GOV.FES-PE.PE | F84: Formação de Registro de Preços para o fornecimento eventual de dispositivos médicos do Tipo DRENOS visando atender as necessidades dos hospitais e estabelecimentos vinculados à Secretaria Estadual de Saúde de Pernambuco, conforme as condições, especificações, quantidades e exigências contidas no Termo de Referência | G84: NFOCPO | H84: 45888 | I84: Cancelada | J84: =VLOOKUP(A84,'TODOS OS PROCESSOS ATUALIZADOS '!A:I,7,0) -> Em revisão | K84: Cancelar Com o Suporte | L84: =IFERROR(IF(J84=I84, "Item não atualizado", "Item atualizado"), "Item não localizado") -> Item atualizado | N84: Cancelar Com o Suporte | P84: 2300001213.000196/2025-34 | Q84: Cancelado Devido a não Autorização do Gestor
A85: A.004-ARP.0012.01.2025.GOV.HEMOPE.PE | B85: =IFERROR(__xludf.DUMMYFUNCTION("REGEXEXTRACT(A85, ""\.(?:GOV|EXT)\.([A-Z0-9\-]+)"") "),"HEMOPE") -> HEMOPE | C85: HOSPITAL REGIONAL DO AGRESTE DR.WALDEMIRO FERREIRA | D85: Adesão | E85: =IFERROR(__xludf.DUMMYFUNCTION("REGEXEXTRACT(A85, ""-(.*)"")"),"ARP.0012.01.2025.GOV.HEMOPE.PE") -> ARP.0012.01.2025.GOV.HEMOPE.PE | F85: Registro de Preços para o fornecimento eventual de insumos para Saúde GRUPO 2 , visando atender as necessidades do Hospital HEMOPE – Fundação de Hematologia e Hemoterapia de Pernambuco | H85: 45896 | I85: Concluído | J85: =VLOOKUP(A85,'TODOS OS PROCESSOS ATUALIZADOS '!A:I,7,0) -> Autorizada Sucesso | K85: Concluído | L85: =IFERROR(IF(J85=I85, "Item não atualizado", "Item atualizado"), "Item não localizado") -> Item atualizado | N85: Concluído | O85: Enviado ao NOF | P85: 2300001213.000326/2025-39
A86: A.004-ARP.0010.00.2025.GOV.HR.PE | B86: =IFERROR(__xludf.DUMMYFUNCTION("REGEXEXTRACT(A86, ""\.(?:GOV|EXT)\.([A-Z0-9\-]+)"") "),"HR") -> HR | C86: HOSPITAL REGIONAL DO AGRESTE DR.WALDEMIRO FERREIRA | D86: Adesão | E86: =IFERROR(__xludf.DUMMYFUNCTION("REGEXEXTRACT(A86, ""-(.*)"")"),"ARP.0010.00.2025.GOV.HR.PE") -> ARP.0010.00.2025.GOV.HR.PE | F86: Registro de Preços para o fornecimento eventual de BENS (MATERIAL E UTENSÍLIO CULINÁRIO DE USO DOMESTICO E PESSOAL), visando atender as necessidades do Hospital da Restauração e do Hospital Agamenon Magalhães | G86: NAMP | H86: 45887 | I86: Concluído | J86: =VLOOKUP(A86,'TODOS OS PROCESSOS ATUALIZADOS '!A:I,7,0) -> Autorizada Sucesso | K86: Concluído | L86: =IFERROR(IF(J86=I86, "Item não atualizado", "Item atualizado"), "Item não localizado") -> Item atualizado | N86: Concluído | O86: Enviado ao NOF | P86: 2300002544.000065/2025-78
A87: A.003-ARP.0328.01.2025.EXT.131763.PB | B87: =IFERROR(__xludf.DUMMYFUNCTION("REGEXEXTRACT(A87, ""\.(?:GOV|EXT)\.([A-Z0-9\-]+)"") "),"131763") -> 131763 | C87: HOSPITAL REGIONAL DO AGRESTE DR.WALDEMIRO FERREIRA | D87: Adesão | E87: =IFERROR(__xludf.DUMMYFUNCTION("REGEXEXTRACT(A87, ""-(.*)"")"),"ARP.0328.01.2025.EXT.131763.PB") -> ARP.0328.01.2025.EXT.131763.PB | F87: Registro de Preços para a eventual aquisição de sondas urinárias. | H87: 45896 | I87: Concluído | J87: =VLOOKUP(A87,'TODOS OS PROCESSOS ATUALIZADOS '!A:I,7,0) -> Autorizada Integrado | K87: Concluído | L87: =IFERROR(IF(J87=I87, "Item não atualizado", "Item atualizado"), "Item não localizado") -> Item atualizado | N87: Concluído | O87: Enviado ao NOF | P87: 2300001213.000245/2025-39
A88: A.003-ARP.0093.00.2024.GOV.CISAM.PE | B88: =IFERROR(__xludf.DUMMYFUNCTION("REGEXEXTRACT(A88, ""\.(?:GOV|EXT)\.([A-Z0-9\-]+)"") "),"CISAM") -> CISAM | C88: HOSPITAL REGIONAL DO AGRESTE DR.WALDEMIRO FERREIRA | D88: Adesão | E88: =IFERROR(__xludf.DUMMYFUNCTION("REGEXEXTRACT(A88, ""-(.*)"")"),"ARP.0093.00.2024.GOV.CISAM.PE") -> ARP.0093.00.2024.GOV.CISAM.PE | F88: REGISTRO DE PREÇOS PARA O EVENTUAL FORNECIMENTO DE MEDICAMENTOS, VISANDO ATENDER AS NECESSIDADES DO CISAM/UPE E DEMAIS ÓRGÃOS PARTICIPANTES | H88: 45884 | I88: Concluído | J88: =VLOOKUP(A88,'TODOS OS PROCESSOS ATUALIZADOS '!A:I,7,0) -> Autorizada Sucesso | K88: Concluído | L88: =IFERROR(IF(J88=I88, "Item não atualizado", "Item atualizado"), "Item não localizado") -> Item atualizado | N88: Concluído | O88: Enviado ao NOF | P88: 2300001213.000004/2025-90
A89: A.003-ARP.0059.00.2025.GOV.FES-PE.PE | B89: =IFERROR(__xludf.DUMMYFUNCTION("REGEXEXTRACT(A89, ""\.(?:GOV|EXT)\.([A-Z0-9\-]+)"") "),"FES-PE") -> FES-PE | C89: HOSPITAL REGIONAL DO AGRESTE DR.WALDEMIRO FERREIRA | D89: Adesão | E89: =IFERROR(__xludf.DUMMYFUNCTION("REGEXEXTRACT(A89, ""-(.*)"")"),"ARP.0059.00.2025.GOV.FES-PE.PE") -> ARP.0059.00.2025.GOV.FES-PE.PE | F89: FORMAÇÃO DE REGISTRO DE PREÇOS PARA O FORNECIMENTO DE DISPOSITIVOS MÉDICOS, DO TIPO BOLSAS PARA OSTOMIA, VISANDO ATENDER AS NECESSIDADES DOS HOSPITAIS E ESTABELECIMENTOS VINCULADOS À SECRETARIA ESTADUAL DE SAÚDE DE PERNAMBUCO. | H89: 45911 | I89: Cancelada | J89: =VLOOKUP(A89,'TODOS OS PROCESSOS ATUALIZADOS '!A:I,7,0) -> Cancelada | K89: Cancelado | L89: =IFERROR(IF(J89=I89, "Item não atualizado", "Item atualizado"), "Item não localizado") -> Item não atualizado | N89: Cancelado | O89: SEI não localizado
A90: A.003-ARP.0014.00.2025.GOV.HR.PE | B90: =IFERROR(__xludf.DUMMYFUNCTION("REGEXEXTRACT(A90, ""\.(?:GOV|EXT)\.([A-Z0-9\-]+)"") "),"HR") -> HR | C90: HOSPITAL REGIONAL DO AGRESTE DR.WALDEMIRO FERREIRA | D90: Adesão | E90: =IFERROR(__xludf.DUMMYFUNCTION("REGEXEXTRACT(A90, ""-(.*)"")"),"ARP.0014.00.2025.GOV.HR.PE") -> ARP.0014.00.2025.GOV.HR.PE | F90: Registro de Preços para o fornecimento eventual de PRODUTOS MÉDICOS HOSPITALARES PARA ENDOSCOPIA | H90: 45877 | I90: Concluído | J90: =VLOOKUP(A90,'TODOS OS PROCESSOS ATUALIZADOS '!A:I,7,0) -> Autorizada Sucesso | K90: Concluído | L90: =IFERROR(IF(J90=I90, "Item não atualizado", "Item atualizado"), "Item não localizado") -> Item atualizado | N90: Em andamento | O90: Enviado ao JURIDICO | P90: 2300001213.000300/2025-91
A91: A.003-ARP.0010.05.2025.GOV.HAM.PE | B91: =IFERROR(__xludf.DUMMYFUNCTION("REGEXEXTRACT(A91, ""\.(?:GOV|EXT)\.([A-Z0-9\-]+)"") "),"HAM") -> HAM | C91: HOSPITAL REGIONAL DO AGRESTE DR.WALDEMIRO FERREIRA | D91: Adesão | E91: =IFERROR(__xludf.DUMMYFUNCTION("REGEXEXTRACT(A91, ""-(.*)"")"),"ARP.0010.05.2025.GOV.HAM.PE") -> ARP.0010.05.2025.GOV.HAM.PE | F91: Registro de Preços para o fornecimento eventual de material médico hospitalar destinado ao serviço de anestesia, visando atender as necessidades do Hospital Agamenon Magalhães | H91: 45911 | I91: Cancelada | J91: =VLOOKUP(A91,'TODOS OS PROCESSOS ATUALIZADOS '!A:I,7,0) -> Cancelada | K91: Cancelado | L91: =IFERROR(IF(J91=I91, "Item não atualizado", "Item atualizado"), "Item não localizado") -> Item não atualizado | N91: Cancelado | O91: SEI não localizado
A92: A.003-ARP.0005.00.2025.EXT.136144.ES | B92: =IFERROR(__xludf.DUMMYFUNCTION("REGEXEXTRACT(A92, ""\.(?:GOV|EXT)\.([A-Z0-9\-]+)"") "),"136144") -> 136144 | C92: HOSPITAL REGIONAL DO AGRESTE DR.WALDEMIRO FERREIRA | D92: Adesão | E92: =IFERROR(__xludf.DUMMYFUNCTION("REGEXEXTRACT(A92, ""-(.*)"")"),"ARP.0005.00.2025.EXT.136144.ES") -> ARP.0005.00.2025.EXT.136144.ES | F92: A presente Ata tem por objeto o registro de preços para a eventual aquisição de MEDICAMENTOS-PERP, especificado no Termo de Referência, anexo do Edital de Licitação nº 133/2025, que é parte integrante desta Ata, assim como as propostas cujos preços tenham sido registrados, independentemente de transcrição | H92: 45898 | I92: Concluído | J92: =VLOOKUP(A92,'TODOS OS PROCESSOS ATUALIZADOS '!A:I,7,0) -> Autorizada Integrado | K92: Concluído | L92: =IFERROR(IF(J92=I92, "Item não atualizado", "Item atualizado"), "Item não localizado") -> Item atualizado | N92: Concluído | O92: Enviado ao NOF | P92: 2300001213.000314/2025-12
A93: A.002-ARP.0059.00.2025.GOV.FES-PE.PE | B93: =IFERROR(__xludf.DUMMYFUNCTION("REGEXEXTRACT(A93, ""\.(?:GOV|EXT)\.([A-Z0-9\-]+)"") "),"FES-PE") -> FES-PE | C93: HOSPITAL REGIONAL DO AGRESTE DR.WALDEMIRO FERREIRA | D93: Adesão | E93: =IFERROR(__xludf.DUMMYFUNCTION("REGEXEXTRACT(A93, ""-(.*)"")"),"ARP.0059.00.2025.GOV.FES-PE.PE") -> ARP.0059.00.2025.GOV.FES-PE.PE | F93: FORMAÇÃO DE REGISTRO DE PREÇOS PARA O FORNECIMENTO DE DISPOSITIVOS MÉDICOS, DO TIPO BOLSAS PARA OSTOMIA, VISANDO ATENDER AS NECESSIDADES DOS HOSPITAIS E ESTABELECIMENTOS VINCULADOS À SECRETARIA ESTADUAL DE SAÚDE DE PERNAMBUCO. | G93: NFOCPO | H93: 45884 | I93: Concluído | J93: =VLOOKUP(A93,'TODOS OS PROCESSOS ATUALIZADOS '!A:I,7,0) -> Autorizada Sucesso | K93: Concluído | L93: =IFERROR(IF(J93=I93, "Item não atualizado", "Item atualizado"), "Item não localizado") -> Item atualizado | N93: Em andamento | O93: Enviado a GCONTRATOS | P93: 2300001213.000229/2025-46
A94: A.002-ARP.0019.00.2025.EXT.131763.PB | B94: =IFERROR(__xludf.DUMMYFUNCTION("REGEXEXTRACT(A94, ""\.(?:GOV|EXT)\.([A-Z0-9\-]+)"") "),"131763") -> 131763 | C94: HOSPITAL REGIONAL DO AGRESTE DR.WALDEMIRO FERREIRA | D94: Adesão | E94: =IFERROR(__xludf.DUMMYFUNCTION("REGEXEXTRACT(A94, ""-(.*)"")"),"ARP.0019.00.2025.EXT.131763.PB") -> ARP.0019.00.2025.EXT.131763.PB | F94: A presente Ata tem por objeto o registro de preços para a eventual aquisição de medicamentos (sistema cardiovascular), especificado (s) no item 1.1 do Termo de Referência, anexo do edital de Pregão nº 114/2024, que é parte integrante desta Ata, assim como as propostas cujos preços tenham sido registrados, independentemente de transcrição | H94: 45888 | I94: Concluído | J94: =VLOOKUP(A94,'TODOS OS PROCESSOS ATUALIZADOS '!A:I,7,0) -> Autorizada Integrado | K94: Concluído | L94: =IFERROR(IF(J94=I94, "Item não atualizado", "Item atualizado"), "Item não localizado") -> Item atualizado | N94: Em andamento | O94: Enviado a NFOCPO | P94: 2300001213.000246/2025-83
A95: A.002-ARP.0011.02.2025.GOV.HEMOPE.PE | B95: =IFERROR(__xludf.DUMMYFUNCTION("REGEXEXTRACT(A95, ""\.(?:GOV|EXT)\.([A-Z0-9\-]+)"") "),"HEMOPE") -> HEMOPE | C95: HOSPITAL REGIONAL DO AGRESTE DR.WALDEMIRO FERREIRA | D95: Adesão | E95: =IFERROR(__xludf.DUMMYFUNCTION("REGEXEXTRACT(A95, ""-(.*)"")"),"ARP.0011.02.2025.GOV.HEMOPE.PE") -> ARP.0011.02.2025.GOV.HEMOPE.PE | F95: Registro de Preços para o fornecimento eventual de dispositivos médicos do tipo ponteiras, pipetas, lâminas e tubos de ensaio diversos, com cessão gratuita em comodato de equipamentos e acessórios | H95: 45896 | I95: Concluído | J95: =VLOOKUP(A95,'TODOS OS PROCESSOS ATUALIZADOS '!A:I,7,0) -> Autorizada Sucesso | K95: Concluído | L95: =IFERROR(IF(J95=I95, "Item não atualizado", "Item atualizado"), "Item não localizado") -> Item atualizado | N95: Concluído | O95: Enviado ao NOF | P95: 2300001213.000321/2025-14
A96: A.002-ARP.0010.02.2025.GOV.HOF.PE | B96: =IFERROR(__xludf.DUMMYFUNCTION("REGEXEXTRACT(A96, ""\.(?:GOV|EXT)\.([A-Z0-9\-]+)"") "),"HOF") -> HOF | C96: HOSPITAL REGIONAL DO AGRESTE DR.WALDEMIRO FERREIRA | D96: Adesão | E96: =IFERROR(__xludf.DUMMYFUNCTION("REGEXEXTRACT(A96, ""-(.*)"")"),"ARP.0010.02.2025.GOV.HOF.PE") -> ARP.0010.02.2025.GOV.HOF.PE | F96: Registro de Preços para eventual fornecimento de dispositivos médicos INSUMOS PARA O SERVIÇO DE ENDOSCOPIA. | H96: 45905 | I96: Concluído | J96: =VLOOKUP(A96,'TODOS OS PROCESSOS ATUALIZADOS '!A:I,7,0) -> Autorizada Sucesso | K96: Concluído | L96: =IFERROR(IF(J96=I96, "Item não atualizado", "Item atualizado"), "Item não localizado") -> Item atualizado | N96: Em andamento | O96: Enviado a GCONTRATOS | P96: 2300001213.000339/2025-16
A97: A.002-ARP.0010.02.2025.EXT.HMAR.PE | B97: =IFERROR(__xludf.DUMMYFUNCTION("REGEXEXTRACT(A97, ""\.(?:GOV|EXT)\.([A-Z0-9\-]+)"") "),"HMAR") -> HMAR | C97: HOSPITAL REGIONAL DO AGRESTE DR.WALDEMIRO FERREIRA | D97: Adesão | E97: =IFERROR(__xludf.DUMMYFUNCTION("REGEXEXTRACT(A97, ""-(.*)"")"),"ARP.0010.02.2025.EXT.HMAR.PE") -> ARP.0010.02.2025.EXT.HMAR.PE | F97: Aquisição de Medicamentos – Antibióticos, soros e eletrólitos - GCALC - BENZILPENICILINA. | H97: 45882 | I97: Concluído | J97: =VLOOKUP(A97,'TODOS OS PROCESSOS ATUALIZADOS '!A:I,7,0) -> Autorizada Integrado | K97: Concluído | L97: =IFERROR(IF(J97=I97, "Item não atualizado", "Item atualizado"), "Item não localizado") -> Item atualizado | N97: Concluído | O97: Enviado ao NOF | P97: 2300001213.000135/2025-77
A98: A.002-ARP.0001.01.2025.EXT.CDE.RN | B98: =IFERROR(__xludf.DUMMYFUNCTION("REGEXEXTRACT(A98, ""\.(?:GOV|EXT)\.([A-Z0-9\-]+)"") "),"CDE") -> CDE | C98: HOSPITAL REGIONAL DO AGRESTE DR.WALDEMIRO FERREIRA | D98: Adesão | E98: =IFERROR(__xludf.DUMMYFUNCTION("REGEXEXTRACT(A98, ""-(.*)"")"),"ARP.0001.01.2025.EXT.CDE.RN") -> ARP.0001.01.2025.EXT.CDE.RN | F98: A presente Ata tem por objeto o registro de preços para a eventual aquisição de materiais médicos hospitalares diversos (incluindo curativos, fios, OPME, CME e outros), para atender as necessidades do Hospital de Guarnição de Natal (HGuN), especificado(s) no(s) item(ns) do Termo de Referência, anexo do Edital de Licitação nº 90.009/2024, que é parte integrante desta Ata, assim como as propostas cujos preços tenham sido registrados, independentemente de transcrição. | H98: 45889 | I98: Concluído | J98: =VLOOKUP(A98,'TODOS OS PROCESSOS ATUALIZADOS '!A:I,7,0) -> Autorizada Integrado | K98: Concluído | L98: =IFERROR(IF(J98=I98, "Item não atualizado", "Item atualizado"), "Item não localizado") -> Item atualizado | N98: Concluído | O98: Enviado ao NOF | P98: 2300001213.000270/2025-12
A99: A.001-ARP.0501.00.2025.EXT.HGJMM.RN | B99: =IFERROR(__xludf.DUMMYFUNCTION("REGEXEXTRACT(A99, ""\.(?:GOV|EXT)\.([A-Z0-9\-]+)"") "),"HGJMM") -> HGJMM | C99: HOSPITAL REGIONAL DO AGRESTE DR.WALDEMIRO FERREIRA | D99: Adesão | E99: =IFERROR(__xludf.DUMMYFUNCTION("REGEXEXTRACT(A99, ""-(.*)"")"),"ARP.0501.00.2025.EXT.HGJMM.RN") -> ARP.0501.00.2025.EXT.HGJMM.RN | F99: Aquisição de Medicamentos - ANTIMICROBIANOS , conforme condições e exigências estabelecidas neste instrumento. | H99: 45897 | I99: Concluído | J99: =VLOOKUP(A99,'TODOS OS PROCESSOS ATUALIZADOS '!A:I,7,0) -> Autorizada Integrado | K99: Concluído | L99: =IFERROR(IF(J99=I99, "Item não atualizado", "Item atualizado"), "Item não localizado") -> Item atualizado | N99: Concluído | O99: Enviado ao NOF | P99: 2300001213.000197/2025-89
A100: A.001-ARP.0068.00.2025.GOV.FES-PE.PE | B100: =IFERROR(__xludf.DUMMYFUNCTION("REGEXEXTRACT(A100, ""\.(?:GOV|EXT)\.([A-Z0-9\-]+)"") "),"FES-PE") -> FES-PE | C100: HOSPITAL REGIONAL DO AGRESTE DR.WALDEMIRO FERREIRA | D100: Adesão | E100: =IFERROR(__xludf.DUMMYFUNCTION("REGEXEXTRACT(A100, ""-(.*)"")"),"ARP.0068.00.2025.GOV.FES-PE.PE") -> ARP.0068.00.2025.GOV.FES-PE.PE | F100: FORMAÇÃO DE REGISTRO DE PREÇOS PARA O FORNECIMENTO DE DISPOSITIVOS MÉDICOS, DO TIPO INSUMOS PARA OSTOMIA, VISANDO ATENDER AS NECESSIDADES DOS HOSPITAIS E ESTABELECIMENTOS VINCULADOS À SECRETARIA ESTADUAL DE SAÚDE DE PERNAMBUCO | G100: NFOCPO | H100: 45898 | I100: Concluído | J100: =VLOOKUP(A100,'TODOS OS PROCESSOS ATUALIZADOS '!A:I,7,0) -> Autorizada Sucesso | K100: Concluído | L100: =IFERROR(IF(J100=I100, "Item não atualizado", "Item atualizado"), "Item não localizado") -> Item atualizado | N100: Em andamento | O100: Enviado a GCONTRATOS | P100: 2300001213.000348/2025-07
...

Sheet PROCESSOS CONCLUIDOS
A1: Número da solicitação | B1: Unidade gestora | C1: Tipo da solicitação | D1: Número da ata | E1: Objeto | F1: Data de solicitação | G1: Situação | H1: SEI | I1: ENCAMINHADO / SETOR | J1: DATA DO ENCAMINHAMENTO | K1: STATUS | L1: VALOR
A2: C.002-ARP.0099.00.2025.GOV.FES-PE.PE | B2: HOSPITAL REGIONAL DO AGRESTE DR.WALDEMIRO FERREIRA | C2: Consumo | D2: ARP.0099.00.2025.GOV.FES-PE.PE | E2: Formação de Registro de Preços para o fornecimento de Dispositivos Médicos do tipo Disco para Antibiograma visando atender as necessidades dos hospitais e estabelecimentos vinculados à Secretaria Estadual de Saúde de Pernambuco | F2: 45940 | G2: Autorizada Sucesso | H2: 2300001209.000078/2025-95 | I2: GCONTRATOS | J2: 45943 | K2: AGUARDANDO EMPENHO | L2: 4139.77
A3: C.015-ARPC.0039.00.2025.GOV.SAD.PE | B3: HOSPITAL REGIONAL DO AGRESTE DR.WALDEMIRO FERREIRA | C3: Consumo | D3: ARPC.0039.00.2025.GOV.SAD.PE | E3: Registro de Preços para o fornecimento eventual de material de higiene pessoal, visando atender as necessidades dos órgãos da Administração Direta, dos Fundos Especiais Autarquias e Fundações Públicas integrantes do Poder Executivo do Estado de Pernambuco | F3: 45937 | G3: Autorizada Sucesso | H3: 2300002544.000078/2025-47 | I3: GCONTRATOS | J3: 45952
A4: C.007-ARP.0049.03.2025.GOV.FES-PE.PE | B4: HOSPITAL REGIONAL DO AGRESTE DR.WALDEMIRO FERREIRA | C4: Consumo | D4: ARP.0049.03.2025.GOV.FES-PE.PE | E4: Formação de Registro de Preços para o fornecimento eventual de Medicamentos Comprimidos Grupo 4 visando atender as necessidades dos hospitais e estabelecimentos vinculados à Secretaria Estadual de Saúde de Pernambuco | F4: 45916 | G4: Autorizada Sucesso | H4: 2300001213.000413/2025-96 | I4: GCONTRATOS | J4: 22/102025
A5: C.008-ARP.0049.01.2025.GOV.FES-PE.PE | B5: HOSPITAL REGIONAL DO AGRESTE DR.WALDEMIRO FERREIRA | C5: Consumo | D5: ARP.0049.01.2025.GOV.FES-PE.PE | E5: Formação de Registro de Preços para o fornecimento eventual de Medicamentos Comprimidos Grupo 4 visando atender as necessidades dos hospitais e estabelecimentos vinculados à Secretaria Estadual de Saúde de Pernambuco | F5: 45911 | G5: Autorizada Sucesso | H5: 2300001213.000408/2025-83 | I5: GCONTRATOS | J5: 45952
A6: C.011-ARP.0049.04.2025.GOV.FES-PE.PE | B6: HOSPITAL REGIONAL DO AGRESTE DR.WALDEMIRO FERREIRA | C6: Consumo | D6: ARP.0049.04.2025.GOV.FES-PE.PE | E6: Formação de Registro de Preços para o fornecimento eventual de Medicamentos Comprimidos Grupo 4 visando atender as necessidades dos hospitais e estabelecimentos vinculados à Secretaria Estadual de Saúde de Pernambuco | F6: 45911 | G6: Autorizada Sucesso | H6: 2300001213.000406/2025-94 | I6: GCONTRATOS | J6: 45952
A7: C.011-ARP.0008.01.2025.GOV.HAM.PE | B7: HOSPITAL REGIONAL DO AGRESTE DR.WALDEMIRO FERREIRA | C7: Consumo | D7: ARP.0008.01.2025.GOV.HAM.PE | E7: Formação de Registro de Preços para o fornecimento eventual de solução parenteral por um período de 12 meses, visando atender as necessidades do Hospital Agamenon Magalhães | F7: 45908 | G7: Autorizada Sucesso | H7: Não Localizado
A8: C.014-ARP.0067.01.2025.GOV.FES-PE.PE | B8: HOSPITAL REGIONAL DO AGRESTE DR.WALDEMIRO FERREIRA | C8: Consumo | D8: ARP.0067.01.2025.GOV.FES-PE.PE | E8: FORMAÇÃO DE REGISTRO DE PREÇOS PARA O FORNECIMENTO DE DISPOSITIVOS MÉDICOS, DO TIPO MATERIAIS MÉDICO HOSPITALARES (GRUPO 8), VISANDO ATENDER AS NECESSIDADES DOS HOSPITAIS E ESTABELECIMENTOS VINCULADOS À SECRETARIA ESTADUAL DE SAÚDE DE PERNAMBUCO | F8: 45905 | G8: Autorizada Sucesso | H8: Não Localizado
A9: C.006-ARP.0077.01.2025.GOV.FES-PE.PE | B9: HOSPITAL REGIONAL DO AGRESTE DR.WALDEMIRO FERREIRA | C9: Consumo | D9: ARP.0077.01.2025.GOV.FES-PE.PE | E9: Registro de Preços para Fornecimento Eventual de Dispositivos Médicos do tipo: Antissépticos, Desinfetantes e Saneantes – Grupo 2 | F9: 45904 | G9: Autorizada Sucesso | H9: Não Localizado
A10: C.011-ARP.0044.04.2025.GOV.FES-PE.PE | B10: HOSPITAL REGIONAL DO AGRESTE DR.WALDEMIRO FERREIRA | C10: Consumo | D10: ARP.0044.04.2025.GOV.FES-PE.PE | E10: Formação de Registro de Preços para o fornecimento eventual de dispositivos médicos do Tipo DRENOS visando atender as necessidades dos hospitais e estabelecimentos vinculados à Secretaria Estadual de Saúde de Pernambuco, conforme as condições, especificações, quantidades e exigências contidas no Termo de Referência | F10: 45904 | G10: Autorizada Sucesso | H10: Não Localizado
A11: C.009-ARP.0044.02.2025.GOV.FES-PE.PE | B11: HOSPITAL REGIONAL DO AGRESTE DR.WALDEMIRO FERREIRA | C11: Consumo | D11: ARP.0044.02.2025.GOV.FES-PE.PE | E11: Formação de Registro de Preços para o fornecimento eventual de dispositivos médicos do Tipo DRENOS visando atender as necessidades dos hospitais e estabelecimentos vinculados à Secretaria Estadual de Saúde de Pernambuco, conforme as condições, especificações, quantidades e exigências contidas no Termo de Referência | F11: 45904 | G11: Autorizada Integrado | H11: Não Localizado
A12: C.002-ARP.0022.02.2024.GOV.HOF.PE | B12: HOSPITAL REGIONAL DO AGRESTE DR.WALDEMIRO FERREIRA | C12: Consumo | D12: ARP.0022.02.2024.GOV.HOF.PE | E12: FORMAÇÃO DE REGISTRO DE PREÇOS PARA O FORNECIMENTO EVENTUAL DE INSUMOS PARA O SERVIÇO DE CIRURGIA TORÁCICA VISANDO ATENDER AS NECESSIDADES DO HOSPITAL OTÁVIO DE FREITAS E HOSPITAL REGIONAL DO AGRESTE. | F12: 45902 | G12: Autorizada Sucesso | H12: Não Localizado
A13: C.004-ARP.0001.00.2024.FES-PE.PE | B13: HOSPITAL REGIONAL DO AGRESTE DR.WALDEMIRO FERREIRA | C13: Consumo | D13: ARP.0001.00.2024.FES-PE.PE | E13: Formação de Registro de Preços para o fornecimento eventual de Água Mineral sem gás, visando atender as necessidades da Secretaria Estadual de Saúde de Pernambuco e dos hospitais da Região Metropolitana do Recife (RMR) e das cidades de Caruaru, Garanhuns e Serra Talhada. | F13: 45898 | G13: Autorizada Sucesso | H13: Não Localizado
A14: C.023-ARP.0070.03.2025.GOV.FES-PE.PE | B14: HOSPITAL REGIONAL DO AGRESTE DR.WALDEMIRO FERREIRA | C14: Consumo | D14: ARP.0070.03.2025.GOV.FES-PE.PE | E14: Formação de Registro de Preços para o fornecimento eventual de medicamentos (INJETÁVEIS GRUPO 10) visando atender as necessidades dos hospitais e estabelecimentos vinculados à Secretaria Estadual de Saúde de Pernambuco | F14: 45891 | G14: Autorizada Sucesso | H14: Não Localizado
A15: C.004-ARP.0079.01.2025.GOV.FES-PE.PE | B15: HOSPITAL REGIONAL DO AGRESTE DR.WALDEMIRO FERREIRA | C15: Consumo | D15: ARP.0079.01.2025.GOV.FES-PE.PE | E15: Registro de Preços para a eventual aquisição de Material Médico Hospitalar - MMH (grupo 01) | F15: 45891 | G15: Autorizada Sucesso | H15: Não Localizado
A16: C.004-ARP.0079.00.2025.GOV.FES-PE.PE | B16: HOSPITAL REGIONAL DO AGRESTE DR.WALDEMIRO FERREIRA | C16: Consumo | D16: ARP.0079.00.2025.GOV.FES-PE.PE | E16: Registro de Preços para a eventual aquisição de Material Médico Hospitalar - MMH (grupo 01) | F16: 45891 | G16: Autorizada Sucesso | H16: Não Localizado
A17: C.010-ARP.0008.01.2025.GOV.HAM.PE | B17: HOSPITAL REGIONAL DO AGRESTE DR.WALDEMIRO FERREIRA | C17: Consumo | D17: ARP.0008.01.2025.GOV.HAM.PE | E17: Formação de Registro de Preços para o fornecimento eventual de solução parenteral por um período de 12 meses, visando atender as necessidades do Hospital Agamenon Magalhães | F17: 45882 | G17: Autorizada Sucesso | H17: Não Localizado
A18: C.007-ARP.0079.14.2025.GOV.FES-PE.PE | B18: HOSPITAL REGIONAL DO AGRESTE DR.WALDEMIRO FERREIRA | C18: Consumo | D18: ARP.0079.14.2025.GOV.FES-PE.PE | E18: Registro de Preços para a eventual aquisição de Material Médico Hospitalar - MMH (grupo 01) | F18: 45880 | G18: Autorizada Sucesso | H18: Não Localizado
... A21: C.005-ARP.0068.00.2025.GOV.FES-PE.PE | B21: HOSPITAL REGIONAL DO AGRESTE DR.WALDEMIRO FERREIRA | C21: Consumo | D21: ARP.0068.00.2025.GOV.FES-PE.PE | E21: FORMAÇÃO DE REGISTRO DE PREÇOS PARA O FORNECIMENTO DE DISPOSITIVOS MÉDICOS, DO TIPO INSUMOS PARA OSTOMIA, VISANDO ATENDER AS NECESSIDADES DOS HOSPITAIS E ESTABELECIMENTOS VINCULADOS À SECRETARIA ESTADUAL DE SAÚDE DE PERNAMBUCO | F21: 45874 | G21: Autorizada Sucesso | H21: Não Localizado
A22: C.002-ARP.0011.03.2025.GOV.HGV.PE | B22: HOSPITAL REGIONAL DO AGRESTE DR.WALDEMIRO FERREIRA | C22: Consumo | D22: ARP.0011.03.2025.GOV.HGV.PE | E22: Formação de Registro de Preços para o fornecimento eventual de SMS - EMBALAGENS DESCARTÁVEIS PARA ESTERILIZAÇÃO visando atender a demanda do Hospital Getúlio Vargas conforme condições, especificações, quantidades e exigências contidas neste Termo de Referência. | F22: 45874 | G22: Autorizada Sucesso | H22: 2300001213.000317/2025-48 | I22: juridico | J22: 45960
A23: C.003-ARP.0079.04.2025.GOV.FES-PE.PE | B23: HOSPITAL REGIONAL DO AGRESTE DR.WALDEMIRO FERREIRA | C23: Consumo | D23: ARP.0079.04.2025.GOV.FES-PE.PE | E23: Registro de Preços para a eventual aquisição de Material Médico Hospitalar - MMH (grupo 01) | F23: 45869 | G23: Autorizada Sucesso | H23: 2300001213.000312/2025-15 | I23: juridico | J23: 45960
A24: C.012-ARP.0044.06.2025.GOV.FES-PE.PE | B24: HOSPITAL REGIONAL DO AGRESTE DR.WALDEMIRO FERREIRA | C24: Consumo | D24: ARP.0044.06.2025.GOV.FES-PE.PE | E24: Formação de Registro de Preços para o fornecimento eventual de dispositivos médicos do Tipo DRENOS visando atender as necessidades dos hospitais e estabelecimentos vinculados à Secretaria Estadual de Saúde de Pernambuco, conforme as condições, especificações, quantidades e exigências contidas no Termo de Referência | F24: 45863 | G24: Autorizada Sucesso | H24: Não Localizado
A25: C.014-ARP.0016.03.2025.GOV.FES-PE.PE | B25: HOSPITAL REGIONAL DO AGRESTE DR.WALDEMIRO FERREIRA | C25: Consumo | D25: ARP.0016.03.2025.GOV.FES-PE.PE | E25: Registro de Preços para o fornecimento eventual de medicamentos do tipo COMPRIMIDOS (Grupo 05 | F25: 45862 | G25: Autorizada Sucesso
A26: C.017-ARP.0009.00.2025.GOV.FES-PE.PE | B26: HOSPITAL REGIONAL DO AGRESTE DR.WALDEMIRO FERREIRA | C26: Consumo | D26: ARP.0009.00.2025.GOV.FES-PE.PE | E26: Registro de Preços para aquisição de Material Médico Hospitalar - Luvas (Unificado) | F26: 45861 | G26: Autorizada Sucesso | H26: 2300002544.000067/2025-67 | I26: ORDEM DE FORNECIMENTO | J26: 45933
A27: C.003-ARP.0011.02.2025.GOV.HGV.PE | B27: HOSPITAL REGIONAL DO AGRESTE DR.WALDEMIRO FERREIRA | C27: Consumo | D27: ARP.0011.02.2025.GOV.HGV.PE | E27: Formação de Registro de Preços para o fornecimento eventual de SMS - EMBALAGENS DESCARTÁVEIS PARA ESTERILIZAÇÃO visando atender a demanda do Hospital Getúlio Vargas conforme condições, especificações, quantidades e exigências contidas neste Termo de Referência. | F27: 45860 | G27: Autorizada Sucesso | H27: Não Localizado
A28: C.002-ARP.0077.00.2025.GOV.FES-PE.PE | B28: HOSPITAL REGIONAL DO AGRESTE DR.WALDEMIRO FERREIRA | C28: Consumo | D28: ARP.0077.00.2025.GOV.FES-PE.PE | E28: Registro de Preços para Fornecimento Eventual de Dispositivos Médicos do tipo: Antissépticos, Desinfetantes e Saneantes – Grupo 2 | F28: 45859 | G28: Autorizada Sucesso | H28: Não Localizado
A29: C.012-ARP.0053.02.2025.GOV.FES-PE.PE | B29: HOSPITAL REGIONAL DO AGRESTE DR.WALDEMIRO FERREIRA | C29: Consumo | D29: ARP.0053.02.2025.GOV.FES-PE.PE | E29: Formação de Ata de Registro de Preços para o fornecimento eventual de Dispositivos Médicos do Tipo: Diversos visando atender as necessidades dos hospitais e estabelecimentos da rede estadual de saúde de Pernambuco | F29: 45853 | G29: Autorizada Sucesso | H29: Não Localizado
A30: C.009-ARP.0008.01.2025.GOV.HAM.PE | B30: HOSPITAL REGIONAL DO AGRESTE DR.WALDEMIRO FERREIRA | C30: Consumo | D30: ARP.0008.01.2025.GOV.HAM.PE | E30: Formação de Registro de Preços para o fornecimento eventual de solução parenteral por um período de 12 meses, visando atender as necessidades do Hospital Agamenon Magalhães | F30: 45849 | G30: Autorizada Sucesso | H30: Não Localizado
A31: C.016-ARP.0070.03.2025.GOV.FES-PE.PE | B31: HOSPITAL REGIONAL DO AGRESTE DR.WALDEMIRO FERREIRA | C31: Consumo | D31: ARP.0070.03.2025.GOV.FES-PE.PE | E31: Formação de Registro de Preços para o fornecimento eventual de medicamentos (INJETÁVEIS GRUPO 10) visando atender as necessidades dos hospitais e estabelecimentos vinculados à Secretaria Estadual de Saúde de Pernambuco | F31: 45848 | G31: Autorizada Sucesso | H31: Não Localizado
A32: C.002-ARP.0011.01.2025.GOV.HGV.PE | B32: HOSPITAL REGIONAL DO AGRESTE DR.WALDEMIRO FERREIRA | C32: Consumo | D32: ARP.0011.01.2025.GOV.HGV.PE | E32: Formação de Registro de Preços para o fornecimento eventual de SMS - EMBALAGENS DESCARTÁVEIS PARA ESTERILIZAÇÃO visando atender a demanda do Hospital Getúlio Vargas conforme condições, especificações, quantidades e exigências contidas neste Termo de Referência. | F32: 45838 | G32: Autorizada Sucesso | H32: 2300001213.000258/2025-16 | I32: ORDEM DE FORNECIMENTO | J32: 45909
A33: C.005-ARP.0087.02.2024.GOV.CISAM.PE | B33: HOSPITAL REGIONAL DO AGRESTE DR.WALDEMIRO FERREIRA | C33: Consumo | D33: ARP.0087.02.2024.GOV.CISAM.PE | E33: REGISTRO DE PREÇOS PARA FORNECIMENTO EVENTUAL DE MATERIAIS MÉDICO-HOSPITALARES (DIVERSOS), VISANDO ATENDER AS NECESSIDADES DO CISAM/UPE E DEMAIS ÓRGÃO PARTICIPANTES. | F33: 45833 | G33: Autorizada Sucesso | H33: 2300001213.000254/2025-20 | I33: nfo | J33: 45959
A34: C.002-ARP.0006.03.2025.GOV.CISAM.PE | B34: HOSPITAL REGIONAL DO AGRESTE DR.WALDEMIRO FERREIRA | C34: Consumo | D34: ARP.0006.03.2025.GOV.CISAM.PE | E34: REGISTRO DE PREÇOS PARA O FORNECIMENTO EVENTUAL DE MATERIAIS MÉDICO-HOSPITALARES (SERINGA DESCARTÁVEL), VISANDO ATENDER AS NECESSIDADES DO CISAM/UPE E DEMAIS ÓRGÃOS PARTICIPANTES | F34: 45826 | G34: Autorizada Sucesso | H34: 2300001213.000255/2025-74 | I34: nfo | J34: 45959
A35: C.007-ARP.0008.01.2025.GOV.HAM.PE | B35: HOSPITAL REGIONAL DO AGRESTE DR.WALDEMIRO FERREIRA | C35: Consumo | D35: ARP.0008.01.2025.GOV.HAM.PE | E35: Formação de Registro de Preços para o fornecimento eventual de solução parenteral por um período de 12 meses, visando atender as necessidades do Hospital Agamenon Magalhães | F35: 45824 | G35: Autorizada Sucesso | H35: Não Localizado
A36: C.028-ARP.0064.02.2024.GOV.FES-PE.PE | B36: HOSPITAL REGIONAL DO AGRESTE DR.WALDEMIRO FERREIRA | C36: Consumo | D36: ARP.0064.02.2024.GOV.FES-PE.PE | E36: PREGÃO ELETRÔNICO PARA FORMAÇÃO DE REGISTRO DE PREÇOS PARA A EVENTUAL FORNECIMENTO DE MEDICAMENTOS INJETÁVEIS (GRUPO 04) VISANDO ATENDER A DEMANDA DOS HOSPITAIS E ESTABELECIMENTOS DA REDE ESTADUAL DE SAÚDE DE PERNAMBUCO. | F36: 45819 | G36: Autorizada Sucesso | H36: Não Localizado
A37: C.004-ARP.0073.01.2025.GOV.FES-PE.PE | B37: HOSPITAL REGIONAL DO AGRESTE DR.WALDEMIRO FERREIRA | C37: Consumo | D37: ARP.0073.01.2025.GOV.FES-PE.PE | E37: Registro de Preços para o fornecimento eventual de Dispositivos Médicos do tipo Materiais Médicos (Indicadores, cera, e cimento cirúrgico), conforme especificações e quantitativos previstos no Termo de Referência, visando atender as necessidades dos hospitais e estabelecimentos vinculados à Secretaria Estadual de Saúde de Pernambuco | F37: 45818 | G37: Autorizada Sucesso | H37: Não Localizado
A38: C.004-ARP.0073.00.2025.GOV.FES-PE.PE | B38: HOSPITAL REGIONAL DO AGRESTE DR.WALDEMIRO FERREIRA | C38: Consumo | D38: ARP.0073.00.2025.GOV.FES-PE.PE | E38: Registro de Preços para o fornecimento eventual de Dispositivos Médicos do tipo Materiais Médicos (Indicadores, cera, e cimento cirúrgico), conforme especificações e quantitativos previstos no Termo de Referência, visando atender as necessidades dos hospitais e estabelecimentos vinculados à Secretaria Estadual de Saúde de Pernambuco | F38: 45818 | G38: Autorizada Sucesso | H38: Não Localizado
A39: C.005-ARP.0045.00.2025.GOV.FES-PE.PE | B39: HOSPITAL REGIONAL DO AGRESTE DR.WALDEMIRO FERREIRA | C39: Consumo | D39: ARP.0045.00.2025.GOV.FES-PE.PE | E39: Registro de Preços para o fornecimento eventual de Medicamentos Comprimidos (Grupo 03), visando atender as necessidades dos hospitais e estabelecimentos vinculados à Secretaria Estadual de Saúde de Pernambuco. | F39: 45813 | G39: Autorizada Sucesso | H39: Não Localizado
A40: C.012-ARP.0070.03.2025.GOV.FES-PE.PE | B40: HOSPITAL REGIONAL DO AGRESTE DR.WALDEMIRO FERREIRA | C40: Consumo | D40: ARP.0070.03.2025.GOV.FES-PE.PE | E40: Formação de Registro de Preços para o fornecimento eventual de medicamentos (INJETÁVEIS GRUPO 10) visando atender as necessidades dos hospitais e estabelecimentos vinculados à Secretaria Estadual de Saúde de Pernambuco | F40: 45812 | G40: Autorizada Sucesso | H40: Não Localizado
A41: C.022-ARP.0015.06.2025.GOV.FES-PE.PE | B41: HOSPITAL REGIONAL DO AGRESTE DR.WALDEMIRO FERREIRA | C41: Consumo | D41: ARP.0015.06.2025.GOV.FES-PE.PE | E41: Formação de Registro de Preços para o fornecimento eventual de medicamentos visando atender as necessidades dos hospitais e estabelecimentos vinculados à Secretaria Estadual de Saúde de Pernambuco, conforme as condições, especificações, quantidades e exigências contidas no Termo de Referência. | F41: 45806 | G41: Autorizada Sucesso | H41: Não Localizado
A42: C.002-ARP.0012.07.2025.GOV.HAM.PE | B42: HOSPITAL REGIONAL DO AGRESTE DR.WALDEMIRO FERREIRA | C42: Consumo | D42: ARP.0012.07.2025.GOV.HAM.PE | E42: Registro de Preços para o fornecimento eventual de material de consumo (aquisição de materiais de almoxarifado) visando atender as necessidades do Hospital Agamenon Magalhães, Hospital Otávio de Freitas, Hospital Regional do Agreste e da Secretaria de Saúde | F42: 45806 | G42: Autorizada Sucesso | H42: Não Localizado
A43: C.011-ARP.0067.03.2025.GOV.FES-PE.PE | B43: HOSPITAL REGIONAL DO AGRESTE DR.WALDEMIRO FERREIRA | C43: Consumo | D43: ARP.0067.03.2025.GOV.FES-PE.PE | E43: FORMAÇÃO DE REGISTRO DE PREÇOS PARA O FORNECIMENTO DE DISPOSITIVOS MÉDICOS, DO TIPO MATERIAIS MÉDICO HOSPITALARES (GRUPO 8), VISANDO ATENDER AS NECESSIDADES DOS HOSPITAIS E ESTABELECIMENTOS VINCULADOS À SECRETARIA ESTADUAL DE SAÚDE DE PERNAMBUCO | F43: 45806 | G43: Autorizada Sucesso | H43: Não Localizado
A44: C.006-ARP.0049.02.2025.GOV.FES-PE.PE | B44: HOSPITAL REGIONAL DO AGRESTE DR.WALDEMIRO FERREIRA | C44: Consumo | D44: ARP.0049.02.2025.GOV.FES-PE.PE | E44: Formação de Registro de Preços para o fornecimento eventual de Medicamentos Comprimidos Grupo 4 visando atender as necessidades dos hospitais e estabelecimentos vinculados à Secretaria Estadual de Saúde de Pernambuco | F44: 45803 | G44: Autorizada Sucesso | H44: Não Localizado
A45: C.009-ARP.0067.06.2025.GOV.FES-PE.PE | B45: HOSPITAL REGIONAL DO AGRESTE DR.WALDEMIRO FERREIRA | C45: Consumo | D45: ARP.0067.06.2025.GOV.FES-PE.PE | E45: FORMAÇÃO DE REGISTRO DE PREÇOS PARA O FORNECIMENTO DE DISPOSITIVOS MÉDICOS, DO TIPO MATERIAIS MÉDICO HOSPITALARES (GRUPO 8), VISANDO ATENDER AS NECESSIDADES DOS HOSPITAIS E ESTABELECIMENTOS VINCULADOS À SECRETARIA ESTADUAL DE SAÚDE DE PERNAMBUCO | F45: 45803 | G45: Autorizada Sucesso | H45: Não Localizado
A46: C.008-ARP.0067.01.2025.GOV.FES-PE.PE | B46: HOSPITAL REGIONAL DO AGRESTE DR.WALDEMIRO FERREIRA | C46: Consumo | D46: ARP.0067.01.2025.GOV.FES-PE.PE | E46: FORMAÇÃO DE REGISTRO DE PREÇOS PARA O FORNECIMENTO DE DISPOSITIVOS MÉDICOS, DO TIPO MATERIAIS MÉDICO HOSPITALARES (GRUPO 8), VISANDO ATENDER AS NECESSIDADES DOS HOSPITAIS E ESTABELECIMENTOS VINCULADOS À SECRETARIA ESTADUAL DE SAÚDE DE PERNAMBUCO | F46: 45803 | G46: Autorizada Sucesso | H46: Não Localizado
A47: C.011-ARP.0010.05.2025.GOV.FES-PE.PE | B47: HOSPITAL REGIONAL DO AGRESTE DR.WALDEMIRO FERREIRA | C47: Consumo | D47: ARP.0010.05.2025.GOV.FES-PE.PE | E47: REGISTRO DE PREÇOS PARA A EVENTUAL AQUISIÇÃODE DISPOSITIVOS MÉDICOS DO TIPO PRODUTOS MÉDICOS (PAPEL CIRÚRGICO, ESCOVA PARA LIMPEZA DE MATERIAIS, EMBALAGEM DESCARTÁVEIS PARA ESTERILIZAÇÃO) VISANDO ATENDER A DEMANDA DOS HOSPITAIS E ESTABELECIMENTOS DA REDE ESTADUAL DE SAÚDE DE PERNAMBUCO, SES/PE. | F47: 45800 | G47: Autorizada Sucesso | H47: Não Localizado
A48: C.003-ARP.0006.00.2025.GOV.CISAM.PE | B48: HOSPITAL REGIONAL DO AGRESTE DR.WALDEMIRO FERREIRA | C48: Consumo | D48: ARP.0006.00.2025.GOV.CISAM.PE | E48: REGISTRO DE PREÇOS PARA O FORNECIMENTO EVENTUAL DE MATERIAIS MÉDICO-HOSPITALARES (SERINGA DESCARTÁVEL), VISANDO ATENDER AS NECESSIDADES DO CISAM/UPE E DEMAIS ÓRGÃOS PARTICIPANTES | F48: 45799 | G48: Autorizada Sucesso | H48: 2300001213.000162/2025-40 | I48: nof | J48: 45959
A49: C.005-ARP.0006.01.2025.GOV.CISAM.PE | B49: HOSPITAL REGIONAL DO AGRESTE DR.WALDEMIRO FERREIRA | C49: Consumo | D49: ARP.0006.01.2025.GOV.CISAM.PE | E49: REGISTRO DE PREÇOS PARA O FORNECIMENTO EVENTUAL DE MATERIAIS MÉDICO-HOSPITALARES (SERINGA DESCARTÁVEL), VISANDO ATENDER AS NECESSIDADES DO CISAM/UPE E DEMAIS ÓRGÃOS PARTICIPANTES | F49: 45799 | G49: Autorizada Sucesso | H49: 2300001213.000163/2025-94 | I49: nof | J49: 45959
A50: C.006-ARP.0021.01.2024.GOV.HOF.PE | B50: HOSPITAL REGIONAL DO AGRESTE DR.WALDEMIRO FERREIRA | C50: Consumo | D50: ARP.0021.01.2024.GOV.HOF.PE | E50: Formação de Registro de Preços para o fornecimento eventual de Material Médico Hospitalar INSUMOS PARA HIGIENE E PROTEÇÃO, visando atender a necessidade do do Hospital Otávio de Freitas (HOF), Hospital Regional do Agreste (HRA), Hospital Getúlio Vargas (HGV), Hospital Agamenon Magalhães (HAM), | F50: 45798 | G50: Autorizada Sucesso | H50: 2300001213.000156/2025-92 | I50: gcontratos | J50: 45958
A51: C.006-ARP.0083.06.2024.GOV.FES-PE.PE | B51: HOSPITAL REGIONAL DO AGRESTE DR.WALDEMIRO FERREIRA | C51: Consumo | D51: ARP.0083.06.2024.GOV.FES-PE.PE | E51: Registro de Preços para o fornecimento eventual de Medicamentos Diversos (Grupo 03), visando atender as necessidades dos hospitais e estabelecimentos da rede estadual de saúde de Pernambuco | F51: 45797 | G51: Autorizada | H51: Não Localizado
A52: C.003-ARP.0021.06.2024.GOV.HOF.PE | B52: HOSPITAL REGIONAL DO AGRESTE DR.WALDEMIRO FERREIRA | C52: Consumo | D52: ARP.0021.06.2024.GOV.HOF.PE | E52: Formação de Registro de Preços para o fornecimento eventual de Material Médico Hospitalar INSUMOS PARA HIGIENE E PROTEÇÃO, visando atender a necessidade do do Hospital Otávio de Freitas (HOF), Hospital Regional do Agreste (HRA), Hospital Getúlio Vargas (HGV), Hospital Agamenon Magalhães (HAM), | F52: 45797 | G52: Autorizada Sucesso | H52: Não Localizado
A53: C.004-ARP.0021.11.2024.GOV.HOF.PE | B53: HOSPITAL REGIONAL DO AGRESTE DR.WALDEMIRO FERREIRA | C53: Consumo | D53: ARP.0021.11.2024.GOV.HOF.PE | E53: Formação de Registro de Preços para o fornecimento eventual de Material Médico Hospitalar INSUMOS PARA HIGIENE E PROTEÇÃO, visando atender a necessidade do do Hospital Otávio de Freitas (HOF), Hospital Regional do Agreste (HRA), Hospital Getúlio Vargas (HGV), Hospital Agamenon Magalhães (HAM), | F53: 45797 | G53: Autorizada Sucesso | H53: Não Localizado
A54: C.008-ARP.0067.03.2025.GOV.FES-PE.PE | B54: HOSPITAL REGIONAL DO AGRESTE DR.WALDEMIRO FERREIRA | C54: Consumo | D54: ARP.0067.03.2025.GOV.FES-PE.PE | E54: FORMAÇÃO DE REGISTRO DE PREÇOS PARA O FORNECIMENTO DE DISPOSITIVOS MÉDICOS, DO TIPO MATERIAIS MÉDICO HOSPITALARES (GRUPO 8), VISANDO ATENDER AS NECESSIDADES DOS HOSPITAIS E ESTABELECIMENTOS VINCULADOS À SECRETARIA ESTADUAL DE SAÚDE DE PERNAMBUCO | F54: 45797 | G54: Autorizada Sucesso | H54: Não Localizado
A55: C.014-ARP.0009.01.2025.GOV.FES-PE.PE | B55: HOSPITAL REGIONAL DO AGRESTE DR.WALDEMIRO FERREIRA | C55: Consumo | D55: ARP.0009.01.2025.GOV.FES-PE.PE | E55: Registro de Preços para aquisição de Material Médico Hospitalar - Luvas (Unificado) | F55: 45796 | G55: Autorizada Sucesso | H55: Não Localizado
A56: C.011-ARP.0053.02.2025.GOV.FES-PE.PE | B56: HOSPITAL REGIONAL DO AGRESTE DR.WALDEMIRO FERREIRA | C56: Consumo | D56: ARP.0053.02.2025.GOV.FES-PE.PE | E56: Formação de Ata de Registro de Preços para o fornecimento eventual de Dispositivos Médicos do Tipo: Diversos visando atender as necessidades dos hospitais e estabelecimentos da rede estadual de saúde de Pernambuco | F56: 45796 | G56: Autorizada Sucesso | H56: Não Localizado
A57: C.006-ARP.0083.05.2024.GOV.FES-PE.PE | B57: HOSPITAL REGIONAL DO AGRESTE DR.WALDEMIRO FERREIRA | C57: Consumo | D57: ARP.0083.05.2024.GOV.FES-PE.PE | E57: Registro de Preços para o fornecimento eventual de Medicamentos Diversos (Grupo 03), visando atender as necessidades dos hospitais e estabelecimentos da rede estadual de saúde de Pernambuco | F57: 45796 | G57: Autorizada Sucesso | H57: Não Localizado
A58: C.027-ARP.0063.00.2024.GOV.FES-PE.PE | B58: HOSPITAL REGIONAL DO AGRESTE DR.WALDEMIRO FERREIRA | C58: Consumo | D58: ARP.0063.00.2024.GOV.FES-PE.PE | E58: Formação de Registro de Preços, por um período de 12 (doze) meses, para eventual aquisição de MATERIAL MÉDICO HOSPITALAR (Grupo 04) visando atender a demanda dos hospitais e estabelecimentos da rede estadual de saúde de Pernambuco. | F58: 45796 | G58: Autorizada Sucesso | H58: Não Localizado
A59: C.027-ARP.0063.00.2024.GOV.FES-PE.PE | B59: HOSPITAL REGIONAL DO AGRESTE DR.WALDEMIRO FERREIRA | C59: Consumo | D59: ARP.0061.02.2024.GOV.FES-PE.PE | E59: Registro de Preços para o fornecimento eventual de Medicamentos Controlados (grupo 02), conforme especificações e quantitativos previstos no Anexo I do Edital, para atender a demanda dos hospitais e estabelecimentos da rede estadual de saúde de Pernambuco indicados no mencionado Anexo. | F59: 45793 | G59: Autorizada Sucesso | H59: Não Localizado
A60: C.013-ARP.0063.10.2024.GOV.FES-PE.PE | B60: HOSPITAL REGIONAL DO AGRESTE DR.WALDEMIRO FERREIRA | C60: Consumo | D60: ARP.0063.10.2024.GOV.FES-PE.PE | E60: Formação de Registro de Preços, por um período de 12 (doze) meses, para eventual aquisição de MATERIAL MÉDICO HOSPITALAR (Grupo 04) visando atender a demanda dos hospitais e estabelecimentos da rede estadual de saúde de Pernambuco. | F60: 45785 | G60: Autorizada Sucesso | H60: Não Localizado
A61: C.002-ARP.0017.03.2024.GOV.HOF.PE | B61: HOSPITAL REGIONAL DO AGRESTE DR.WALDEMIRO FERREIRA | C61: Consumo | D61: ARP.0017.03.2024.GOV.HOF.PE | E61: Registro de Preços para Aquisição de Medicamentos Clínicos Respiratórios para o abastecimento de 12 (doze) meses para atender as necessidades do HOF. | F61: 45783 | G61: Autorizada Sucesso | H61: Não Localizado
A62: C.017-ARP.0061.00.2024.GOV.FES-PE.PE | B62: HOSPITAL REGIONAL DO AGRESTE DR.WALDEMIRO FERREIRA | C62: Consumo | D62: ARP.0061.00.2024.GOV.FES-PE.PE | E62: Registro de Preços para o fornecimento eventual de Medicamentos Controlados (grupo 02), conforme especificações e quantitativos previstos no Anexo I do Edital, para atender a demanda dos hospitais e estabelecimentos da rede estadual de saúde de Pernambuco indicados no mencionado Anexo. | F62: 45783 | G62: Autorizada Sucesso | H62: Não Localizado
A63: C.003-ARP.0047.00.2025.GOV.FES-PE.PE | B63: HOSPITAL REGIONAL DO AGRESTE DR.WALDEMIRO FERREIRA | C63: Consumo | D63: ARP.0047.00.2025.GOV.FES-PE.PE | E63: Registro de Preços para o fornecimento eventual de Dispositivos médicos do Tipo: Reagente para testes Hematológicos, com cessão gratuita de 02 (dois) equipamentos automatizados, sendo 1 (um) principal e outro suporte, com manutenção preventiva e corretiva (para cada lote) visando atender as necessidades dos hospitais e estabelecimentos vinculados à Secretaria Estadual de Saúde de Pernambuco, conforme especificações e quantitativos previstos no Termo de Referência | F63: 45783 | G63: Autorizada Sucesso | H63: 2300001209.000033/2025-11 | I63: nof | J63: 45959
A64: C.031-ARP.0052.03.2024.GOV.FES-PE.PE | B64: HOSPITAL REGIONAL DO AGRESTE DR.WALDEMIRO FERREIRA | C64: Consumo | D64: ARP.0052.03.2024.GOV.FES-PE.PE | E64: Formação de registro de preços para o eventual fornecimento de medicamentos injetáveis (grupo 06), visando atender a demanda dos Hospitais e Estabelecimentos da Rede Estadual de Saúde de Pernambuco | F64: 45783 | G64: Autorizada Sucesso | H64: Não Localizado
A65: C.019-ARP.0058.00.2024.GOV.FES-PE.PE | B65: HOSPITAL REGIONAL DO AGRESTE DR.WALDEMIRO FERREIRA | C65: Consumo | D65: ARP.0058.00.2024.GOV.FES-PE.PE | E65: Formação de Registro de Preços, por um período de 12 (doze) meses, para eventual aquisição de MATERIAL MÉDICO HOSPITALAR (Grupo 06) visando atender a demanda dos hospitais e estabelecimentos da rede estadual de saúde de Pernambuco. | F65: 45782 | G65: Autorizada Sucesso | H65: Não Localizado
A66: C.008-ARP.0097.04.2024.GOV.FES-PE.PE | B66: HOSPITAL REGIONAL DO AGRESTE DR.WALDEMIRO FERREIRA | C66: Consumo | D66: ARP.0097.04.2024.GOV.FES-PE.PE | E66: Formação de Ata de Registro de Preços para o fornecimento eventual de medicamentos COMPRIMIDOS (Grupo 06), visando atender as necessidades dos Hospitais e estabelecimentos da rede estadual de saúde de Pernambuco. | F66: 45774 | G66: Autorizada Sucesso | H66: Não Localizado
A67: C.009-ARP.0052.12.2024.GOV.CISAM.PE | B67: HOSPITAL REGIONAL DO AGRESTE DR.WALDEMIRO FERREIRA | C67: Consumo | D67: ARP.0052.12.2024.GOV.CISAM.PE | E67: REGISTRO DE PREÇOS PARA O EVENTUAL FORNECIMENTO DE MEDICAMENTOS PARA O CISAM/UPE E DEMAIS ÓRGÃOS PARTICIPANTES | F67: 45774 | G67: Autorizada Sucesso | H67: 2300001213.000120/2025-17 | I67: nof | J67: 45959
A68: C.005-ARP.0052.11.2024.GOV.CISAM.PE | B68: HOSPITAL REGIONAL DO AGRESTE DR.WALDEMIRO FERREIRA | C68: Consumo | D68: ARP.0052.11.2024.GOV.CISAM.PE | E68: REGISTRO DE PREÇOS PARA O EVENTUAL FORNECIMENTO DE MEDICAMENTOS PARA O CISAM/UPE E DEMAIS ÓRGÃOS PARTICIPANTES | F68: 45770 | G68: Autorizada Sucesso | H68: Não Localizado
A69: C.004-ARP.0052.11.2024.GOV.CISAM.PE | B69: HOSPITAL REGIONAL DO AGRESTE DR.WALDEMIRO FERREIRA | C69: Consumo | D69: ARP.0052.11.2024.GOV.CISAM.PE | E69: REGISTRO DE PREÇOS PARA O EVENTUAL FORNECIMENTO DE MEDICAMENTOS PARA O CISAM/UPE E DEMAIS ÓRGÃOS PARTICIPANTES | F69: 45770 | G69: Autorizada Sucesso | H69: Não Localizado
A70: C.002-ARP.0021.12.2024.GOV.HOF.PE | B70: HOSPITAL REGIONAL DO AGRESTE DR.WALDEMIRO FERREIRA | C70: Consumo | D70: ARP.0021.12.2024.GOV.HOF.PE | E70: Formação de Registro de Preços para o fornecimento eventual de Material Médico Hospitalar INSUMOS PARA HIGIENE E PROTEÇÃO, visando atender a necessidade do do Hospital Otávio de Freitas (HOF), Hospital Regional do Agreste (HRA), Hospital Getúlio Vargas (HGV), Hospital Agamenon Magalhães (HAM), | F70: 45763 | G70: Autorizada Sucesso | H70: Não Localizado
A71: C.003-ARP.0003.00.2025.GOV.DASIS.PE | B71: HOSPITAL REGIONAL DO AGRESTE DR.WALDEMIRO FERREIRA | C71: Consumo | D71: ARP.0003.00.2025.GOV.DASIS.PE | E71: Registro de Preços para contratação eventual de prestação de serviços de esterilização, reesterilização e /ou processamento de artigos médicos hospitalares, visando atender as necessidades do Centro Médico Hospitalar da PMPE/CBMPE e do Hospital Regional do Agreste Doutor Waldemiro Ferreira | F71: 45761 | G71: Autorizada Sucesso | H71: Não Localizado
A72: C.016-ARP.0046.01.2024.GOV.FES-PE.PE | B72: HOSPITAL REGIONAL DO AGRESTE DR.WALDEMIRO FERREIRA | C72: Consumo | D72: ARP.0046.01.2024.GOV.FES-PE.PE | E72: Registro de Preços para a eventual aquisição de Medicamentos Injetáveis (grupo 05) visando atender a demanda dos hospitais e estabelecimentos da rede estadual de saúde de Pernambuco | F72: 45761 | G72: Autorizada Sucesso | H72: Não Localizado
A73: C.022-ARP.0046.02.2024.GOV.FES-PE.PE | B73: HOSPITAL REGIONAL DO AGRESTE DR.WALDEMIRO FERREIRA | C73: Consumo | D73: ARP.0046.02.2024.GOV.FES-PE.PE | E73: Registro de Preços para a eventual aquisição de Medicamentos Injetáveis (grupo 05) visando atender a demanda dos hospitais e estabelecimentos da rede estadual de saúde de Pernambuco | F73: 45761 | G73: Autorizada Sucesso | H73: Não Localizado
A74: C.003-ARP.0044.04.2025.GOV.FES-PE.PE | B74: HOSPITAL REGIONAL DO AGRESTE DR.WALDEMIRO FERREIRA | C74: Consumo | D74: ARP.0044.04.2025.GOV.FES-PE.PE | E74: Formação de Registro de Preços para o fornecimento eventual de dispositivos médicos do Tipo DRENOS visando atender as necessidades dos hospitais e estabelecimentos vinculados à Secretaria Estadual de Saúde de Pernambuco, conforme as condições, especificações, quantidades e exigências contidas no Termo de Referência | F74: 45761 | G74: Autorizada Sucesso | H74: Não Localizado
A75: C.001-ARP.0059.02.2025.GOV.FES-PE.PE | B75: HOSPITAL REGIONAL DO AGRESTE DR.WALDEMIRO FERREIRA | C75: Consumo | D75: ARP.0059.02.2025.GOV.FES-PE.PE | E75: FORMAÇÃO DE REGISTRO DE PREÇOS PARA O FORNECIMENTO DE DISPOSITIVOS MÉDICOS, DO TIPO BOLSAS PARA OSTOMIA, VISANDO ATENDER AS NECESSIDADES DOS HOSPITAIS E ESTABELECIMENTOS VINCULADOS À SECRETARIA ESTADUAL DE SAÚDE DE PERNAMBUCO. | F75: 45757 | G75: Autorizada Sucesso | H75: Não Localizado
A76: C.001-ARP.0059.00.2025.GOV.FES-PE.PE | B76: HOSPITAL REGIONAL DO AGRESTE DR.WALDEMIRO FERREIRA | C76: Consumo | D76: ARP.0059.00.2025.GOV.FES-PE.PE | E76: FORMAÇÃO DE REGISTRO DE PREÇOS PARA O FORNECIMENTO DE DISPOSITIVOS MÉDICOS, DO TIPO BOLSAS PARA OSTOMIA, VISANDO ATENDER AS NECESSIDADES DOS HOSPITAIS E ESTABELECIMENTOS VINCULADOS À SECRETARIA ESTADUAL DE SAÚDE DE PERNAMBUCO. | F76: 45756 | G76: Autorizada Sucesso | H76: Não Localizado
A77: C.003-ARP.0021.03.2024.GOV.HOF.PE | B77: HOSPITAL REGIONAL DO AGRESTE DR.WALDEMIRO FERREIRA | C77: Consumo | D77: ARP.0021.03.2024.GOV.HOF.PE | E77: Formação de Registro de Preços para o fornecimento eventual de Material Médico Hospitalar INSUMOS PARA HIGIENE E PROTEÇÃO, visando atender a necessidade do do Hospital Otávio de Freitas (HOF), Hospital Regional do Agreste (HRA), Hospital Getúlio Vargas (HGV), Hospital Agamenon Magalhães (HAM), | F77: 45756 | G77: Autorizada Sucesso | H77: Não Localizado
A78: C.007-ARP.0010.05.2025.GOV.FES-PE.PE | B78: HOSPITAL REGIONAL DO AGRESTE DR.WALDEMIRO FERREIRA | C78: Consumo | D78: ARP.0010.05.2025.GOV.FES-PE.PE | E78: REGISTRO DE PREÇOS PARA A EVENTUAL AQUISIÇÃODE DISPOSITIVOS MÉDICOS DO TIPO PRODUTOS MÉDICOS (PAPEL CIRÚRGICO, ESCOVA PARA LIMPEZA DE MATERIAIS, EMBALAGEM DESCARTÁVEIS PARA ESTERILIZAÇÃO) VISANDO ATENDER A DEMANDA DOS HOSPITAIS E ESTABELECIMENTOS DA REDE ESTADUAL DE SAÚDE DE PERNAMBUCO, SES/PE. | F78: 45756 | G78: Autorizada Sucesso | H78: Não Localizado
A79: C.003-ARP.0021.00.2024.GOV.HOF.PE | B79: HOSPITAL REGIONAL DO AGRESTE DR.WALDEMIRO FERREIRA | C79: Consumo | D79: ARP.0021.00.2024.GOV.HOF.PE | E79: Formação de Registro de Preços para o fornecimento eventual de Material Médico Hospitalar INSUMOS PARA HIGIENE E PROTEÇÃO, visando atender a necessidade do do Hospital Otávio de Freitas (HOF), Hospital Regional do Agreste (HRA), Hospital Getúlio Vargas (HGV), Hospital Agamenon Magalhães (HAM), | F79: 45756 | G79: Autorizada Sucesso | H79: 2300001213.000073/2025-01 | I79: nof | J79: 45959
A80: C.004-ARP.0036.10.2025.GOV.FES-PE.PE | B80: HOSPITAL REGIONAL DO AGRESTE DR.WALDEMIRO FERREIRA | C80: Consumo | D80: ARP.0036.10.2025.GOV.FES-PE.PE | E80: Formação de Registro de Preços para o fornecimento eventual de Medicamentos Injetáveis – Grupo 01 com a finalidade de atender às necessidades dos hospitais e estabelecimentos vinculados à Secretaria E | F80: 45750 | G80: Autorizada Sucesso | H80: Não Localizado
A81: C.003-ARP.0031.02.2025.GOV.FES-PE.PE | B81: HOSPITAL REGIONAL DO AGRESTE DR.WALDEMIRO FERREIRA | C81: Consumo | D81: ARP.0031.02.2025.GOV.FES-PE.PE | E81: Formação de Registro de Preços para o fornecimento eventual de Dispositivos Médicos do tipo Diversos (grupo 01) para atender às necessidades dos hospitais e estabelecimentos vinculados a SES/PE | F81: 45750 | G81: Autorizada Sucesso | H81: Não Localizado
A82: C.004-ARP.0054.07.2025.GOV.FES-PE.PE | B82: HOSPITAL REGIONAL DO AGRESTE DR.WALDEMIRO FERREIRA | C82: Consumo | D82: ARP.0054.07.2025.GOV.FES-PE.PE | E82: Formação de Registro de Preços para Eventual Fornecimento de Dispositivos Médicos do tipo: Antissépticos, Desinfetantes e Saneantes e Cal sodada | F82: 45749 | G82: Autorizada Sucesso | H82: Não Localizado
A83: C.013-ARP.0009.00.2025.GOV.FES-PE.PE | B83: HOSPITAL REGIONAL DO AGRESTE DR.WALDEMIRO FERREIRA | C83: Consumo | D83: ARP.0009.00.2025.GOV.FES-PE.PE | E83: Registro de Preços para aquisição de Material Médico Hospitalar - Luvas (Unificado) | F83: 45748 | G83: Autorizada Sucesso | H83: Não Localizado
A84: C.016-ARP.0009.02.2025.GOV.FES-PE.PE | B84: HOSPITAL REGIONAL DO AGRESTE DR.WALDEMIRO FERREIRA | C84: Consumo | D84: ARP.0009.02.2025.GOV.FES-PE.PE | E84: Registro de Preços para aquisição de Material Médico Hospitalar - Luvas (Unificado) | F84: 45748 | G84: Autorizada Sucesso | H84: Não Localizado
A85: C.021-ARP.0063.00.2024.GOV.FES-PE.PE | B85: HOSPITAL REGIONAL DO AGRESTE DR.WALDEMIRO FERREIRA | C85: Consumo | D85: ARP.0063.00.2024.GOV.FES-PE.PE | E85: Formação de Registro de Preços, por um período de 12 (doze) meses, para eventual aquisição de MATERIAL MÉDICO HOSPITALAR (Grupo 04) visando atender a demanda dos hospitais e estabelecimentos da rede estadual de saúde de Pernambuco. | F85: 45747 | G85: Autorizada Sucesso | H85: Não Localizado
A86: C.027-ARP.0064.01.2024.GOV.FES-PE.PE | B86: HOSPITAL REGIONAL DO AGRESTE DR.WALDEMIRO FERREIRA | C86: Consumo | D86: ARP.0064.01.2024.GOV.FES-PE.PE | E86: PREGÃO ELETRÔNICO PARA FORMAÇÃO DE REGISTRO DE PREÇOS PARA A EVENTUAL FORNECIMENTO DE MEDICAMENTOS INJETÁVEIS (GRUPO 04) VISANDO ATENDER A DEMANDA DOS HOSPITAIS E ESTABELECIMENTOS DA REDE ESTADUAL DE SAÚDE DE PERNAMBUCO. | F86: 45747 | G86: Autorizada Sucesso | H86: Não Localizado
A87: C.016-ARP.0022.01.2025.GOV.FES-PE.PE | B87: HOSPITAL REGIONAL DO AGRESTE DR.WALDEMIRO FERREIRA | C87: Consumo | D87: ARP.0022.01.2025.GOV.FES-PE.PE | E87: Formação de Registro de Preços para o fornecimento eventual de Medicamentos Controlados – Grupo 02 com a finalidade de atender às necessidades dos hospitais e estabelecimentos vinculados à SES/PE | F87: 45742 | G87: Autorizada Sucesso | H87: Não Localizado
A88: C.002-ARP.0006.02.2025.GOV.HOF.PE | B88: HOSPITAL REGIONAL DO AGRESTE DR.WALDEMIRO FERREIRA | C88: Consumo | D88: ARP.0006.02.2025.GOV.HOF.PE | E88: Registro de Preços para fornecimento de Material Médico hospitalar para abastecimento de 12 (doze) meses, cujo objeto: COLETOR DE AMOSTRA BIOLOGICA E DE URINA. | F88: 45737 | G88: Autorizada Sucesso | H88: 2300001213.000053/2025-22 | I88: nof | J88: 45959
A89: C.001-ARP.0048.03.2025.GOV.FES-PE.PE | B89: HOSPITAL REGIONAL DO AGRESTE DR.WALDEMIRO FERREIRA | C89: Consumo | D89: ARP.0048.03.2025.GOV.FES-PE.PE | E89: FORMAÇÃO DE ATA DE REGISTRO DE PREÇOS PARA O FORNECIMENTO EVENTUAL DE DISPOSITIVOS MÉDICOS DO TIPO: INSUMOS PARA O SERVIÇO DE ENDOSCOPIA – GRUPO 3, VISANDO ATENDER AS DEMANDAS DOS HOSPITAIS E ESTABELECIMENTOS VINCULADOS À SECRETARIA ESTADUAL DE SAÚDE DE PERNAMBUCO. | F89: 45736 | G89: Autorizada Sucesso | H89: 2300001207.000068/2025-70 | I89: nof | J89: 45959
A90: C.001-ARP.0048.02.2025.GOV.FES-PE.PE | B90: HOSPITAL REGIONAL DO AGRESTE DR.WALDEMIRO FERREIRA | C90: Consumo | D90: ARP.0048.02.2025.GOV.FES-PE.PE | E90: FORMAÇÃO DE ATA DE REGISTRO DE PREÇOS PARA O FORNECIMENTO EVENTUAL DE DISPOSITIVOS MÉDICOS DO TIPO: INSUMOS PARA O SERVIÇO DE ENDOSCOPIA – GRUPO 3, VISANDO ATENDER AS DEMANDAS DOS HOSPITAIS E ESTABELECIMENTOS VINCULADOS À SECRETARIA ESTADUAL DE SAÚDE DE PERNAMBUCO. | F90: 45736 | G90: Autorizada Sucesso | H90: 2300001207.000067/2025-25 | I90: nof | J90: 45959
A91: C.013-ARP.0005.01.2025.GOV.FES-PE.PE | B91: HOSPITAL REGIONAL DO AGRESTE DR.WALDEMIRO FERREIRA | C91: Consumo | D91: ARP.0005.01.2025.GOV.FES-PE.PE | E91: Formação de Registro de Preços para o Fornecimento eventual de Dispositivos Médicos do tipo Cateter/Sonda com a finalidade de atender às necessidades dos hospitais e estabelecimentos vinculados à SES | F91: 45735 | G91: Autorizada Sucesso | H91: 2300001207.000022/2025-51 | I91: nof | J91: 45959
A92: C.001-ARP.0048.01.2025.GOV.FES-PE.PE | B92: HOSPITAL REGIONAL DO AGRESTE DR.WALDEMIRO FERREIRA | C92: Consumo | D92: ARP.0048.01.2025.GOV.FES-PE.PE | E92: FORMAÇÃO DE ATA DE REGISTRO DE PREÇOS PARA O FORNECIMENTO EVENTUAL DE DISPOSITIVOS MÉDICOS DO TIPO: INSUMOS PARA O SERVIÇO DE ENDOSCOPIA – GRUPO 3, VISANDO ATENDER AS DEMANDAS DOS HOSPITAIS E ESTABELECIMENTOS VINCULADOS À SECRETARIA ESTADUAL DE SAÚDE DE PERNAMBUCO. | F92: 45733 | G92: Autorizada Sucesso | H92: 2300001207.000064/2025-91 | I92: nof | J92: 45959
A93: C.001-ARP.0048.00.2025.GOV.FES-PE.PE | B93: HOSPITAL REGIONAL DO AGRESTE DR.WALDEMIRO FERREIRA | C93: Consumo | D93: ARP.0048.00.2025.GOV.FES-PE.PE | E93: FORMAÇÃO DE ATA DE REGISTRO DE PREÇOS PARA O FORNECIMENTO EVENTUAL DE DISPOSITIVOS MÉDICOS DO TIPO: INSUMOS PARA O SERVIÇO DE ENDOSCOPIA – GRUPO 3, VISANDO ATENDER AS DEMANDAS DOS HOSPITAIS E ESTABELECIMENTOS VINCULADOS À SECRETARIA ESTADUAL DE SAÚDE DE PERNAMBUCO. | F93: 45733 | G93: Autorizada Sucesso | H93: 2300001207.000065/2025-36 | I93: nof | J93: 45959
A94: C.014-ARP.0009.02.2025.GOV.FES-PE.PE | B94: HOSPITAL REGIONAL DO AGRESTE DR.WALDEMIRO FERREIRA | C94: Consumo | D94: ARP.0009.02.2025.GOV.FES-PE.PE | E94: Registro de Preços para aquisição de Material Médico Hospitalar - Luvas (Unificado) | F94: 45728 | G94: Autorizada Sucesso | H94: Não Localizado
A95: C.006-ARP.0010.00.2025.GOV.CISAM.PE | B95: HOSPITAL REGIONAL DO AGRESTE DR.WALDEMIRO FERREIRA | C95: Consumo | D95: ARP.0010.00.2025.GOV.CISAM.PE | E95: REGISTRO DE PREÇOS PARA FORNECIMENTO EVENTUAL DE MATERIAIS MÉDICO-HOSPITALARES (DIVERSOS), VISANDO ATENDER AS NECESSIDADES DO CISAM/UPE E DEMAIS ÓRGÃOS PARTICIPANTES . | F95: 45728 | G95: Autorizada Sucesso | H95: Não Localizado
A96: C.015-ARPC.0001.00.2025.GOV.SAD.PE | B96: HOSPITAL REGIONAL DO AGRESTE DR.WALDEMIRO FERREIRA | C96: Consumo | D96: ARPC.0001.00.2025.GOV.SAD.PE | E96: Formação de Registro de Preços Corporativo para o fornecimento eventual de Etiqueta Patrimonial, visando atender às necessidades dos órgãos da Administração Direta, Fundos Especiais, Autarquias e Fundações Públicas integrantes do Poder Executivo do Estado de Pernambuco | F96: 45728 | G96: Autorizada Sucesso | H96: 2300002544.000012/2025-57 | I96: nof | J96: 45959
A97: C.002-ARPC.0011.00.2025.GOV.SAD.PE | B97: HOSPITAL REGIONAL DO AGRESTE DR.WALDEMIRO FERREIRA | C97: Consumo | D97: ARPC.0011.00.2025.GOV.SAD.PE | E97: Registro de Preços para o fornecimento eventual de material de expediente sustentável visando atender as necessidades dos órgãos da Administração Direta, dos fundos especiais, Autarquias e Fundações Públicas integrantes do Poder Executivo do Estado de Pernambuco | F97: 45728 | G97: Autorizada Sucesso | H97: 2300002544.000024/2025-81 | I97: nof | J97: 45959
A98: C.018-ARPC.0002.00.2025.GOV.SAD.PE | B98: HOSPITAL REGIONAL DO AGRESTE DR.WALDEMIRO FERREIRA | C98: Consumo | D98: ARPC.0002.00.2025.GOV.SAD.PE | E98: Registro de preços corporativo para a eventual aquisição de Material Médico-Hospitalar – Seringas e Agulhas Hipodérmicas, para atender às demandas dos órgãos da Administração Direta, dos Fundos Especiais, Autarquias e Fundações Públicas integrantes do Poder Executivo do Estado de Pernambuco | F98: 45727 | G98: Autorizada Sucesso | H98: 2300001213.000044/2025-31 | I98: nof | J98: 45959
A99: C.004-ARP.0034.00.2025.GOV.FES-PE.PE | B99: HOSPITAL REGIONAL DO AGRESTE DR.WALDEMIRO FERREIRA | C99: Consumo | D99: ARP.0034.00.2025.GOV.FES-PE.PE | E99: Registro de Preços para o fornecimento eventual de dispositivos médicos do tipo: Aparelho descartável de fisioterapia respiratória, Cânulas de Traqueostomia, Guedel e Máscaras para Oxigenoterapia e Nebulização | F99: 45718 | G99: Autorizada Sucesso | H99: 2300001213.000018/2025-11 | I99: nof | J99: 45959
A100: C.006-ARP.0003.01.2025.GOV.FES-PE.PE | B100: HOSPITAL REGIONAL DO AGRESTE DR.WALDEMIRO FERREIRA | C100: Consumo | D100: ARP.0003.01.2025.GOV.FES-PE.PE | E100: Formação de Registro de Preços para o fornecimento eventual de Dispositivos Médicos do tipo Curativos com a finalidade de atender às necessidades dos hospitais e estabelecimentos vinculados à SES/PE | F100: 45715 | G100: Autorizada Sucesso | H100: Não Localizado
A101: C.001-ARP.0028.02.2025.GOV.FES-PE.PE | B101: HOSPITAL REGIONAL DO AGRESTE DR.WALDEMIRO FERREIRA | C101: Consumo | D101: ARP.0028.02.2025.GOV.FES-PE.PE | E101: Formação de Registro de Preços para o fornecimento eventual de Dispositivos Médicos do tipo Ataduras, Compressas e Algodão com a finalidade de atender às necessidades dos hospitais e estabelecimentos | F101: 45713 | G101: Autorizada | H101: Não Localizado
A102: C.004-ARP.0022.03.2025.GOV.FES-PE.PE | B102: HOSPITAL REGIONAL DO AGRESTE DR.WALDEMIRO FERREIRA | C102: Consumo | D102: ARP.0022.03.2025.GOV.FES-PE.PE | E102: Formação de Registro de Preços para o fornecimento eventual de Medicamentos Controlados – Grupo 02 com a finalidade de atender às necessidades dos hospitais e estabelecimentos vinculados à SES/PE | F102: 45713 | G102: Autorizada Sucesso | H102: Não Localizado
...

Sheet TODOS OS PROCESSOS ATUALIZADOS 
A1: Número da solicitação | B1: Unidade gestora | C1: Tipo da solicitação | D1: Número da ata | E1: Objeto | F1: Data de solicitação | G1: Situação Atual PE INTEGRADO | H1: Situação Monitoramento | I1: Status | J1: Column 20 | K1: Column 21 | L1: Column 22 | M1: Column 23 | N1: Column 24
A2: A.006-ARP.1036.00.2025.GOV.CISAM.PE | B2: HOSPITAL REGIONAL DO AGRESTE DR.WALDEMIRO FERREIRA | C2: Adesão | D2: ARP.1036.00.2025.GOV.CISAM.PE | E2: REGISTRO DE PREÇOS PARA FORNECIMENTO EVENTUAL DE MEDICAMENTOS INJETÁVEIS GRUPO 1 VISANDO ATENDER AS NECESSIDADES DO CISAM/UPE | F2: 45973 | G2: Em configuração | I2: =IF(OR(H2="PROCESSO NÃO ENCONTRADO", G2="PROCESSO NÃO ENCONTRADO"), "PROCESSO NÃO ENCONTRADO", IF(H2=G2,"PROCESSO AINDA NÃO FOI ATUALIZADO","PROCESSO FOI ATUALIZADO")) -> PROCESSO FOI ATUALIZADO
A3: A.002-ARP.0503.00.2025.EXT.HGJMM.RN | B3: HOSPITAL REGIONAL DO AGRESTE DR.WALDEMIRO FERREIRA | C3: Adesão | D3: ARP.0503.00.2025.EXT.HGJMM.RN | E3: Aquisição de Medicamentos - PENICILINAS E CEFALOSPORINAS para atender a demanda desta unidade hospitalar | F3: 45966 | G3: Encaminhada para o orçamento | I3: =IF(OR(H3="PROCESSO NÃO ENCONTRADO", G3="PROCESSO NÃO ENCONTRADO"), "PROCESSO NÃO ENCONTRADO", IF(H3=G3,"PROCESSO AINDA NÃO FOI ATUALIZADO","PROCESSO FOI ATUALIZADO")) -> PROCESSO FOI ATUALIZADO
A4: A.001-ARP.0503.00.2025.EXT.HGJMM.RN | B4: HOSPITAL REGIONAL DO AGRESTE DR.WALDEMIRO FERREIRA | C4: Adesão | D4: ARP.0503.00.2025.EXT.HGJMM.RN | E4: Aquisição de Medicamentos - PENICILINAS E CEFALOSPORINAS para atender a demanda desta unidade hospitalar | F4: 45965 | G4: Cancelada | I4: =IF(OR(H4="PROCESSO NÃO ENCONTRADO", G4="PROCESSO NÃO ENCONTRADO"), "PROCESSO NÃO ENCONTRADO", IF(H4=G4,"PROCESSO AINDA NÃO FOI ATUALIZADO","PROCESSO FOI ATUALIZADO")) -> PROCESSO FOI ATUALIZADO
A5: A.014-ARP.0004.00.2025.GOV.HR.PE | B5: HOSPITAL REGIONAL DO AGRESTE DR.WALDEMIRO FERREIRA | C5: Adesão | D5: ARP.0004.00.2025.GOV.HR.PE | E5: Formação de Ata de Registro de Preços para o fornecimento eventual de produtos médicos (MATERIAL MÉDICO HOSPITALAR), com cessão de equipamentos em regime de comodato, visando atender as necessidades do Hospital da Restauração Gov. Paulo Guerra. | F5: 45961 | G5: Autorizada Sucesso | I5: =IF(OR(H5="PROCESSO NÃO ENCONTRADO", G5="PROCESSO NÃO ENCONTRADO"), "PROCESSO NÃO ENCONTRADO", IF(H5=G5,"PROCESSO AINDA NÃO FOI ATUALIZADO","PROCESSO FOI ATUALIZADO")) -> PROCESSO FOI ATUALIZADO
A6: A.002-ARP.0012.00.2025.EXT.HMAR.PE | B6: HOSPITAL REGIONAL DO AGRESTE DR.WALDEMIRO FERREIRA | C6: Adesão | D6: ARP.0012.00.2025.EXT.HMAR.PE | E6: Aquisição de Materiais e insumos Laboratoriais (LAC I) -RIBBON | F6: 45960 | G6: Em configuração | I6: =IF(OR(H6="PROCESSO NÃO ENCONTRADO", G6="PROCESSO NÃO ENCONTRADO"), "PROCESSO NÃO ENCONTRADO", IF(H6=G6,"PROCESSO AINDA NÃO FOI ATUALIZADO","PROCESSO FOI ATUALIZADO")) -> PROCESSO FOI ATUALIZADO
A7: A.004-ARP.0010.04.2025.GOV.HOF.PE | B7: HOSPITAL REGIONAL DO AGRESTE DR.WALDEMIRO FERREIRA | C7: Adesão | D7: ARP.0010.04.2025.GOV.HOF.PE | E7: Registro de Preços para eventual fornecimento de dispositivos médicos INSUMOS PARA O SERVIÇO DE ENDOSCOPIA. | F7: 45959 | G7: Em configuração | I7: =IF(OR(H7="PROCESSO NÃO ENCONTRADO", G7="PROCESSO NÃO ENCONTRADO"), "PROCESSO NÃO ENCONTRADO", IF(H7=G7,"PROCESSO AINDA NÃO FOI ATUALIZADO","PROCESSO FOI ATUALIZADO")) -> PROCESSO FOI ATUALIZADO
A8: A.026-ARP.0005.12.2025.GOV.HEMOPE.PE | B8: HOSPITAL REGIONAL DO AGRESTE DR.WALDEMIRO FERREIRA | C8: Adesão | D8: ARP.0005.12.2025.GOV.HEMOPE.PE | E8: Formação de Ata de Registro de Preços para o fornecimento eventual de Material Médico Hospitalar - MMH Grupo 3 (eletrodos, equipos para alimentação enteral, parenteral, transfusão de sangue, escovas para limpeza de material, fios, fitas, lâmina de bisturi, fraldas e outros) | F8: 45958 | G8: Em configuração | I8: =IF(OR(H8="PROCESSO NÃO ENCONTRADO", G8="PROCESSO NÃO ENCONTRADO"), "PROCESSO NÃO ENCONTRADO", IF(H8=G8,"PROCESSO AINDA NÃO FOI ATUALIZADO","PROCESSO FOI ATUALIZADO")) -> PROCESSO FOI ATUALIZADO
A9: A.013-ARP.0013.02.2025.GOV.HOF.PE | B9: HOSPITAL REGIONAL DO AGRESTE DR.WALDEMIRO FERREIRA | C9: Adesão | D9: ARP.0013.02.2025.GOV.HOF.PE | E9: REGISTRO DE PREÇOS PARA O FORNECIMENTO DE DISPOSITIVOS MÉDICOS DO TIPO INSUMOS PARA OXIGENOTERAPIA, VISANDO ATENDER AS NECESSIDADES DO HOSPITAL OTÁVIO DE FREITAS. | F9: 45958 | G9: Em configuração | I9: =IF(OR(H9="PROCESSO NÃO ENCONTRADO", G9="PROCESSO NÃO ENCONTRADO"), "PROCESSO NÃO ENCONTRADO", IF(H9=G9,"PROCESSO AINDA NÃO FOI ATUALIZADO","PROCESSO FOI ATUALIZADO")) -> PROCESSO FOI ATUALIZADO
A10: A.002-ARP.0189.00.2025.GOV.HUOC.PE | B10: HOSPITAL REGIONAL DO AGRESTE DR.WALDEMIRO FERREIRA | C10: Adesão | D10: ARP.0189.00.2025.GOV.HUOC.PE | E10: Registro de Preços para o eventual fornecimento de MEDICAMENTOS ANTI-INFLAMATÓRIOS ESTEROIDAIS E NÃO ESTEROIDAIS (SEI nº 0040609437.000105/2025-52) | F10: 45953 | G10: Autorizada Sucesso | I10: =IF(OR(H10="PROCESSO NÃO ENCONTRADO", G10="PROCESSO NÃO ENCONTRADO"), "PROCESSO NÃO ENCONTRADO", IF(H10=G10,"PROCESSO AINDA NÃO FOI ATUALIZADO","PROCESSO FOI ATUALIZADO")) -> PROCESSO FOI ATUALIZADO
A11: A.008-ARP.0008.05.2025.GOV.HGV.PE | B11: HOSPITAL REGIONAL DO AGRESTE DR.WALDEMIRO FERREIRA | C11: Adesão | D11: ARP.0008.05.2025.GOV.HGV.PE | E11: Registro de Preços para o fornecimento eventual de MATERIAIS ESPECIAIS PARA ENDOSCOPIA | F11: 45946 | G11: Cancelada | I11: =IF(OR(H11="PROCESSO NÃO ENCONTRADO", G11="PROCESSO NÃO ENCONTRADO"), "PROCESSO NÃO ENCONTRADO", IF(H11=G11,"PROCESSO AINDA NÃO FOI ATUALIZADO","PROCESSO FOI ATUALIZADO")) -> PROCESSO FOI ATUALIZADO
A12: A.003-ARP.0073.00.2025.GOV.FES-PE.PE | B12: HOSPITAL REGIONAL DO AGRESTE DR.WALDEMIRO FERREIRA | C12: Adesão | D12: ARP.0073.00.2025.GOV.FES-PE.PE | E12: Registro de Preços para o fornecimento eventual de Dispositivos Médicos do tipo Materiais Médicos (Indicadores, cera, e cimento cirúrgico), conforme especificações e quantitativos previstos no Termo de Referência, visando atender as necessidades dos hospitais e estabelecimentos vinculados à Secretaria Estadual de Saúde de Pernambuco | F12: 45946 | G12: Autorizada Sucesso | I12: =IF(OR(H12="PROCESSO NÃO ENCONTRADO", G12="PROCESSO NÃO ENCONTRADO"), "PROCESSO NÃO ENCONTRADO", IF(H12=G12,"PROCESSO AINDA NÃO FOI ATUALIZADO","PROCESSO FOI ATUALIZADO")) -> PROCESSO FOI ATUALIZADO
A13: A.008-ARP.0001.00.2025.GOV.HR.PE | B13: HOSPITAL REGIONAL DO AGRESTE DR.WALDEMIRO FERREIRA | C13: Adesão | D13: ARP.0001.00.2025.GOV.HR.PE | E13: Registro de Preços para o eventual fornecimento de ÓRTESES, PRÓTESES E MATERIAIS ESPECIAIS - OPME’S (TRAUMATO I), visando atender as necessidades do Hospital da Restauração. | F13: 45943 | G13: Autorizada Sucesso | I13: =IF(OR(H13="PROCESSO NÃO ENCONTRADO", G13="PROCESSO NÃO ENCONTRADO"), "PROCESSO NÃO ENCONTRADO", IF(H13=G13,"PROCESSO AINDA NÃO FOI ATUALIZADO","PROCESSO FOI ATUALIZADO")) -> PROCESSO FOI ATUALIZADO
... A713: A.007-ARP.0013.01.2023.GOV.DASIS.PE | B713: HOSPITAL REGIONAL DO AGRESTE DR.WALDEMIRO FERREIRA | C713: Adesão | D713: ARP.0013.01.2023.GOV.DASIS.PE | E713: REGISTRO DE PREÇOS POR UM PERÍODO DE 12 (DOZE) MESES PARA O EVENTUAL FORNECIMENTO DE MEDICAMENTOS INJETÁVEIS BIOLÓGICOS PARA O CENTRO MEDICO HOSPITALAR DA PMPE/CBMPE. | F713: 45156 | G713: Autorizada Integrado | I713: =IF(OR(H713="PROCESSO NÃO ENCONTRADO", G713="PROCESSO NÃO ENCONTRADO"), "PROCESSO NÃO ENCONTRADO", IF(H713=G713,"PROCESSO AINDA NÃO FOI ATUALIZADO","PROCESSO FOI ATUALIZADO")) -> PROCESSO FOI ATUALIZADO
A714: A.002-ARP.0060.01.2023.GOV.HUOC.PE | B714: HOSPITAL REGIONAL DO AGRESTE DR.WALDEMIRO FERREIRA | C714: Adesão | D714: ARP.0060.01.2023.GOV.HUOC.PE | E714: Registro de Preços para eventual fornecimento de MEDICAMENTOS CLÍNICOS GERAIS (SEI nº 0040609437.000428/2022-01) | F714: 45154 | G714: Autorizada Sucesso | I714: =IF(OR(H714="PROCESSO NÃO ENCONTRADO",#REF!= "PROCESSO NÃO ENCONTRADO"), "PROCESSO NÃO ENCONTRADO", IF(H714=#REF!,"PROCESSO AINDA NÃO FOI ATUALIZADO","PROCESSO FOI ATUALIZADO")) -> #REF!
A715: A.001-ARP.0028.00.2023.GOV.HGV.PE | B715: HOSPITAL REGIONAL DO AGRESTE DR.WALDEMIRO FERREIRA | C715: Adesão | D715: ARP.0028.00.2023.GOV.HGV.PE | E715: FORMAÇÃO DE REGISTRO DE PREÇOS PARA EVENTUAL FORNECIMENTO DE MEDICAMENTOS - ANTIMICROBIANOS | F715: 45154 | G715: Cancelada | I715: =IF(OR(H715="PROCESSO NÃO ENCONTRADO",#REF!= "PROCESSO NÃO ENCONTRADO"), "PROCESSO NÃO ENCONTRADO", IF(H715=#REF!,"PROCESSO AINDA NÃO FOI ATUALIZADO","PROCESSO FOI ATUALIZADO")) -> #REF!
A716: A.001-ARP.0042.00.2023.GOV.HUOC.PE | B716: HOSPITAL REGIONAL DO AGRESTE DR.WALDEMIRO FERREIRA | C716: Adesão | D716: ARP.0042.00.2023.GOV.HUOC.PE | E716: REGISTRO DE PREÇO para eventual fornecimento de MATERIAIS MÉDICOS HOSPITALARES - KITS PARA GASTROSTOMIA ENDOSCÓPICA PERCUTÂNEA (SEI Nº 0040609459.000107/2022-41) | F716: 45141 | G716: Autorizada Sucesso | I716: =IF(OR(H716="PROCESSO NÃO ENCONTRADO",#REF!= "PROCESSO NÃO ENCONTRADO"), "PROCESSO NÃO ENCONTRADO", IF(H716=#REF!,"PROCESSO AINDA NÃO FOI ATUALIZADO","PROCESSO FOI ATUALIZADO")) -> #REF!
A717: A.001-ARP.0037.09.2023.GOV.PROCAPE.PE | B717: HOSPITAL REGIONAL DO AGRESTE DR.WALDEMIRO FERREIRA | C717: Adesão | D717: ARP.0037.09.2023.GOV.PROCAPE.PE | E717: REGISTRO DE PREÇOS PARA EVENTUAL FORNECIMENTO DE MATERIAL DE CONSUMO HOSPITALAR (MATERIAL PENSO) | F717: 45141 | G717: Autorizada Sucesso | I717: =IF(OR(H717="PROCESSO NÃO ENCONTRADO",#REF!= "PROCESSO NÃO ENCONTRADO"), "PROCESSO NÃO ENCONTRADO", IF(H717=#REF!,"PROCESSO AINDA NÃO FOI ATUALIZADO","PROCESSO FOI ATUALIZADO")) -> #REF!
A718: A.004-ARP.0032.12.2023.GOV.PROCAPE.PE | B718: HOSPITAL REGIONAL DO AGRESTE DR.WALDEMIRO FERREIRA | C718: Adesão | D718: ARP.0032.12.2023.GOV.PROCAPE.PE | E718: REGISTRO DE PREÇOS PARA EVENTUAL FORNECIMENTO DE MATERIAL DE CONSUMO HOSPITALAR (MEDICAMENTOS) | F718: 45141 | G718: Autorizada Sucesso | I718: =IF(OR(H718="PROCESSO NÃO ENCONTRADO",#REF!= "PROCESSO NÃO ENCONTRADO"), "PROCESSO NÃO ENCONTRADO", IF(H718=#REF!,"PROCESSO AINDA NÃO FOI ATUALIZADO","PROCESSO FOI ATUALIZADO")) -> #REF!
A719: A.001-ARP.0001.00.2023.GOV.DEFN.PE | B719: HOSPITAL REGIONAL DO AGRESTE DR.WALDEMIRO FERREIRA | C719: Adesão | D719: ARP.0001.00.2023.GOV.DEFN.PE | E719: REGISTRO DE PREÇOS PARA AQUISIÇÃO COM FORNECIMENTO PARCELADO DE MATERIAIS MÉDICO HOSPITALARES, PARA ATENDER DEMANDA DA POPULAÇÃO DO ARQUIPÉLAGO DE FERNANDO DE NORONHA. | F719: 45139 | G719: Autorizada Sucesso | I719: =IF(OR(H719="PROCESSO NÃO ENCONTRADO",#REF!= "PROCESSO NÃO ENCONTRADO"), "PROCESSO NÃO ENCONTRADO", IF(H719=#REF!,"PROCESSO AINDA NÃO FOI ATUALIZADO","PROCESSO FOI ATUALIZADO")) -> #REF!
A720: A.004-ARP.0047.06.2023.GOV.HUOC.PE | B720: HOSPITAL REGIONAL DO AGRESTE DR.WALDEMIRO FERREIRA | C720: Adesão | D720: ARP.0047.06.2023.GOV.HUOC.PE | E720: REGISTRO DE PREÇO para eventual fornecimento de MATERIAIS MÉDICOS HOSPITALARES - AGULHAS DIVERSAS (SEI: 0040609459.000008/2022-69) | F720: 45117 | G720: Autorizada Sucesso | I720: =IF(OR(H720="PROCESSO NÃO ENCONTRADO",#REF!= "PROCESSO NÃO ENCONTRADO"), "PROCESSO NÃO ENCONTRADO", IF(H720=#REF!,"PROCESSO AINDA NÃO FOI ATUALIZADO","PROCESSO FOI ATUALIZADO")) -> #REF!
A721: A.001-ARP.0025.12.2023.GOV.HR.PE | B721: HOSPITAL REGIONAL DO AGRESTE DR.WALDEMIRO FERREIRA | C721: Adesão | D721: ARP.0025.12.2023.GOV.HR.PE | E721: Formação de Registro de Preços, por um período de 12 (doze) meses, para eventual fornecimento de MEDICAMENTOS. | F721: 45117 | G721: Cancelada | I721: =IF(OR(H721="PROCESSO NÃO ENCONTRADO",#REF!= "PROCESSO NÃO ENCONTRADO"), "PROCESSO NÃO ENCONTRADO", IF(H721=#REF!,"PROCESSO AINDA NÃO FOI ATUALIZADO","PROCESSO FOI ATUALIZADO")) -> #REF!
A722: A.001-ARP.0009.00.2023.GOV.DASIS.PE | B722: HOSPITAL REGIONAL DO AGRESTE DR.WALDEMIRO FERREIRA | C722: Adesão | D722: ARP.0009.00.2023.GOV.DASIS.PE | E722: REGISTRO DE PREÇOS POR UM PERÍODO DE 12 (DOZE) MESES PARA EVENTUAL FORNECIMENTO DE KITS, REAGENTES, CONTROLE, CALIBRADORES E INSUMOS PARA REALIZAÇÃO DE DOSAGEM EM BIOQUÍMICA, IMUNOLOGIA, HORMÔNIOS, MARCADORES TUMORAIS E CARDÍACO, COM CESSÃO A TÍTULO DE COMODATO DE UM 01 (UM) EQUIPAMENTO PRINCIPAL E UM 01 (UM) EQUIPAMENTO BACKUP, NECESSÁRIOS AO SEU PROCESSAMENTO, VISANDO ATENDER ÀS NECESSIDADES DO SEACLIN DO CENTRO MÉDICO HOSPITALAR DA PMPE/CBMPE | F722: 45117 | G722: Cancelada | I722: =IF(OR(H722="PROCESSO NÃO ENCONTRADO",#REF!= "PROCESSO NÃO ENCONTRADO"), "PROCESSO NÃO ENCONTRADO", IF(H722=#REF!,"PROCESSO AINDA NÃO FOI ATUALIZADO","PROCESSO FOI ATUALIZADO")) -> #REF!
A723: A.002-ARP.0015.00.2023.GOV.HAM.PE | B723: HOSPITAL REGIONAL DO AGRESTE DR.WALDEMIRO FERREIRA | C723: Adesão | D723: ARP.0015.00.2023.GOV.HAM.PE | E723: FORMAÇÃO DE REGISTRO DE PREÇOS, COM VALIDADE DE 12 (DOZE) MESES, PARA FORNECIMENTO EVENTUAL DE MATERIAIS TÉCNICOS DE USOS HOSPITALARES, VISANDO ATENDER AS NECESSIDADES DO HOSPITAL AGAMENON MAGALHÃES E RESTAURAÇÃO | F723: 45098 | G723: Autorizada Sucesso | I723: =IF(OR(H723="PROCESSO NÃO ENCONTRADO",#REF!= "PROCESSO NÃO ENCONTRADO"), "PROCESSO NÃO ENCONTRADO", IF(H723=#REF!,"PROCESSO AINDA NÃO FOI ATUALIZADO","PROCESSO FOI ATUALIZADO")) -> #REF!
A724: A.002-ARP.0003.00.2023.GOV.HRA.PE | B724: HOSPITAL REGIONAL DO AGRESTE DR.WALDEMIRO FERREIRA | C724: Adesão | D724: ARP.0003.00.2023.GOV.HRA.PE | E724: REGISTRO DE PREÇOS PARA AQUISIÇÃO DE MEDICAMENTOS EM GERAL VI | F724: 45096 | G724: Cancelada | I724: =IF(OR(H724="PROCESSO NÃO ENCONTRADO",#REF!= "PROCESSO NÃO ENCONTRADO"), "PROCESSO NÃO ENCONTRADO", IF(H724=#REF!,"PROCESSO AINDA NÃO FOI ATUALIZADO","PROCESSO FOI ATUALIZADO")) -> #REF!
A725: A.001-ARP.0003.00.2023.GOV.HRA.PE | B725: HOSPITAL REGIONAL DO AGRESTE DR.WALDEMIRO FERREIRA | C725: Adesão | D725: ARP.0003.00.2023.GOV.HRA.PE | E725: REGISTRO DE PREÇOS PARA AQUISIÇÃO DE MEDICAMENTOS EM GERAL VI | F725: 45096 | G725: Cancelada | I725: =IF(OR(H725="PROCESSO NÃO ENCONTRADO",#REF!= "PROCESSO NÃO ENCONTRADO"), "PROCESSO NÃO ENCONTRADO", IF(H725=#REF!,"PROCESSO AINDA NÃO FOI ATUALIZADO","PROCESSO FOI ATUALIZADO")) -> #REF!
... A1094: C.001-ARP.0098.00.2024.GOV.FES-PE.PE | B1094: HOSPITAL REGIONAL DO AGRESTE DR.WALDEMIRO FERREIRA | C1094: Consumo | D1094: ARP.0098.00.2024.GOV.FES-PE.PE | E1094: Dispensa de licitação com fundamento no art. 75, inc. VIII da Lei nº 14.133/21, visando o Registro de Preços para eventual fornecimento de Dispositivos Médicos do tipo Avental para atender às necessi | F1094: 45679 | G1094: Autorizada Sucesso | I1094: =IF(OR(H1094="PROCESSO NÃO ENCONTRADO",#REF!= "PROCESSO NÃO ENCONTRADO"), "PROCESSO NÃO ENCONTRADO", IF(H1094=#REF!,"PROCESSO AINDA NÃO FOI ATUALIZADO","PROCESSO FOI ATUALIZADO")) -> #REF!
A1095: C.005-ARPC.0002.00.2025.GOV.SAD.PE | B1095: HOSPITAL REGIONAL DO AGRESTE DR.WALDEMIRO FERREIRA | C1095: Consumo | D1095: ARPC.0002.00.2025.GOV.SAD.PE | E1095: Registro de preços corporativo para a eventual aquisição de Material Médico-Hospitalar – Seringas e Agulhas Hipodérmicas, para atender às demandas dos órgãos da Administração Direta, dos Fundos Especiais, Autarquias e Fundações Públicas integrantes do Poder Executivo do Estado de Pernambuco | F1095: 45673 | G1095: Autorizada Sucesso
A1096: C.004-ARPC.0002.00.2025.GOV.SAD.PE | B1096: HOSPITAL REGIONAL DO AGRESTE DR.WALDEMIRO FERREIRA | C1096: Consumo | D1096: ARPC.0002.00.2025.GOV.SAD.PE | E1096: Registro de preços corporativo para a eventual aquisição de Material Médico-Hospitalar – Seringas e Agulhas Hipodérmicas, para atender às demandas dos órgãos da Administração Direta, dos Fundos Especiais, Autarquias e Fundações Públicas integrantes do Poder Executivo do Estado de Pernambuco | F1096: 45673 | G1096: Cancelada
A1097: C.002-ARPC.0001.00.2025.GOV.SAD.PE | B1097: HOSPITAL REGIONAL DO AGRESTE DR.WALDEMIRO FERREIRA | C1097: Consumo | D1097: ARPC.0001.00.2025.GOV.SAD.PE | E1097: Formação de Registro de Preços Corporativo para o fornecimento eventual de Etiqueta Patrimonial, visando atender às necessidades dos órgãos da Administração Direta, Fundos Especiais, Autarquias e Fundações Públicas integrantes do Poder Executivo do Estado de Pernambuco | F1097: 45673 | G1097: Cancelada
A1098: C.003-ARPC.0002.00.2025.GOV.SAD.PE | B1098: HOSPITAL REGIONAL DO AGRESTE DR.WALDEMIRO FERREIRA | C1098: Consumo | D1098: ARPC.0002.00.2025.GOV.SAD.PE | E1098: Registro de preços corporativo para a eventual aquisição de Material Médico-Hospitalar – Seringas e Agulhas Hipodérmicas, para atender às demandas dos órgãos da Administração Direta, dos Fundos Especiais, Autarquias e Fundações Públicas integrantes do Poder Executivo do Estado de Pernambuco | F1098: 45673 | G1098: Cancelada
A1099: C.037-ARPC.0018.00.2024.GOV.SAD.PE | B1099: HOSPITAL REGIONAL DO AGRESTE DR.WALDEMIRO FERREIRA | C1099: Consumo | D1099: ARPC.0018.00.2024.GOV.SAD.PE | E1099: Registro de Preços Corporativo para o fornecimento eventual de material médico-hospitalar – luvas descartáveis visando atender as necessidades dos órgãos da Administração Direta, Autarquias e Fundações Públicas integrantes do Poder Executivo do Estado de Pernambuco | F1099: 45646 | G1099: Autorizada Sucesso
A1100: C.029-ARP.0050.00.2024.GOV.FES-PE.PE | B1100: HOSPITAL REGIONAL DO AGRESTE DR.WALDEMIRO FERREIRA | C1100: Consumo | D1100: ARP.0050.00.2024.GOV.FES-PE.PE | E1100: Registro de Preços para a eventual aquisição de Medicamentos Controlados (grupo 03) visando atender a demanda dos hospitais e estabelecimentos da rede estadual de saúde de Pernambuco. | F1100: 45646 | G1100: Cancelada
A1101: C.020-ARP.0061.03.2024.GOV.FES-PE.PE | B1101: HOSPITAL REGIONAL DO AGRESTE DR.WALDEMIRO FERREIRA | C1101: Consumo | D1101: ARP.0061.03.2024.GOV.FES-PE.PE | E1101: Registro de Preços para o fornecimento eventual de Medicamentos Controlados (grupo 02), conforme especificações e quantitativos previstos no Anexo I do Edital, para atender a demanda dos hospitais e estabelecimentos da rede estadual de saúde de Pernambuco indicados no mencionado Anexo. | F1101: 45646 | G1101: Cancelada por fim vigencia ATA
A1102: C.002-ARP.0088.01.2024.GOV.CISAM.PE | B1102: HOSPITAL REGIONAL DO AGRESTE DR.WALDEMIRO FERREIRA | C1102: Consumo | D1102: ARP.0088.01.2024.GOV.CISAM.PE | E1102: REGISTRO DE PREÇOS PARA FORNECIMENTO EVENTUAL DE MATERIAIS MÉDICO-HOSPITALARES (DIVERSOS), VISANDO ATENDER AS NECESSIDADES DO CISAM/UPE E DEMAIS ÓRGÃOS PARTICIPANTES . | F1102: 45644 | G1102: Autorizada Sucesso
A1103: C.001-ARP.0088.01.2024.GOV.CISAM.PE | B1103: HOSPITAL REGIONAL DO AGRESTE DR.WALDEMIRO FERREIRA | C1103: Consumo | D1103: ARP.0088.01.2024.GOV.CISAM.PE | E1103: REGISTRO DE PREÇOS PARA FORNECIMENTO EVENTUAL DE MATERIAIS MÉDICO-HOSPITALARES (DIVERSOS), VISANDO ATENDER AS NECESSIDADES DO CISAM/UPE E DEMAIS ÓRGÃOS PARTICIPANTES . | F1103: 45644 | G1103: Autorizada Sucesso
A1104: C.002-ARP.0089.01.2024.GOV.CISAM.PE | B1104: HOSPITAL REGIONAL DO AGRESTE DR.WALDEMIRO FERREIRA | C1104: Consumo | D1104: ARP.0089.01.2024.GOV.CISAM.PE | E1104: REGISTRO DE PREÇOS PARA O FORNECIMENTO EVENTUAL DE MATERIAIS MÉDICO-HOSPITALARES (CAMPO OPERATÓRIO, COMPRESSA DE GAZE E FRALDA DESCARTÁVEL), VISANDO ATENDER AS NECESSIDADES DO CISAM/UPE E DEMAIS ÓRGÃOS PARTICIPANTES | F1104: 45644 | G1104: Cancelada
A1105: C.001-ARP.0089.01.2024.GOV.CISAM.PE | B1105: HOSPITAL REGIONAL DO AGRESTE DR.WALDEMIRO FERREIRA | C1105: Consumo | D1105: ARP.0089.01.2024.GOV.CISAM.PE | E1105: REGISTRO DE PREÇOS PARA O FORNECIMENTO EVENTUAL DE MATERIAIS MÉDICO-HOSPITALARES (CAMPO OPERATÓRIO, COMPRESSA DE GAZE E FRALDA DESCARTÁVEL), VISANDO ATENDER AS NECESSIDADES DO CISAM/UPE E DEMAIS ÓRGÃOS PARTICIPANTES | F1105: 45644 | G1105: Cancelada
A1106: C.003-ARP.0087.00.2024.GOV.CISAM.PE | B1106: HOSPITAL REGIONAL DO AGRESTE DR.WALDEMIRO FERREIRA | C1106: Consumo | D1106: ARP.0087.00.2024.GOV.CISAM.PE | E1106: REGISTRO DE PREÇOS PARA FORNECIMENTO EVENTUAL DE MATERIAIS MÉDICO-HOSPITALARES (DIVERSOS), VISANDO ATENDER AS NECESSIDADES DO CISAM/UPE E DEMAIS ÓRGÃO PARTICIPANTES. | F1106: 45644 | G1106: Cancelada
... A1464: C.014-ARPC.0004.00.2023.GOV.SAD.PE | B1464: HOSPITAL REGIONAL DO AGRESTE DR.WALDEMIRO FERREIRA | C1464: Consumo | D1464: ARPC.0004.00.2023.GOV.SAD.PE | E1464: Formação de Registro de Preços para o fornecimento eventual de material de expediente (papel), visando atender as necessidades dos órgãos da Administração Direta, Autarquias e Fundações Públicas integrantes do Poder Executivo do Estado de Pernambuco. | F1464: 45006 | G1464: Autorizada Sucesso

Sheet ENCAMINHADA PARA ORÇAMENTO
A1: Número da Solicitação | B1: Orgão | C1: Situação do Processo
A2: A.001-ARP.0059.02.2025.GOV.FES-PE.PE | B2: FES-PE | C2: (vazio)
A3: C.001-ARP.0048.00.2025.GOV.FES-PE.PE | B3: FES-PE | C3: (vazio)
A4: (vazio) | B4: #N/A | C4: (vazio)
